Workbook

Sheet Cover
B2: FUNGI LABS MULTI-SPECIALITY HOSPITAL
B3: 100-Bed Greenfield Project | Nashik, Maharashtra | Tier-2 India
B5: MASTER FINANCIAL MODEL
B6: Feasibility · DPR · Financial Projections · Viability & Bankability
B8: Project | C8: Fungi Labs Multi-Speciality Hospital Pvt. Ltd.
B9: Facility | C9: 100 operational beds, balanced multi-specialty
B10: Location | C10: Nashik, Maharashtra (Tier-2), catchment ~21 lakh
B11: Land & building | C11: Greenfield — 2.0 acres freehold, 1,05,000 sq ft built-up
B12: Specialties | C12: Gen. Medicine · Gen. Surgery · Orthopaedics · Cardiology (cath lab) ·
C13: OBG · Paediatrics & NICU · Nephrology & Dialysis · Critical Care
B14: Project cost | C14: Rs 110.78 Cr (Rs 11,078 Lakh)
B15: Cost per bed | C15: Rs 1.11 Cr
B16: Funding — base case | C16: 70:30 Debt:Equity — Term loan Rs 77.54 Cr / Promoter equity Rs 33.23 Cr
B17: Promoter support facility | C17: Rs 17.80 Cr (DSRA + start-up deficit funding)
B18: Model horizon | C18: 10 operating years — FY2029 to FY2038
B19: Currency & units | C19: Indian Rupees. All amounts in Rs Lakh unless stated. 100 Lakh = 1 Crore.
B20: Model date | C20: 8 August 2026
B22: HEADLINE OUTPUTS — BASE CASE
B23: Revenue — Year 1 / Year 5 / Year 10 | C23: Rs 30.1 Cr / Rs 104.4 Cr / Rs 158.3 Cr
B24: EBITDA — Year 5 / Year 10 | C24: Rs 24.8 Cr (23.7%) / Rs 42.1 Cr (26.6%)
B25: EBITDA breakeven / PAT breakeven | C25: Year 2 / Year 4
B26: Minimum / Average DSCR (post-moratorium) | C26: 1.46x / 1.66x — covenant breaches: 0
B27: Project IRR / NPV @ 12.5% WACC | C27: 22.13% / Rs 123.2 Cr
B28: Equity IRR / Money multiple (10-yr hold) | C28: 26.91% / 12.32x
B29: Break-even occupancy (Year 5) — accounting / cash | C29: 45.2% / 61.1%
B32: COLOUR CONVENTION
B33: Blue text on yellow fill | C33: Hardcoded input or scenario lever — EDIT THESE
B34: Black text | C34: Formula calculated on this sheet — do not overwrite
B35: Green text | C35: Link to another sheet — do not overwrite
B37: SHEET INDEX
B38: Control Panel | C38: Scenario, funding-structure and payer-mix switches. START HERE.
B39: Assumptions | C39: Every operating, cost, working-capital, tax and valuation assumption
B40: Capex & Funding | C40: Cost of project, IDC closed-form solution, means of finance
B41: Depreciation | C41: Block-wise book depreciation (SLM) and income-tax WDV depreciation
B42: Revenue Build | C42: Bed-days, ARPOB, IPD/OPD/diagnostics/pharmacy/dialysis build-up
B43: Manpower | C43: Cadre-wise headcount and cost ramp
B44: Operating Costs | C44: Full opex build; variable vs fixed classification
B45: Working Capital | C45: Debtor days driven by payer mix; inventory, creditors, net WC
B46: Repayment Schedule | C46: Quarterly term-loan repayment ladder — 28 instalments
B47: Debt Schedule | C47: Annual term loan + working-capital facility, interest, closing balance
B48: P&L | C48: Profit & loss with loss carry-forward and s.115BAA tax
B49: Cash Flow | C49: Operating / investing / financing; FCFF and FCFE
... B63: Charts | C63: Revenue & EBITDA bridge, DSCR profile, cash flow, sensitivity charts
B65: IMPORTANT — READ BEFORE USE
B66: This is an illustrative case-study model built for teaching purposes. 'Fungi Labs' is a fictitious entity.
B67: Sector benchmarks (occupancy, ARPOB growth, operating margin) are drawn from published ICRA research on the
B68: Indian hospital industry; see the Assumptions sheet for the source note against each figure. All other inputs are
B69: reasoned estimates, not audited or independently verified data. Nothing here is investment, tax or legal advice.
B70: Sensitivity grids, the tornado analysis and the Monte Carlo results are produced by re-running the full model at
B71: each parameter combination in Python (see fl_analytics.py); they are pasted as values because Excel cannot
B72: recalculate them without VBA. Every other number in this workbook is a live formula.

Sheet Control Panel
A1: CONTROL PANEL — MODEL SWITCHES
A2: Change the three switches below and the whole workbook recalculates. Edit ONLY the blue cells on yellow fill.
A5: Scenario (1 = Base, 2 = Optimistic, 3 = Pessimistic, 4 = Lender Stress) | B5: 1
A6: Active scenario | B6: =INDEX($C$16:$F$16,1,$B$5) -> Base
A8: Funding structure (1 = 70:30, 2 = 65:35, 3 = 60:40 with PE) | B8: 1
A9: Active funding structure | B9: =INDEX($C$32:$E$32,1,$B$8) -> Opt 1: 70:30
A11: Payer mix (1 = Blended, 2 = Government-heavy, 3 = Cash-premium) | B11: 1
A12: Active payer mix | B12: =INDEX($B$40:$D$40,1,$B$11) -> Blended
A15: SCENARIO DRIVER TABLE
A16: Driver | B16: Unit | C16: Base | D16: Optimistic | E16: Pessimistic | F16: Lender Stress | G16: ACTIVE
A17: Peak occupancy (stabilised) | B17: % | C17: 0.72 | D17: 0.78 | E17: 0.64 | F17: 0.58 | G17: =INDEX($C17:$F17,1,$B$5) -> 0.72 | I17: ICRA: sector 62-64%; well-run tier-2 65-75%
A18: Occupancy ramp multiplier | B18: x | C18: 1 | D18: 1.1 | E18: 0.88 | F18: 0.78 | G18: =INDEX($C18:$F18,1,$B$5) -> 1 | I18: Speed of the ramp toward peak occupancy
A19: ARPOB Year 1 (gross tariff) | B19: Rs/bed-day | C19: 26500 | D19: 28500 | E19: 24000 | F19: 22500 | G19: =INDEX($C19:$F19,1,$B$5) -> 26500 | I19: Gross of payer discount; net = gross x realisation index
A20: ARPOB escalation p.a. | B20: % | C20: 0.075 | D20: 0.08 | E20: 0.055 | F20: 0.045 | G20: =INDEX($C20:$F20,1,$B$5) -> 0.075 | I20: ICRA guides 6-8% p.a. for the sector
A21: OPD footfall multiplier | B21: x | C21: 1 | D21: 1.12 | E21: 0.88 | F21: 0.8 | G21: =INDEX($C21:$F21,1,$B$5) -> 1
A22: Consumables % of revenue | B22: % | C22: 0.23 | D22: 0.218 | E22: 0.242 | F22: 0.25 | G22: =INDEX($C22:$F22,1,$B$5) -> 0.23 | I22: Drugs, implants, surgical disposables, lab reagents
A23: Salary escalation p.a. | B23: % | C23: 0.08 | D23: 0.075 | E23: 0.09 | F23: 0.1 | G23: =INDEX($C23:$F23,1,$B$5) -> 0.08
A24: Consultant payout % of IPD+OPD | B24: % | C24: 0.11 | D24: 0.105 | E24: 0.12 | F24: 0.125 | G24: =INDEX($C24:$F24,1,$B$5) -> 0.11 | I24: Fee-for-service visiting consultants only; full-time consultants sit in salaries
A25: Capex overrun | B25: % | C25: 0 | D25: -0.03 | E25: 0.06 | F25: 0.12 | G25: =INDEX($C25:$F25,1,$B$5) -> 0 | I25: Applied to everything except land
A26: Base interest rate | B26: % | C26: 0.1075 | D26: 0.1 | E26: 0.115 | F26: 0.125 | G26: =INDEX($C26:$F26,1,$B$5) -> 0.1075 | I26: Market range for hospital term loans is 9.5-12.5%
A27: Construction delay | B27: months | C27: 0 | D27: 0 | E27: 3 | F27: 6 | G27: =INDEX($C27:$F27,1,$B$5) -> 0 | I27: Extends IDC and defers first revenue
A28: Exit EV/EBITDA multiple | B28: x | C28: 13 | D28: 15 | E28: 11 | F28: 9 | G28: =INDEX($C28:$F28,1,$B$5) -> 13 | I28: Unlisted tier-2 asset; listed Indian hospitals trade far higher
A31: FUNDING STRUCTURE TABLE
A32: Parameter | B32: Unit | C32: Opt 1: 70:30 | D32: Opt 2: 65:35 | E32: Opt 3: 60:40 + PE | G32: ACTIVE
A33: Term debt as % of cost of project | B33: % | C33: 0.7 | D33: 0.65 | E33: 0.6 | G33: =INDEX($C33:$E33,1,$B$8) -> 0.7 | I33: Cost of project excludes the promoter support facility
A34: Promoter support facility (DSRA + deficit) | B34: Rs Lakh | C34: 1780 | D34: 1587 | E34: 1450 | G34: =INDEX($C34:$E34,1,$B$8) -> 1780 | I34: Solved so the minimum cash balance stays >= Rs 150 L in the base case
A35: Interest rate adjustment | B35: % | C35: 0 | D35: -0.0015 | E35: -0.0025 | G35: =INDEX($C35:$E35,1,$B$8) -> 0 | I35: Lower leverage earns finer pricing
A36: Effective interest rate applied in the model | G36: =$G$26+$G$35 -> 0.1075
A39: PAYER MIX TABLE
A40: Payer segment | B40: Blended | C40: Govt-heavy | D40: Cash-premium | E40: ACTIVE mix | F40: Realisation vs list | G40: Debtor days
A41: Cash / self-pay | B41: 0.4 | C41: 0.3 | D41: 0.6 | E41: =INDEX($B41:$D41,1,$B$11) -> 0.4 | F41: 1 | G41: 3
A42: Private insurance / TPA | B42: 0.35 | C42: 0.25 | D42: 0.35 | E42: =INDEX($B42:$D42,1,$B$11) -> 0.35 | F42: 0.94 | G42: 55
A43: Government schemes (PMJAY / CGHS / ESI) | B43: 0.25 | C43: 0.45 | D43: 0.05 | E43: =INDEX($B43:$D43,1,$B$11) -> 0.25 | F43: 0.72 | G43: 110
A44: Total | B44: =SUM(B41:B43) -> 1 | C44: =SUM(C41:C43) -> 1 | D44: =SUM(D41:D43) -> 1 | E44: =SUM(E41:E43) -> 1
A45: Integrity check — active mix must total 100% | E45: =IF(ABS($E$44-1)<0.0001,"OK","ERROR - mix does not sum to 100%") -> OK
A47: Weighted realisation index | E47: =SUMPRODUCT($E$41:$E$43,$F$41:$F$43) -> 0.909 | I47: Net ARPOB = gross ARPOB x this index
A48: Weighted debtor days | E48: =SUMPRODUCT($E$41:$E$43,$G$41:$G$43) -> 47.95 | I48: Drives receivables on the Working Capital sheet
A51: HOW THIS MODEL IS WIRED
A52: Control Panel -> Assumptions -> Revenue Build / Manpower / Operating Costs -> P&L
A53: Capex & Funding -> Depreciation (into P&L) and Debt Schedule (interest into P&L)
A54: P&L + Working Capital + Debt -> Cash Flow -> Balance Sheet (with a balance check)
A55: Cash Flow -> DSCR & Covenants -> Returns & IRR -> Valuation
A57: Every downstream sheet reads the ACTIVE column (G) of the tables above. Nothing is hardcoded twice.

Sheet Assumptions
A1: ASSUMPTIONS
A2: All amounts in Rs Lakh unless the unit column says otherwise. Blue on yellow = input. Source notes in column E.
A4: 1. CAPACITY & PHYSICAL PARAMETERS
A5: Operational beds | B5: beds | C5: 100 | E5: Licensed and commissioned bed strength
A6: Built-up area | B6: sq ft | C6: 105000 | E6: 1,050 sq ft per bed — NABH-compliant planning norm
A7: Land area | B7: acres | C7: 2 | E7: Allows FSI headroom for a Phase-2 vertical expansion
A8: Number of operation theatres | B8: nos | C8: 4 | E8: 3 major + 1 minor/emergency
A9: Critical care beds (ICU/CCU/NICU/HDU) | B9: beds | C9: 33 | E9: 33% of total — appropriate for a tier-2 tertiary-lite facility
A10: Dialysis stations | B10: nos | C10: 10
A11: Construction period | B11: months | C11: 18 | E11: From financial closure to commercial operation date (COD)
A12: Construction delay (from scenario) | B12: months | C12: ='Control Panel'!$G$27 -> 0 | E12: Linked to the Control Panel
A13: Effective construction period | B13: months | C13: =C11+C12 -> 18
A15: 2. BED CONFIGURATION
A16: Bed category | B16: Beds | C16: % of total
A17: General ward (multi-bedded) | B17: 34 | C17: =IFERROR(B17/$B$25,0) -> 0.34
A18: Semi-private (twin sharing) | B18: 18 | C18: =IFERROR(B18/$B$25,0) -> 0.18
A19: Private / deluxe room | B19: 12 | C19: =IFERROR(B19/$B$25,0) -> 0.12
A20: ICU — medical & surgical | B20: 14 | C20: =IFERROR(B20/$B$25,0) -> 0.14
A21: CCU — coronary care | B21: 6 | C21: =IFERROR(B21/$B$25,0) -> 0.06
A22: NICU / PICU | B22: 8 | C22: =IFERROR(B22/$B$25,0) -> 0.08
A23: HDU / step-down | B23: 5 | C23: =IFERROR(B23/$B$25,0) -> 0.05
A24: Isolation / negative pressure | B24: 3 | C24: =IFERROR(B24/$B$25,0) -> 0.03
A25: Total beds | B25: =SUM(B17:B24) -> 100 | C25: =SUM(C17:C24) -> 1
A26: Integrity check — bed config must equal operational beds | B26: =IF(B25=C5,"OK","ERROR") -> OK
A28: 3. OCCUPANCY & CASE-MIX DRIVERS
A29: Peak (stabilised) occupancy | B29: % | C29: ='Control Panel'!$G$17 -> 0.72 | E29: ICRA FY2026: sector occupancy 62-64%; well-run tier-2 65-75%
A30: Occupancy ramp multiplier | B30: x | C30: ='Control Panel'!$G$18 -> 1 | E30: Scenario lever on the speed of the ramp
A31: ARPOB Year 1 — gross of payer discount | B31: Rs/bed-day | C31: ='Control Panel'!$G$19 -> 26500 | E31: Average revenue per occupied bed-day at list tariff
A32: ARPOB escalation p.a. | B32: % | C32: ='Control Panel'!$G$20 -> 0.075 | E32: ICRA guides 6-8% p.a.; driven by tariff revision plus case-mix enrichment
A33: Weighted realisation index (payer mix) | B33: index | C33: ='Control Panel'!$E$47 -> 0.909 | E33: Net ARPOB = gross ARPOB x this index
A34: Average length of stay (ALOS) | B34: days | C34: 3.9 | E34: Used to derive admissions from bed-days
A36: Occupancy ramp profile — % of peak occupancy achieved
A37: Ramp factor | B37: Unit | C37: Year 1 | D37: Year 2 | E37: Year 3 | F37: Year 4 | G37: Year 5 | H37: Year 6 | I37: Year 7 | J37: Year 8 | K37: Year 9 | L37: Year 10
A38: Financial year | C38: FY2029 | D38: FY2030 | E38: FY2031 | F38: FY2032 | G38: FY2033 | H38: FY2034 | I38: FY2035 | J38: FY2036 | K38: FY2037 | L38: FY2038
A39: % of peak occupancy achieved | B39: % | C39: 0.38 | D39: 0.6 | E39: 0.78 | F39: 0.89 | G39: 0.97 | H39: 1 | I39: 1 | J39: 1 | K39: 1 | L39: 1 | N39: Blue inputs — the shape of the ramp is a management judgement
A40: Occupancy achieved | B40: % | C40: =MIN($C$29*C39*$C$30,0.92) -> 0.2736 | D40: =MIN($C$29*D39*$C$30,0.92) -> 0.432 | E40: =MIN($C$29*E39*$C$30,0.92) -> 0.5616 | F40: =MIN($C$29*F39*$C$30,0.92) -> 0.6408 | G40: =MIN($C$29*G39*$C$30,0.92) -> 0.6984 | H40: =MIN($C$29*H39*$C$30,0.92) -> 0.72 | I40: =MIN($C$29*I39*$C$30,0.92) -> 0.72 | J40: =MIN($C$29*J39*$C$30,0.92) -> 0.72 | ... L40: =MIN($C$29*L39*$C$30,0.92) -> 0.72 | N40: Capped at 92% — physical maximum with turnaround time
A42: 4. OUTPATIENT, DIAGNOSTICS, PHARMACY & DIALYSIS DRIVERS
A43: OPD footfall multiplier | B43: x | C43: ='Control Panel'!$G$21 -> 1
A44: OPD footfall Year 1 | B44: patients/day | C44: 100 | E44: Ramps per the profile below
A45: Net revenue per OPD visit — Year 1 | B45: Rs | C45: 700 | E45: Consultation + procedure charges retained
A46: Price escalation — OPD, diagnostics, pharmacy | B46: % | C46: 0.06
A47: Diagnostics conversion — Year 1 | B47: % of footfall | C47: 0.45 | E47: Share of OPD patients ordering lab or radiology
A48: Average diagnostics ticket — Year 1 | B48: Rs | C48: 950
A49: Pharmacy conversion — Year 1 | B49: % of footfall | C49: 0.55
A50: Average pharmacy ticket — Year 1 | B50: Rs | C50: 480
A51: Dialysis stations | B51: nos | C51: 10
A52: Shifts per day | B52: nos | C52: 3
A53: Operating days per year | B53: days | C53: 350
A54: Revenue per dialysis session — Year 1 | B54: Rs | C54: 1900 | E54: Net of PMJAY/insurance discounting on the blended mix
A56: Ramp / conversion profile | B56: Unit | C56: Year 1 | D56: Year 2 | E56: Year 3 | F56: Year 4 | G56: Year 5 | H56: Year 6 | I56: Year 7 | J56: Year 8 | K56: Year 9 | L56: Year 10
A57: Financial year | C57: FY2029 | D57: FY2030 | E57: FY2031 | F57: FY2032 | G57: FY2033 | H57: FY2034 | I57: FY2035 | J57: FY2036 | K57: FY2037 | L57: FY2038
A58: OPD footfall index (Year 1 = 1.00) | B58: x | C58: 1 | D58: 1.6 | E58: 2.2 | F58: 2.6 | G58: 2.9 | H58: 3.1 | I58: 3.25 | J58: 3.35 | K58: 3.45 | L58: 3.55
A59: Diagnostics conversion | B59: % | C59: 0.45 | D59: 0.47 | E59: 0.48 | F59: 0.49 | G59: 0.5 | H59: 0.5 | I59: 0.51 | J59: 0.51 | K59: 0.52 | L59: 0.52
A60: Pharmacy conversion | B60: % | C60: 0.55 | D60: 0.57 | E60: 0.58 | F60: 0.59 | G60: 0.6 | H60: 0.6 | I60: 0.61 | J60: 0.61 | K60: 0.62 | L60: 0.62
A61: Dialysis station utilisation | B61: % | C61: 0.3 | D61: 0.45 | E61: 0.6 | F61: 0.68 | G61: 0.75 | H61: 0.8 | I61: 0.82 | J61: 0.83 | K61: 0.84 | L61: 0.85
A62: Other income (health checks, ambulance, academics, rentals) | B62: Rs Lakh | C62: 40 | D62: 55 | E62: 70 | F62: 82 | G62: 95 | H62: 105 | I62: 115 | J62: 124 | K62: 133 | L62: 142
A64: 5. OPERATING COST DRIVERS
A65: Consultant payout — % of IPD + OPD revenue | B65: % | C65: ='Control Panel'!$G$24 -> 0.11 | E65: Fee-for-service visiting consultants. Full-time consultants sit in salaries.
A66: Consumables — % of total revenue | B66: % | C66: ='Control Panel'!$G$22 -> 0.23 | E66: Drugs, implants, surgical disposables, lab reagents, medical gases
A67: Salary cost — Year 1 (from the Manpower build) | B67: Rs Lakh | C67: 1493.9 | E67: Built bottom-up on the Manpower sheet from headcount x cost per head. Shown here for reference only — edit the cadre table on the Manpower sheet, not this cell.
A68: Salary escalation p.a. | B68: % | C68: ='Control Panel'!$G$23 -> 0.08 | E68: Nursing wage inflation is the binding constraint in Indian hospitals
A70: Semi-fixed cost lines | B70: Unit | C70: Year 1 | D70: Year 2 | E70: Year 3 | F70: Year 4 | G70: Year 5 | H70: Year 6 | I70: Year 7 | J70: Year 8 | K70: Year 9 | L70: Year 10
A71: Financial year | C71: FY2029 | D71: FY2030 | E71: FY2031 | F71: FY2032 | G71: FY2033 | H71: FY2034 | I71: FY2035 | J71: FY2036 | K71: FY2037 | L71: FY2038
A72: Power & fuel | B72: Rs Lakh | C72: 200 | D72: 250 | E72: 310 | F72: 380 | G72: 460 | H72: 500 | I72: 530 | J72: 560 | K72: 590 | L72: 620 | N72: Largely fixed — HVAC and medical gas run regardless of occupancy
A73: Outsourced services (housekeeping, security, laundry, catering, biomedical AMC) | B73: Rs Lakh | C73: 185 | D73: 215 | E73: 265 | F73: 300 | G73: 420 | H73: 445 | I73: 470 | J73: 495 | K73: 520 | L73: 545
A74: Repairs & maintenance | B74: Rs Lakh | C74: 120 | D74: 145 | E74: 190 | F74: 240 | G74: 300 | H74: 330 | I74: 355 | J74: 380 | K74: 405 | L74: 430
A75: Administrative & other overheads | B75: Rs Lakh | C75: 155 | D75: 180 | E75: 230 | F75: 300 | G75: 380 | H75: 410 | I75: 440 | J75: 470 | K75: 500 | L75: 530
A76: Marketing & business development | B76: Rs Lakh | C76: 170 | D76: 175 | E76: 180 | F76: 185 | G76: 190 | H76: 200 | I76: 210 | J76: 220 | K76: 230 | L76: 240 | N76: Front-loaded — brand-building spend in the launch years
A77: Insurance, rates & taxes, licences | B77: Rs Lakh | C77: 90 | D77: 100 | E77: 120 | F77: 140 | G77: 160 | H77: 172 | I77: 184 | J77: 196 | K77: 208 | L77: 220
A79: 6. WORKING CAPITAL
A80: Debtor days (weighted by payer mix) | B80: days | C80: ='Control Panel'!$E$48 -> 47.95 | E80: Cash 3d, insurance 55d, government schemes 110d
A81: Inventory days — on consumables cost | B81: days | C81: 25 | E81: Pharmacy, implants, reagents
A82: Creditor days — on consumables + outsourced | B82: days | C82: 45
A83: Other current assets — days of revenue | B83: days | C83: 12 | E83: Advances, deposits, prepaid expenses
A84: Other current liabilities — days of revenue | B84: days | C84: 18 | E84: Statutory dues, provisions, accruals
A85: Minimum cash balance to be maintained | B85: Rs Lakh | C85: 150
A87: 7. DEPRECIATION & AMORTISATION (BOOK — SLM, Companies Act 2013 Sch. II)
A88: Building & civil — SLM rate | B88: % | C88: 0.0334 | E88: 30-year useful life, 5% residual value
A89: Medical equipment — SLM rate | B89: % | C89: 0.075 | E89: 13-year useful life
A90: Non-medical equipment & utilities | B90: % | C90: 0.1 | E90: 10-year useful life
A91: Furniture & fixtures | B91: % | C91: 0.1 | E91: 10-year useful life
A92: IT, HIS & PACS | B92: % | C92: 0.1667 | E92: 6-year useful life
A93: Pre-operative expenses — amortisation period | B93: years | C93: 5
A94: Maintenance capex — % of revenue from Year 3 | B94: % | C94: 0.02
A95: Expansion capex — Year 3 (1.5T MRI) | B95: Rs Lakh | C95: 550 | E95: Deliberately deferred to Year 3 — the volumes do not justify it at launch
A97: 8. TAXATION
A98: Corporate tax rate | B98: % | C98: 0.25168 | E98: s.115BAA: 22% base + 10% surcharge + 4% health & education cess = 25.168%
A99: Business loss carry-forward | B99: years | C99: 8 | E99: s.72 — 8 assessment years. Unabsorbed depreciation carries forward indefinitely (s.32(2)).
A100: Income-tax depreciation — building (WDV) | B100: % | C100: 0.1 | E100: Not used in the P&L; shown for deferred-tax context
A101: Income-tax depreciation — plant & machinery (WDV) | B101: % | C101: 0.15
A102: Income-tax depreciation — computers (WDV) | B102: % | C102: 0.4
A104: 9. FINANCING
A105: Term debt as % of cost of project | B105: % | C105: ='Control Panel'!$G$33 -> 0.7
A106: Effective interest rate on term loan | B106: % | C106: ='Control Panel'!$G$36 -> 0.1075 | E106: Market range 9.5-12.5% p.a. for Indian hospital term loans
A107: Upfront processing fee | B107: % | C107: 0.01 | E107: Expensed against reserves on drawdown
A108: Principal moratorium after COD | B108: months | C108: 36 | E108: First instalment falls due at the start of operating Year 4, once the hospital has cleared cash break-even. Interest is serviced throughout. This is the single most important structuring decision in the deal.
A109: Repayment tenor after moratorium | B109: years | C109: 7 | E109: 28 quarterly instalments
A110: Door-to-door tenor | B110: years | C110: =ROUND(C13/12,1)+C108/12+C109 -> 11.5 | E110: Construction + moratorium + repayment
A111: Average debt drawdown factor during construction | B111: index | C111: 0.45 | E111: Average debt outstanding over the construction period, as a fraction of the final sanction (S-curve drawdown). Used in the closed-form IDC solution.
A112: Promoter support facility (DSRA + start-up deficit) | B112: Rs Lakh | C112: ='Control Panel'!$G$34 -> 1780 | E112: Ring-fenced DSRA plus funding of the Year 1-2 operating deficit
...

Sheet Capex & Funding
A1: COST OF PROJECT & MEANS OF FINANCE
A2: All amounts in Rs Lakh. IDC is solved in closed form to avoid the classic circular reference.
A4: A. COST OF PROJECT
A5: Cost head | B5: Basis | C5: Amount | D5: % of total
A6: Land — 2.0 acres freehold | B6: 2.0 ac @ Rs 550 L/acre | C6: =2*550 -> 1100 | D6: =IFERROR(C6/$C$25,0) -> 0.09930031
A7: Site development, boundary wall & approach | B7: Lump sum | C7: =150*(1+'Control Panel'!$G$25) -> 150 | D7: =IFERROR(C7/$C$25,0) -> 0.013540951
A8: Civil construction | B8: 1,05,000 sq ft @ Rs 2,700/sq ft | C8: =Assumptions!$C$6*2700/100000*(1+'Control Panel'!$G$25) -> 2835 | D8: =IFERROR(C8/$C$25,0) -> 0.25592398
A9: MEP & building services | B9: @ Rs 950/sq ft — HVAC, electrical, plumbing, medical gas, fire | C9: =Assumptions!$C$6*950/100000*(1+'Control Panel'!$G$25) -> 997.5 | D9: =IFERROR(C9/$C$25,0) -> 0.090047327
A10: Interiors & finishes | B10: @ Rs 520/sq ft | C10: =Assumptions!$C$6*520/100000*(1+'Control Panel'!$G$25) -> 546 | D10: =IFERROR(C10/$C$25,0) -> 0.049289063
A11: Medical equipment | B11: See equipment schedule below | C11: =2650*(1+'Control Panel'!$G$25) -> 2650 | D11: =IFERROR(C11/$C$25,0) -> 0.23922347
A12: Non-medical equipment & utilities | B12: DG sets, lifts, CSSD, laundry, kitchen, STP | C12: =620*(1+'Control Panel'!$G$25) -> 620 | D12: =IFERROR(C12/$C$25,0) -> 0.055969266
A13: Furniture & fixtures | B13: Beds, cots, cabinets, workstations | C13: =300*(1+'Control Panel'!$G$25) -> 300 | D13: =IFERROR(C13/$C$25,0) -> 0.027081903
A14: IT, HIS & PACS | B14: HIS/HMIS licence, servers, network, PACS, CCTV | C14: =185*(1+'Control Panel'!$G$25) -> 185 | D14: =IFERROR(C14/$C$25,0) -> 0.016700507
A15: Pre-operative expenses | B15: Licences, consultancy, recruitment, pre-launch marketing, trial run | C15: =450*(1+'Control Panel'!$G$25) -> 450 | D15: =IFERROR(C15/$C$25,0) -> 0.040622854
A16: Contingency @ 4% | B16: On hard cost excl. land and pre-operative | C16: =0.04*(SUM(C7:C14)) -> 331.34 | D16: =IFERROR(C16/$C$25,0) -> 0.029911059
A17: Margin money for working capital | B17: Promoter's contribution to working capital | C17: 350 | D17: =IFERROR(C17/$C$25,0) -> 0.031595553
A18: Hard cost (before IDC) | C18: =SUM(C6:C17) -> 10514.84 | D18: =IFERROR(C18/$C$25,0) -> 0.94920625
D19: =IFERROR(C19/$C$25,0) -> 0
A20: Interest during construction (IDC) — closed-form solution | D20: =IFERROR(C20/$C$25,0) -> 0
A21: IDC depends on the debt, the debt depends on the project cost, and the project cost includes IDC. | D21: =IFERROR(C21/$C$25,0) -> 0
A22: Rather than iterate, solve algebraically: IDC = k x HardCost / (1 - k), where k = d x r x (m/12) x f | D22: =IFERROR(C22/$C$25,0) -> 0
A23: k = debt% x rate x (months/12) x drawdown factor | C23: =Assumptions!$C$105*Assumptions!$C$106*(Assumptions!$C$13/12)*Assumptions!$C$111 -> 0.05079375 | D23: =IFERROR(C23/$C$25,0) -> 4.5853047e-06
A24: Interest during construction (IDC) | B24: Capitalised into the asset blocks | C24: =C23*C18/(1-C23) -> 562.66818 | D24: =IFERROR(C24/$C$25,0) -> 0.05079375
A25: TOTAL COST OF PROJECT | C25: =C18+C24 -> 11077.508 | D25: =C25/$C$25 -> 1 | F25: This is the figure the lender appraises and lends against.
A27: Cost per operational bed | C27: =C25/Assumptions!$C$5 -> 110.77508 | F27: Benchmark: Rs 70-100 L/bed ex-land for a metro build; this project carries a cath lab, CT, 4 OTs and 33 critical-care beds.
A28: Cost per bed excluding land | C28: =(C25-C6)/Assumptions!$C$5 -> 99.775082
A30: B. MEANS OF FINANCE
A31: Source | B31: Basis | C31: Amount | D31: % of cost of project
A32: Term loan from bank / FI | B32: Per the active funding structure | C32: =C25*Assumptions!$C$105 -> 7754.2557 | D32: =C32/$C$25 -> 0.7
A33: Promoter equity (incl. land contributed in kind) | C33: =C25-C32 -> 3323.2525 | D33: =C33/$C$25 -> 0.3
A34: Total means of finance — cost of project | C34: =C32+C33 -> 11077.508 | D34: =C34/$C$25 -> 1
A35: Integrity check — means of finance must equal cost of project | C35: =IF(ABS(C34-C25)<0.01,"OK","ERROR") -> OK
A37: Additional promoter commitment — outside the cost of project
A38: Promoter support facility (DSRA + start-up operating deficit) | B38: Unsecured subordinated promoter loan / equity | C38: =Assumptions!$C$112 -> 1780 | F38: A greenfield hospital loses money for roughly two years. Banks do not lend against operating losses, so the promoter must commit this separately. Sized so the minimum cash balance stays positive.
A39: TOTAL FUNDING REQUIREMENT | C39: =C34+C38 -> 12857.508
A40: Term debt as % of TOTAL funding requirement | C40: =C32/C39 -> 0.60309164 | F40: Headline gearing is 70:30 on the cost of project, but only ~60:40 once the promoter's cash-flow support is counted. Both views matter — quote the first to a lender, the second to yourself.
A41: Total promoter contribution | C41: =C33+C38 -> 5103.2525 | D41: =C41/C39 -> 0.39690836
A42: Upfront processing fee on term loan | C42: =C32*Assumptions!$C$107 -> 77.542557
A44: C. MEDICAL EQUIPMENT SCHEDULE
A45: Equipment | B45: Qty | C45: Rs Lakh | D45: Note
A46: Cardiac catheterisation laboratory (single plane) | B46: 1 | C46: 650 | D46: Anchor for the cardiology programme
A47: CT scanner — 128 slice | B47: 1 | C47: 420
A48: Modular operation theatres — equipment for 4 OTs | B48: 4 | C48: 420 | D48: Tables, lights, anaesthesia, electrosurgery
A49: ICU / CCU / NICU equipment | B49: 33 | C49: 380 | D49: Ventilators, monitors, infusion pumps, warmers
A50: Laparoscopy & endoscopy towers | B50: 3 | C50: 175
A51: Ultrasound, echocardiography, colour Doppler | B51: 4 | C51: 130
A52: Digital radiography & C-arm | B52: 3 | C52: 115
A53: Clinical laboratory — biochemistry, haematology, microbiology | B53: 1 | C53: 160 | D53: Fully automated analysers
A54: Dialysis machines & RO plant | B54: 10 | C54: 85
A55: Cath lab & OT support, CSSD instruments | B55: 1 | C55: 65
A56: Physiotherapy, audiometry, ophthalmology, ENT | B56: 1 | C56: 50
A57: Total medical equipment (before scenario overrun) | C57: =SUM(C46:C56) -> 2650
A58: Deferred to Year 3 — MRI 1.5T | C58: =Assumptions!$C$95 -> 550 | D58: Held back until IPD volumes justify it — a real capital-discipline decision
A60: D. DEPRECIABLE ASSET BLOCKS
A61: Contingency and IDC are allocated pro-rata across the depreciable blocks.
A62: Allocation base (depreciable hard cost, excl. land and pre-operative) | C62: =SUM(C7:C14) -> 8283.5
A63: Uplift factor for contingency + IDC | C63: =(C16+C24)/C62 -> 0.10792638
A64: Block | B64: Gross before uplift | C64: Gross block | D64: SLM rate
A65: Building, civil, MEP & interiors | B65: =C7+C8+C9+C10 -> 4528.5 | C65: =B65*(1+$C$63) -> 5017.2446 | D65: =Assumptions!$C$88 -> 0.0334
A66: Medical equipment | B66: =C11 -> 2650 | C66: =B66*(1+$C$63) -> 2936.0049 | D66: =Assumptions!$C$89 -> 0.075
A67: Non-medical equipment & utilities | B67: =C12 -> 620 | C67: =B67*(1+$C$63) -> 686.91436 | D67: =Assumptions!$C$90 -> 0.1
A68: Furniture & fixtures | B68: =C13 -> 300 | C68: =B68*(1+$C$63) -> 332.37791 | D68: =Assumptions!$C$91 -> 0.1
A69: IT, HIS & PACS | B69: =C14 -> 185 | C69: =B69*(1+$C$63) -> 204.96638 | D69: =Assumptions!$C$92 -> 0.1667
A70: Pre-operative expenses (amortised) | B70: =C15 -> 450 | C70: =B70 -> 450 | D70: =1/Assumptions!$C$93 -> 0.2
A71: Land (not depreciated) | B71: =C6 -> 1100 | C71: =B71 -> 1100 | D71: 0
A72: Total gross block | C72: =SUM(C65:C71) -> 10727.508
A73: Check — gross block + margin money must equal cost of project | C73: =IF(ABS(C72+C17-C25)<0.01,"OK","ERROR") -> OK

Sheet Depreciation
A1: DEPRECIATION & AMORTISATION SCHEDULE
A2: Book depreciation on the straight-line method (Companies Act 2013, Schedule II). Rs Lakh.
A4: Particulars | B4: Basis | C4: Year 1 | D4: Year 2 | E4: Year 3 | F4: Year 4 | G4: Year 5 | H4: Year 6 | I4: Year 7 | J4: Year 8 | K4: Year 9 | L4: Year 10
A5: Financial year | C5: FY2029 | D5: FY2030 | E5: FY2031 | F5: FY2032 | G5: FY2033 | H5: FY2034 | I5: FY2035 | J5: FY2036 | K5: FY2037 | L5: FY2038
A6: Maintenance capex incurred in the year | B6: Rs Lakh | C6: =IF(1>=3,Assumptions!$C$94*'Revenue Build'!C$43,0) -> 0 | D6: =IF(2>=3,Assumptions!$C$94*'Revenue Build'!D$43,0) -> 0 | E6: =IF(3>=3,Assumptions!$C$94*'Revenue Build'!E$43,0) -> 144.09758 | F6: =IF(4>=3,Assumptions!$C$94*'Revenue Build'!F$43,0) -> 177.60471 | G6: =IF(5>=3,Assumptions!$C$94*'Revenue Build'!G$43,0) -> 208.78917 | H6: =IF(6>=3,Assumptions!$C$94*'Revenue Build'!H$43,0) -> 232.44099 | I6: =IF(7>=3,Assumptions!$C$94*'Revenue Build'!I$43,0) -> 252.05481 | J6: =IF(8>=3,Assumptions!$C$94*'Revenue Build'!J$43,0) -> 271.83259 | K6: =IF(9>=3,Assumptions!$C$94*'Revenue Build'!K$43,0) -> 293.68097 | L6: =IF(10>=3,Assumptions!$C$94*'Revenue Build'!L$43,0) -> 316.61633
A7: Expansion capex — MRI (Year 3) | B7: Rs Lakh | C7: =0 -> 0 | D7: =0 -> 0 | E7: =Assumptions!$C$95 -> 550 | F7: =0 -> 0 | G7: =0 -> 0 | H7: =0 -> 0 | I7: =0 -> 0 | J7: =0 -> 0 | K7: =0 -> 0 | L7: =0 -> 0
A8: Total capex in the year | B8: Rs Lakh | C8: =C6+C7 -> 0 | D8: =D6+D7 -> 0 | E8: =E6+E7 -> 694.09758 | F8: =F6+F7 -> 177.60471 | G8: =G6+G7 -> 208.78917 | H8: =H6+H7 -> 232.44099 | I8: =I6+I7 -> 252.05481 | J8: =J6+J7 -> 271.83259 | ... L8: =L6+L7 -> 316.61633
A10: Depreciation by block
A11: Building, civil, MEP & interiors | B11: Rs Lakh | C11: ='Capex & Funding'!$C$65*'Capex & Funding'!$D$65 -> 167.57597 | D11: ='Capex & Funding'!$C$65*'Capex & Funding'!$D$65 -> 167.57597 | E11: ='Capex & Funding'!$C$65*'Capex & Funding'!$D$65 -> 167.57597 | F11: ='Capex & Funding'!$C$65*'Capex & Funding'!$D$65 -> 167.57597 | G11: ='Capex & Funding'!$C$65*'Capex & Funding'!$D$65 -> 167.57597 | H11: ='Capex & Funding'!$C$65*'Capex & Funding'!$D$65 -> 167.57597 | I11: ='Capex & Funding'!$C$65*'Capex & Funding'!$D$65 -> 167.57597 | J11: ='Capex & Funding'!$C$65*'Capex & Funding'!$D$65 -> 167.57597 | ... L11: ='Capex & Funding'!$C$65*'Capex & Funding'!$D$65 -> 167.57597
A12: Medical equipment (incl. MRI from Year 3) | B12: Rs Lakh | C12: =('Capex & Funding'!$C$66)*'Capex & Funding'!$D$66 -> 220.20037 | D12: =('Capex & Funding'!$C$66)*'Capex & Funding'!$D$66 -> 220.20037 | E12: =('Capex & Funding'!$C$66+Assumptions!$C$95)*'Capex & Funding'!$D$66 -> 261.45037 | F12: =('Capex & Funding'!$C$66+Assumptions!$C$95)*'Capex & Funding'!$D$66 -> 261.45037 | G12: =('Capex & Funding'!$C$66+Assumptions!$C$95)*'Capex & Funding'!$D$66 -> 261.45037 | H12: =('Capex & Funding'!$C$66+Assumptions!$C$95)*'Capex & Funding'!$D$66 -> 261.45037 | I12: =('Capex & Funding'!$C$66+Assumptions!$C$95)*'Capex & Funding'!$D$66 -> 261.45037 | J12: =('Capex & Funding'!$C$66+Assumptions!$C$95)*'Capex & Funding'!$D$66 -> 261.45037 | K12: =('Capex & Funding'!$C$66+Assumptions!$C$95)*'Capex & Funding'!$D$66 -> 261.45037 | L12: =('Capex & Funding'!$C$66+Assumptions!$C$95)*'Capex & Funding'!$D$66 -> 261.45037
A13: Non-medical equipment & utilities | B13: Rs Lakh | C13: ='Capex & Funding'!$C$67*'Capex & Funding'!$D$67 -> 68.691436 | D13: ='Capex & Funding'!$C$67*'Capex & Funding'!$D$67 -> 68.691436 | E13: ='Capex & Funding'!$C$67*'Capex & Funding'!$D$67 -> 68.691436 | F13: ='Capex & Funding'!$C$67*'Capex & Funding'!$D$67 -> 68.691436 | G13: ='Capex & Funding'!$C$67*'Capex & Funding'!$D$67 -> 68.691436 | H13: ='Capex & Funding'!$C$67*'Capex & Funding'!$D$67 -> 68.691436 | I13: ='Capex & Funding'!$C$67*'Capex & Funding'!$D$67 -> 68.691436 | J13: ='Capex & Funding'!$C$67*'Capex & Funding'!$D$67 -> 68.691436 | ... L13: ='Capex & Funding'!$C$67*'Capex & Funding'!$D$67 -> 68.691436
A14: Furniture & fixtures | B14: Rs Lakh | C14: ='Capex & Funding'!$C$68*'Capex & Funding'!$D$68 -> 33.237791 | D14: ='Capex & Funding'!$C$68*'Capex & Funding'!$D$68 -> 33.237791 | E14: ='Capex & Funding'!$C$68*'Capex & Funding'!$D$68 -> 33.237791 | F14: ='Capex & Funding'!$C$68*'Capex & Funding'!$D$68 -> 33.237791 | G14: ='Capex & Funding'!$C$68*'Capex & Funding'!$D$68 -> 33.237791 | H14: ='Capex & Funding'!$C$68*'Capex & Funding'!$D$68 -> 33.237791 | I14: ='Capex & Funding'!$C$68*'Capex & Funding'!$D$68 -> 33.237791 | J14: ='Capex & Funding'!$C$68*'Capex & Funding'!$D$68 -> 33.237791 | ... L14: ='Capex & Funding'!$C$68*'Capex & Funding'!$D$68 -> 33.237791
A15: IT, HIS & PACS (6-year life — fully written off after Year 6) | B15: Rs Lakh | C15: ='Capex & Funding'!$C$69*'Capex & Funding'!$D$69 -> 34.167896 | D15: ='Capex & Funding'!$C$69*'Capex & Funding'!$D$69 -> 34.167896 | E15: ='Capex & Funding'!$C$69*'Capex & Funding'!$D$69 -> 34.167896 | F15: ='Capex & Funding'!$C$69*'Capex & Funding'!$D$69 -> 34.167896 | G15: ='Capex & Funding'!$C$69*'Capex & Funding'!$D$69 -> 34.167896 | H15: ='Capex & Funding'!$C$69*'Capex & Funding'!$D$69 -> 34.167896 | I15: =0 -> 0 | J15: =0 -> 0 | K15: =0 -> 0 | L15: =0 -> 0
A16: Pre-operative expenses — amortisation | B16: Rs Lakh | C16: ='Capex & Funding'!$C$70/Assumptions!$C$93 -> 90 | D16: ='Capex & Funding'!$C$70/Assumptions!$C$93 -> 90 | E16: ='Capex & Funding'!$C$70/Assumptions!$C$93 -> 90 | F16: ='Capex & Funding'!$C$70/Assumptions!$C$93 -> 90 | G16: ='Capex & Funding'!$C$70/Assumptions!$C$93 -> 90 | H16: =0 -> 0 | I16: =0 -> 0 | J16: =0 -> 0 | K16: =0 -> 0 | L16: =0 -> 0
A17: Depreciation on maintenance capex @ 10% | B17: Rs Lakh | C17: =0 -> 0 | D17: =SUM($C$6:C6)*0.1 -> 0 | E17: =SUM($C$6:D6)*0.1 -> 0 | F17: =SUM($C$6:E6)*0.1 -> 14.409758 | G17: =SUM($C$6:F6)*0.1 -> 32.170229 | H17: =SUM($C$6:G6)*0.1 -> 53.049146 | I17: =SUM($C$6:H6)*0.1 -> 76.293246 | J17: =SUM($C$6:I6)*0.1 -> 101.49873 | K17: =SUM($C$6:J6)*0.1 -> 128.68199 | L17: =SUM($C$6:K6)*0.1 -> 158.05008
A18: TOTAL DEPRECIATION & AMORTISATION | B18: Rs Lakh | C18: =SUM(C11:C17) -> 613.87346 | D18: =SUM(D11:D17) -> 613.87346 | E18: =SUM(E11:E17) -> 655.12346 | F18: =SUM(F11:F17) -> 669.53322 | G18: =SUM(G11:G17) -> 687.29369 | H18: =SUM(H11:H17) -> 618.17261 | I18: =SUM(I11:I17) -> 607.24881 | J18: =SUM(J11:J17) -> 632.45429 | ... L18: =SUM(L11:L17) -> 689.00565
A20: Net block roll-forward
A21: Opening net block | B21: Rs Lakh | C21: ='Capex & Funding'!$C$72 -> 10727.508 | D21: =C22 -> 10113.635 | E21: =D22 -> 9499.7613 | F21: =E22 -> 9538.7354 | G21: =F22 -> 9046.8069 | H21: =G22 -> 8568.3024 | I21: =H22 -> 8182.5707 | J21: =I22 -> 7827.3767 | K21: =J22 -> 7466.755 | L21: =K22 -> 7100.7985
A22: Closing net block | B22: Rs Lakh | C22: =C21+C8-C18 -> 10113.635 | D22: =D21+D8-D18 -> 9499.7613 | E22: =E21+E8-E18 -> 9538.7354 | F22: =F21+F8-F18 -> 9046.8069 | G22: =G21+G8-G18 -> 8568.3024 | H22: =H21+H8-H18 -> 8182.5707 | I22: =I21+I8-I18 -> 7827.3767 | J22: =J21+J8-J18 -> 7466.755 | ... L22: =L21+L8-L18 -> 6728.4091
A24: Income-tax depreciation is computed on the written-down-value method at different rates (building 10%, plant &
A25: machinery 15%, computers 40%), which produces a timing difference and therefore a deferred tax liability. This model
A26: computes tax on book profit for simplicity and flags the difference below rather than maintaining a full DTA/DTL schedule.
A28: Income-tax depreciation (WDV) — for deferred-tax context only
A29: Opening WDV — plant & machinery block | B29: Rs Lakh | C29: ='Capex & Funding'!$C$66+'Capex & Funding'!$C$67+'Capex & Funding'!$C$68 -> 3955.2972 | D29: =C31 -> 3362.0026 | E29: =D31 -> 2857.7022 | F29: =E31 -> 2429.0469 | G29: =F31 -> 2064.6898 | H29: =G31 -> 1754.9864 | I29: =H31 -> 1491.7384 | J29: =I31 -> 1267.9777 | K29: =J31 -> 1077.781 | L29: =K31 -> 916.11385
A30: Income-tax depreciation @ 15% WDV | B30: Rs Lakh | C30: =C29*Assumptions!$C$101 -> 593.29458 | D30: =D29*Assumptions!$C$101 -> 504.30039 | E30: =E29*Assumptions!$C$101 -> 428.65533 | F30: =F29*Assumptions!$C$101 -> 364.35703 | G30: =G29*Assumptions!$C$101 -> 309.70348 | H30: =H29*Assumptions!$C$101 -> 263.24796 | I30: =I29*Assumptions!$C$101 -> 223.76076 | J30: =J29*Assumptions!$C$101 -> 190.19665 | ... L30: =L29*Assumptions!$C$101 -> 137.41708
A31: Closing WDV | B31: Rs Lakh | C31: =C29-C30 -> 3362.0026 | D31: =D29-D30 -> 2857.7022 | E31: =E29-E30 -> 2429.0469 | F31: =F29-F30 -> 2064.6898 | G31: =G29-G30 -> 1754.9864 | H31: =H29-H30 -> 1491.7384 | I31: =I29-I30 -> 1267.9777 | J31: =J29-J30 -> 1077.781 | ... L31: =L29-L30 -> 778.69678
A32: Timing difference vs book depreciation on the same blocks | B32: Rs Lakh | C32: =C30-(C12+C13+C14) -> 271.16498 | D32: =D30-(D12+D13+D14) -> 182.1708 | E32: =E30-(E12+E13+E14) -> 65.275737 | F32: =F30-(F12+F13+F14) -> 0.97743686 | G32: =G30-(G12+G13+G14) -> -53.676118 | H32: =H30-(H12+H13+H14) -> -100.13164 | I32: =I30-(I12+I13+I14) -> -139.61883 | J32: =J30-(J12+J13+J14) -> -173.18295 | ... L32: =L30-(L12+L13+L14) -> -225.96252 | N32: Positive = tax depreciation exceeds book, creating a DTL

Sheet Revenue Build
A1: REVENUE BUILD-UP
A2: Bottom-up: bed-days x ARPOB for inpatient, footfall x ticket for outpatient. Rs Lakh unless stated.
A4: Particulars | B4: Unit | C4: Year 1 | D4: Year 2 | E4: Year 3 | F4: Year 4 | G4: Year 5 | H4: Year 6 | I4: Year 7 | J4: Year 8 | K4: Year 9 | L4: Year 10
A5: Financial year | C5: FY2029 | D5: FY2030 | E5: FY2031 | F5: FY2032 | G5: FY2033 | H5: FY2034 | I5: FY2035 | J5: FY2036 | K5: FY2037 | L5: FY2038
A6: A. Inpatient department (IPD)
A7: Operational beds | B7: beds | C7: =Assumptions!$C$5 -> 100 | D7: =Assumptions!$C$5 -> 100 | E7: =Assumptions!$C$5 -> 100 | F7: =Assumptions!$C$5 -> 100 | G7: =Assumptions!$C$5 -> 100 | H7: =Assumptions!$C$5 -> 100 | I7: =Assumptions!$C$5 -> 100 | J7: =Assumptions!$C$5 -> 100 | ... L7: =Assumptions!$C$5 -> 100
A8: Occupancy | B8: % | C8: =Assumptions!C$40 -> 0.2736 | D8: =Assumptions!D$40 -> 0.432 | E8: =Assumptions!E$40 -> 0.5616 | F8: =Assumptions!F$40 -> 0.6408 | G8: =Assumptions!G$40 -> 0.6984 | H8: =Assumptions!H$40 -> 0.72 | I8: =Assumptions!I$40 -> 0.72 | J8: =Assumptions!J$40 -> 0.72 | ... L8: =Assumptions!L$40 -> 0.72
A9: Occupied bed-days | B9: bed-days | C9: =C7*365*C8 -> 9986.4 | D9: =D7*365*D8 -> 15768 | E9: =E7*365*E8 -> 20498.4 | F9: =F7*365*F8 -> 23389.2 | G9: =G7*365*G8 -> 25491.6 | H9: =H7*365*H8 -> 26280 | I9: =I7*365*I8 -> 26280 | J9: =J7*365*J8 -> 26280 | ... L9: =L7*365*L8 -> 26280
A10: Average length of stay | B10: days | C10: =Assumptions!$C$34 -> 3.9 | D10: =Assumptions!$C$34 -> 3.9 | E10: =Assumptions!$C$34 -> 3.9 | F10: =Assumptions!$C$34 -> 3.9 | G10: =Assumptions!$C$34 -> 3.9 | H10: =Assumptions!$C$34 -> 3.9 | I10: =Assumptions!$C$34 -> 3.9 | J10: =Assumptions!$C$34 -> 3.9 | ... L10: =Assumptions!$C$34 -> 3.9
A11: Admissions (discharges) | B11: patients | C11: =C9/C10 -> 2560.6154 | D11: =D9/D10 -> 4043.0769 | E11: =E9/E10 -> 5256 | F11: =F9/F10 -> 5997.2308 | G11: =G9/G10 -> 6536.3077 | H11: =H9/H10 -> 6738.4615 | I11: =I9/I10 -> 6738.4615 | J11: =J9/J10 -> 6738.4615 | ... L11: =L9/L10 -> 6738.4615
A12: ARPOB — gross of payer discount | B12: Rs/bed-day | C12: =Assumptions!$C$31*(1+Assumptions!$C$32)^0 -> 26500 | D12: =Assumptions!$C$31*(1+Assumptions!$C$32)^1 -> 28487.5 | E12: =Assumptions!$C$31*(1+Assumptions!$C$32)^2 -> 30624.062 | F12: =Assumptions!$C$31*(1+Assumptions!$C$32)^3 -> 32920.867 | G12: =Assumptions!$C$31*(1+Assumptions!$C$32)^4 -> 35389.932 | H12: =Assumptions!$C$31*(1+Assumptions!$C$32)^5 -> 38044.177 | I12: =Assumptions!$C$31*(1+Assumptions!$C$32)^6 -> 40897.49 | J12: =Assumptions!$C$31*(1+Assumptions!$C$32)^7 -> 43964.802 | K12: =Assumptions!$C$31*(1+Assumptions!$C$32)^8 -> 47262.162 | L12: =Assumptions!$C$31*(1+Assumptions!$C$32)^9 -> 50806.825
A13: Weighted realisation index (payer mix) | B13: index | C13: =Assumptions!$C$33 -> 0.909 | D13: =Assumptions!$C$33 -> 0.909 | E13: =Assumptions!$C$33 -> 0.909 | F13: =Assumptions!$C$33 -> 0.909 | G13: =Assumptions!$C$33 -> 0.909 | H13: =Assumptions!$C$33 -> 0.909 | I13: =Assumptions!$C$33 -> 0.909 | J13: =Assumptions!$C$33 -> 0.909 | ... L13: =Assumptions!$C$33 -> 0.909
A14: ARPOB — net realised | B14: Rs/bed-day | C14: =C12*C13 -> 24088.5 | D14: =D12*D13 -> 25895.138 | E14: =E12*E13 -> 27837.273 | F14: =F12*F13 -> 29925.068 | G14: =G12*G13 -> 32169.448 | H14: =H12*H13 -> 34582.157 | I14: =I12*I13 -> 37175.819 | J14: =J12*J13 -> 39964.005 | ... L14: =L12*L13 -> 46183.404
A15: IPD revenue | B15: Rs Lakh | C15: =C9*C14/100000 -> 2405.574 | D15: =D9*D14/100000 -> 4083.1453 | E15: =E9*E14/100000 -> 5706.1955 | F15: =F9*F14/100000 -> 6999.2341 | G15: =G9*G14/100000 -> 8200.5071 | H15: =H9*H14/100000 -> 9088.1909 | I15: =I9*I14/100000 -> 9769.8052 | J15: =J9*J14/100000 -> 10502.541 | ... L15: =L9*L14/100000 -> 12136.998 | N15: ARPOB by convention includes drugs and diagnostics consumed by inpatients
A17: B. Outpatient department (OPD)
A18: OPD footfall per day | B18: patients/day | C18: =Assumptions!$C$44*Assumptions!C$58*Assumptions!$C$43 -> 100 | D18: =Assumptions!$C$44*Assumptions!D$58*Assumptions!$C$43 -> 160 | E18: =Assumptions!$C$44*Assumptions!E$58*Assumptions!$C$43 -> 220 | F18: =Assumptions!$C$44*Assumptions!F$58*Assumptions!$C$43 -> 260 | G18: =Assumptions!$C$44*Assumptions!G$58*Assumptions!$C$43 -> 290 | H18: =Assumptions!$C$44*Assumptions!H$58*Assumptions!$C$43 -> 310 | I18: =Assumptions!$C$44*Assumptions!I$58*Assumptions!$C$43 -> 325 | J18: =Assumptions!$C$44*Assumptions!J$58*Assumptions!$C$43 -> 335 | ... L18: =Assumptions!$C$44*Assumptions!L$58*Assumptions!$C$43 -> 355
A19: Annual OPD visits | B19: visits | C19: =C18*365 -> 36500 | D19: =D18*365 -> 58400 | E19: =E18*365 -> 80300 | F19: =F18*365 -> 94900 | G19: =G18*365 -> 105850 | H19: =H18*365 -> 113150 | I19: =I18*365 -> 118625 | J19: =J18*365 -> 122275 | ... L19: =L18*365 -> 129575
A20: Net revenue per visit | B20: Rs | C20: =Assumptions!$C$45*(1+Assumptions!$C$46)^0 -> 700 | D20: =Assumptions!$C$45*(1+Assumptions!$C$46)^1 -> 742 | E20: =Assumptions!$C$45*(1+Assumptions!$C$46)^2 -> 786.52 | F20: =Assumptions!$C$45*(1+Assumptions!$C$46)^3 -> 833.7112 | G20: =Assumptions!$C$45*(1+Assumptions!$C$46)^4 -> 883.73387 | H20: =Assumptions!$C$45*(1+Assumptions!$C$46)^5 -> 936.7579 | I20: =Assumptions!$C$45*(1+Assumptions!$C$46)^6 -> 992.96338 | J20: =Assumptions!$C$45*(1+Assumptions!$C$46)^7 -> 1052.5412 | K20: =Assumptions!$C$45*(1+Assumptions!$C$46)^8 -> 1115.6937 | L20: =Assumptions!$C$45*(1+Assumptions!$C$46)^9 -> 1182.6353
A21: OPD revenue | B21: Rs Lakh | C21: =C19*C20/100000 -> 255.5 | D21: =D19*D20/100000 -> 433.328 | E21: =E19*E20/100000 -> 631.57556 | F21: =F19*F20/100000 -> 791.19193 | G21: =G19*G20/100000 -> 935.4323 | H21: =H19*H20/100000 -> 1059.9416 | I21: =I19*I20/100000 -> 1177.9028 | J21: =J19*J20/100000 -> 1286.9947 | ... L21: =L19*L20/100000 -> 1532.3997
A23: C. Outpatient diagnostics (radiology & laboratory)
A24: Conversion — share of OPD footfall | B24: % | C24: =Assumptions!C$59 -> 0.45 | D24: =Assumptions!D$59 -> 0.47 | E24: =Assumptions!E$59 -> 0.48 | F24: =Assumptions!F$59 -> 0.49 | G24: =Assumptions!G$59 -> 0.5 | H24: =Assumptions!H$59 -> 0.5 | I24: =Assumptions!I$59 -> 0.51 | J24: =Assumptions!J$59 -> 0.51 | ... L24: =Assumptions!L$59 -> 0.52
A25: Average ticket size | B25: Rs | C25: =Assumptions!$C$48*(1+Assumptions!$C$46)^0 -> 950 | D25: =Assumptions!$C$48*(1+Assumptions!$C$46)^1 -> 1007 | E25: =Assumptions!$C$48*(1+Assumptions!$C$46)^2 -> 1067.42 | F25: =Assumptions!$C$48*(1+Assumptions!$C$46)^3 -> 1131.4652 | G25: =Assumptions!$C$48*(1+Assumptions!$C$46)^4 -> 1199.3531 | H25: =Assumptions!$C$48*(1+Assumptions!$C$46)^5 -> 1271.3143 | I25: =Assumptions!$C$48*(1+Assumptions!$C$46)^6 -> 1347.5932 | J25: =Assumptions!$C$48*(1+Assumptions!$C$46)^7 -> 1428.4487 | K25: =Assumptions!$C$48*(1+Assumptions!$C$46)^8 -> 1514.1557 | L25: =Assumptions!$C$48*(1+Assumptions!$C$46)^9 -> 1605.005
A26: Diagnostics revenue | B26: Rs Lakh | C26: =C19*C24*C25/100000 -> 156.0375 | D26: =D19*D24*D25/100000 -> 276.40136 | E26: =E19*E24*E25/100000 -> 411.42636 | F26: =F19*F24*F25/100000 -> 526.14263 | G26: =G19*G24*G25/100000 -> 634.75763 | H26: =H19*H24*H25/100000 -> 719.24606 | I26: =I19*I24*I25/100000 -> 815.27701 | J26: =J19*J24*J25/100000 -> 890.78421 | ... L26: =L19*L24*L25/100000 -> 1081.4363
A28: D. Outpatient pharmacy
A29: Conversion — share of OPD footfall | B29: % | C29: =Assumptions!C$60 -> 0.55 | D29: =Assumptions!D$60 -> 0.57 | E29: =Assumptions!E$60 -> 0.58 | F29: =Assumptions!F$60 -> 0.59 | G29: =Assumptions!G$60 -> 0.6 | H29: =Assumptions!H$60 -> 0.6 | I29: =Assumptions!I$60 -> 0.61 | J29: =Assumptions!J$60 -> 0.61 | ... L29: =Assumptions!L$60 -> 0.62
A30: Average ticket size | B30: Rs | C30: =Assumptions!$C$50*(1+Assumptions!$C$46)^0 -> 480 | D30: =Assumptions!$C$50*(1+Assumptions!$C$46)^1 -> 508.8 | E30: =Assumptions!$C$50*(1+Assumptions!$C$46)^2 -> 539.328 | F30: =Assumptions!$C$50*(1+Assumptions!$C$46)^3 -> 571.68768 | G30: =Assumptions!$C$50*(1+Assumptions!$C$46)^4 -> 605.98894 | H30: =Assumptions!$C$50*(1+Assumptions!$C$46)^5 -> 642.34828 | I30: =Assumptions!$C$50*(1+Assumptions!$C$46)^6 -> 680.88917 | J30: =Assumptions!$C$50*(1+Assumptions!$C$46)^7 -> 721.74252 | K30: =Assumptions!$C$50*(1+Assumptions!$C$46)^8 -> 765.04708 | L30: =Assumptions!$C$50*(1+Assumptions!$C$46)^9 -> 810.9499
A31: Pharmacy revenue | B31: Rs Lakh | C31: =C19*C29*C30/100000 -> 96.36 | D31: =D19*D29*D30/100000 -> 169.36934 | E31: =E19*E29*E30/100000 -> 251.18662 | F31: =F19*F29*F30/100000 -> 320.09365 | G31: =G19*G29*G30/100000 -> 384.86358 | H31: =H19*H29*H30/100000 -> 436.09025 | I31: =I19*I29*I30/100000 -> 492.69992 | J31: =J19*J29*J30/100000 -> 538.33151 | ... L31: =L19*L29*L30/100000 -> 651.48877
A33: E. Dialysis unit
A34: Session capacity | B34: sessions | C34: =Assumptions!$C$51*Assumptions!$C$52*Assumptions!$C$53 -> 10500 | D34: =Assumptions!$C$51*Assumptions!$C$52*Assumptions!$C$53 -> 10500 | E34: =Assumptions!$C$51*Assumptions!$C$52*Assumptions!$C$53 -> 10500 | F34: =Assumptions!$C$51*Assumptions!$C$52*Assumptions!$C$53 -> 10500 | G34: =Assumptions!$C$51*Assumptions!$C$52*Assumptions!$C$53 -> 10500 | H34: =Assumptions!$C$51*Assumptions!$C$52*Assumptions!$C$53 -> 10500 | I34: =Assumptions!$C$51*Assumptions!$C$52*Assumptions!$C$53 -> 10500 | J34: =Assumptions!$C$51*Assumptions!$C$52*Assumptions!$C$53 -> 10500 | ... L34: =Assumptions!$C$51*Assumptions!$C$52*Assumptions!$C$53 -> 10500
A35: Utilisation | B35: % | C35: =Assumptions!C$61 -> 0.3 | D35: =Assumptions!D$61 -> 0.45 | E35: =Assumptions!E$61 -> 0.6 | F35: =Assumptions!F$61 -> 0.68 | G35: =Assumptions!G$61 -> 0.75 | H35: =Assumptions!H$61 -> 0.8 | I35: =Assumptions!I$61 -> 0.82 | J35: =Assumptions!J$61 -> 0.83 | ... L35: =Assumptions!L$61 -> 0.85
A36: Revenue per session | B36: Rs | C36: =Assumptions!$C$54*(1+Assumptions!$C$46)^0 -> 1900 | D36: =Assumptions!$C$54*(1+Assumptions!$C$46)^1 -> 2014 | E36: =Assumptions!$C$54*(1+Assumptions!$C$46)^2 -> 2134.84 | F36: =Assumptions!$C$54*(1+Assumptions!$C$46)^3 -> 2262.9304 | G36: =Assumptions!$C$54*(1+Assumptions!$C$46)^4 -> 2398.7062 | H36: =Assumptions!$C$54*(1+Assumptions!$C$46)^5 -> 2542.6286 | I36: =Assumptions!$C$54*(1+Assumptions!$C$46)^6 -> 2695.1863 | J36: =Assumptions!$C$54*(1+Assumptions!$C$46)^7 -> 2856.8975 | K36: =Assumptions!$C$54*(1+Assumptions!$C$46)^8 -> 3028.3113 | L36: =Assumptions!$C$54*(1+Assumptions!$C$46)^9 -> 3210.01
A37: Dialysis revenue | B37: Rs Lakh | C37: =C34*C35*C36/100000 -> 59.85 | D37: =D34*D35*D36/100000 -> 95.1615 | E37: =E34*E35*E36/100000 -> 134.49492 | F37: =F34*F35*F36/100000 -> 161.57323 | G37: =G34*G35*G36/100000 -> 188.89812 | H37: =H34*H35*H36/100000 -> 213.5808 | I37: =I34*I35*I36/100000 -> 232.05554 | J37: =J34*J35*J36/100000 -> 248.97862 | ... L37: =L34*L35*L36/100000 -> 286.49339
A39: F. Other operating income
A40: Health checks, ambulance, academics, cafeteria & retail rentals | B40: Rs Lakh | C40: =Assumptions!C$62 -> 40 | D40: =Assumptions!D$62 -> 55 | E40: =Assumptions!E$62 -> 70 | F40: =Assumptions!F$62 -> 82 | G40: =Assumptions!G$62 -> 95 | H40: =Assumptions!H$62 -> 105 | I40: =Assumptions!I$62 -> 115 | J40: =Assumptions!J$62 -> 124 | ... L40: =Assumptions!L$62 -> 142
A42: TOTAL OPERATING REVENUE
A43: Total operating revenue | B43: Rs Lakh | C43: =C15+C21+C26+C31+C37+C40 -> 3013.3215 | D43: =D15+D21+D26+D31+D37+D40 -> 5112.4055 | E43: =E15+E21+E26+E31+E37+E40 -> 7204.879 | F43: =F15+F21+F26+F31+F37+F40 -> 8880.2355 | G43: =G15+G21+G26+G31+G37+G40 -> 10439.459 | H43: =H15+H21+H26+H31+H37+H40 -> 11622.05 | I43: =I15+I21+I26+I31+I37+I40 -> 12602.74 | J43: =J15+J21+J26+J31+J37+J40 -> 13591.63 | ... L43: =L15+L21+L26+L31+L37+L40 -> 15830.817
A44: Revenue growth (YoY) | B44: % | C44: =0 -> 0 | D44: =D43/C43-1 -> 0.69660142 | E44: =E43/D43-1 -> 0.40929334 | F44: =F43/E43-1 -> 0.23253083 | G44: =G43/F43-1 -> 0.17558354 | H44: =H43/G43-1 -> 0.11328085 | I44: =I43/H43-1 -> 0.084381925 | J44: =J43/I43-1 -> 0.078466201 | K44: =K43/J43-1 -> 0.0803744 | L44: =L43/K43-1 -> 0.078096164
A45: Total operating revenue | B45: Rs Crore | C45: =C43/100 -> 30.133215 | D45: =D43/100 -> 51.124055 | E45: =E43/100 -> 72.04879 | F45: =F43/100 -> 88.802355 | G45: =G43/100 -> 104.39459 | H45: =H43/100 -> 116.2205 | I45: =I43/100 -> 126.0274 | J45: =J43/100 -> 135.9163 | ... L45: =L43/100 -> 158.30817
A47: Revenue mix
A48: Inpatient (IPD) | B48: % | C48: =C15/C43 -> 0.79831309 | D48: =D15/D43 -> 0.79867399 | E48: =E15/E43 -> 0.79199047 | F48: =F15/F43 -> 0.78818113 | G48: =G15/G43 -> 0.78552991 | H48: =H15/H43 -> 0.78197833 | I48: =I15/I43 -> 0.77521276 | J48: =J15/J43 -> 0.77272122 | ... L48: =L15/L43 -> 0.76666913
A49: Outpatient (OPD) | B49: % | C49: =C21/C43 -> 0.084790157 | D49: =D21/D43 -> 0.0847601 | E49: =E21/E43 -> 0.087659426 | F49: =F21/F43 -> 0.089095827 | G49: =G21/G43 -> 0.089605441 | H49: =H21/H43 -> 0.091200916 | I49: =I21/I43 -> 0.093464022 | J49: =J21/J43 -> 0.094690244 | ... L49: =L21/L43 -> 0.096798522
A50: Diagnostics | B50: % | C50: =C26/C43 -> 0.05178256 | D50: =D26/D43 -> 0.054064835 | E50: =E26/E43 -> 0.057103855 | F50: =F26/F43 -> 0.059248725 | G50: =G26/G43 -> 0.060803692 | H50: =H26/H43 -> 0.061886336 | I50: =I26/I43 -> 0.064690455 | J50: =J26/J43 -> 0.065539176 | ... L50: =L26/L43 -> 0.0683121
A51: Pharmacy | B51: % | C51: =C31/C43 -> 0.031978002 | D51: =D31/D43 -> 0.033129091 | E51: =E31/E43 -> 0.034863406 | F51: =F31/F43 -> 0.036045626 | G51: =G31/G43 -> 0.036866239 | H51: =H31/H43 -> 0.037522663 | I51: =I31/I43 -> 0.039094665 | J51: =J31/J43 -> 0.039607576 | ... L51: =L31/L43 -> 0.0411532
A52: Dialysis | B52: % | C52: =C37/C43 -> 0.019861804 | D52: =D37/D43 -> 0.01861384 | E52: =E37/E43 -> 0.0186672 | F52: =F37/F43 -> 0.018194701 | G52: =G37/G43 -> 0.018094627 | H52: =H37/H43 -> 0.018377206 | I52: =I37/I43 -> 0.018413102 | J52: =J37/J43 -> 0.018318526 | ... L52: =L37/L43 -> 0.018097196
A53: Other income | B53: % | C53: =C40/C43 -> 0.013274389 | D53: =D40/D43 -> 0.010758145 | E53: =E40/E43 -> 0.0097156385 | F53: =F40/F43 -> 0.0092339893 | G53: =G40/G43 -> 0.0091000887 | H53: =H40/H43 -> 0.0090345511 | I53: =I40/I43 -> 0.0091249995 | J53: =J40/J43 -> 0.0091232621 | ... L53: =L40/L43 -> 0.0089698468
A55: Key per-unit metrics
A56: Revenue per operational bed | B56: Rs Lakh | C56: =C43/C7 -> 30.133215 | D56: =D43/D7 -> 51.124055 | E56: =E43/E7 -> 72.04879 | F56: =F43/F7 -> 88.802355 | G56: =G43/G7 -> 104.39459 | H56: =H43/H7 -> 116.2205 | I56: =I43/I7 -> 126.0274 | J56: =J43/J7 -> 135.9163 | ... L56: =L43/L7 -> 158.30817 | N56: Mature Indian hospitals run Rs 90-130 L per bed
A57: Revenue per sq ft of built-up area | B57: Rs | C57: =C43*100000/Assumptions!$C$6 -> 2869.83 | D57: =D43*100000/Assumptions!$C$6 -> 4868.9576 | E57: =E43*100000/Assumptions!$C$6 -> 6861.7895 | F57: =F43*100000/Assumptions!$C$6 -> 8457.3672 | G57: =G43*100000/Assumptions!$C$6 -> 9942.3417 | H57: =H43*100000/Assumptions!$C$6 -> 11068.619 | I57: =I43*100000/Assumptions!$C$6 -> 12002.61 | J57: =J43*100000/Assumptions!$C$6 -> 12944.409 | ... L57: =L43*100000/Assumptions!$C$6 -> 15076.968
A58: Average revenue per inpatient (ARPP) | B58: Rs | C58: =C15*100000/C11 -> 93945.15 | D58: =D15*100000/D11 -> 100991.04 | E58: =E15*100000/E11 -> 108565.36 | F58: =F15*100000/F11 -> 116707.77 | G58: =G15*100000/G11 -> 125460.85 | H58: =H15*100000/H11 -> 134870.41 | I58: =I15*100000/I11 -> 144985.69 | J58: =J15*100000/J11 -> 155859.62 | ... L58: =L15*100000/L11 -> 180115.27 | N58: ARPOB x ALOS. Rises with case-mix complexity, falls with efficiency gains.

Sheet Manpower
A1: MANPOWER PLAN & COST
A2: Headcount ramp by cadre. Cost escalates at the salary-escalation assumption. Rs Lakh.
A4: Cadre | B4: Unit | C4: Year 1 | D4: Year 2 | E4: Year 3 | F4: Year 4 | G4: Year 5 | H4: Year 6 | I4: Year 7 | J4: Year 8 | K4: Year 9 | L4: Year 10
A5: Financial year | C5: FY2029 | D5: FY2030 | E5: FY2031 | F5: FY2032 | G5: FY2033 | H5: FY2034 | I5: FY2035 | J5: FY2036 | K5: FY2037 | L5: FY2038
A6: Full-time consultants (retainer / employed) | B6: nos | C6: 16 | D6: 18 | E6: 19 | F6: 20 | G6: 20 | H6: 20 | I6: 20 | J6: 20 | K6: 20 | L6: 20 | N6: The clinical anchors. A tier-2 hospital lives or dies on retaining these.
A7: Resident medical officers / DNB residents | B7: nos | C7: 18 | D7: 21 | E7: 23 | F7: 23 | G7: 24 | H7: 24 | I7: 24 | J7: 24 | K7: 24 | L7: 24
A8: Nursing staff | B8: nos | C8: 105 | D8: 123 | E8: 132 | F8: 136 | G8: 140 | H8: 140 | I8: 140 | J8: 140 | K8: 140 | L8: 140 | N8: Nurse:bed ratio ~1.4:1 at maturity, higher in critical care
A9: Paramedical & technicians | B9: nos | C9: 34 | D9: 40 | E9: 43 | F9: 45 | G9: 46 | H9: 46 | I9: 46 | J9: 46 | K9: 46 | L9: 46
A10: Pharmacy staff | B10: nos | C10: 9 | D10: 10 | E10: 11 | F10: 12 | G10: 12 | H10: 12 | I10: 12 | J10: 12 | K10: 12 | L10: 12
A11: Front office, admissions, billing & TPA | B11: nos | C11: 23 | D11: 27 | E11: 29 | F11: 30 | G11: 31 | H11: 31 | I11: 31 | J11: 31 | K11: 31 | L11: 31 | N11: TPA desk size scales with the insurance mix
A12: Finance, HR, IT, quality & NABH | B12: nos | C12: 11 | D12: 13 | E12: 14 | F12: 15 | G12: 15 | H12: 15 | I12: 15 | J12: 15 | K12: 15 | L12: 15
A13: In-house support (biomedical, maintenance) | B13: nos | C13: 19 | D13: 20 | E13: 21 | F13: 21 | G13: 21 | H13: 21 | I13: 21 | J13: 21 | K13: 21 | L13: 21
A14: Total headcount | B14: nos | C14: =SUM(C6:C13) -> 235 | D14: =SUM(D6:D13) -> 272 | E14: =SUM(E6:E13) -> 292 | F14: =SUM(F6:F13) -> 302 | G14: =SUM(G6:G13) -> 309 | H14: =SUM(H6:H13) -> 309 | I14: =SUM(I6:I13) -> 309 | J14: =SUM(J6:J13) -> 309 | ... L14: =SUM(L6:L13) -> 309
A15: Staff per bed | B15: ratio | C15: =C14/Assumptions!$C$5 -> 2.35 | D15: =D14/Assumptions!$C$5 -> 2.72 | E15: =E14/Assumptions!$C$5 -> 2.92 | F15: =F14/Assumptions!$C$5 -> 3.02 | G15: =G14/Assumptions!$C$5 -> 3.09 | H15: =H14/Assumptions!$C$5 -> 3.09 | I15: =I14/Assumptions!$C$5 -> 3.09 | J15: =J14/Assumptions!$C$5 -> 3.09 | ... L15: =L14/Assumptions!$C$5 -> 3.09 | N15: Indian multi-specialty hospitals run 2.5-3.5 staff per bed
A17: Cost per head (Year 1, Rs Lakh per annum)
A18: Full-time consultants (retainer / employed) | B18: Rs L p.a. | C18: 32
A19: Resident medical officers / DNB residents | B19: Rs L p.a. | C19: 9.5
A20: Nursing staff | B20: Rs L p.a. | C20: 3.9
A21: Paramedical & technicians | B21: Rs L p.a. | C21: 4.4
A22: Pharmacy staff | B22: Rs L p.a. | C22: 3.2
A23: Front office, admissions, billing & TPA | B23: Rs L p.a. | C23: 4.2
A24: Finance, HR, IT, quality & NABH | B24: Rs L p.a. | C24: 7
A25: In-house support (biomedical, maintenance) | B25: Rs L p.a. | C25: 2.6
A27: Salary cost
A28: Cost at Year-1 rates (headcount x Year-1 cost per head) | B28: Rs Lakh | C28: =C6*$C$18+C7*$C$19+C8*$C$20+C9*$C$21+C10*$C$22+C11*$C$23+C12*$C$24+C13*$C$25 -> 1493.9 | D28: =D6*$C$18+D7*$C$19+D8*$C$20+D9*$C$21+D10*$C$22+D11*$C$23+D12*$C$24+D13*$C$25 -> 1719.6 | E28: =E6*$C$18+E7*$C$19+E8*$C$20+E9*$C$21+E10*$C$22+E11*$C$23+E12*$C$24+E13*$C$25 -> 1840.1 | F28: =F6*$C$18+F7*$C$19+F8*$C$20+F9*$C$21+F10*$C$22+F11*$C$23+F12*$C$24+F13*$C$25 -> 1910.9 | G28: =G6*$C$18+G7*$C$19+G8*$C$20+G9*$C$21+G10*$C$22+G11*$C$23+G12*$C$24+G13*$C$25 -> 1944.6 | H28: =H6*$C$18+H7*$C$19+H8*$C$20+H9*$C$21+H10*$C$22+H11*$C$23+H12*$C$24+H13*$C$25 -> 1944.6 | I28: =I6*$C$18+I7*$C$19+I8*$C$20+I9*$C$21+I10*$C$22+I11*$C$23+I12*$C$24+I13*$C$25 -> 1944.6 | J28: =J6*$C$18+J7*$C$19+J8*$C$20+J9*$C$21+J10*$C$22+J11*$C$23+J12*$C$24+J13*$C$25 -> 1944.6 | ... L28: =L6*$C$18+L7*$C$19+L8*$C$20+L9*$C$21+L10*$C$22+L11*$C$23+L12*$C$24+L13*$C$25 -> 1944.6
A29: Cumulative escalation factor | B29: x | C29: =(1+Assumptions!$C$68)^0 -> 1 | D29: =(1+Assumptions!$C$68)^1 -> 1.08 | E29: =(1+Assumptions!$C$68)^2 -> 1.1664 | F29: =(1+Assumptions!$C$68)^3 -> 1.259712 | G29: =(1+Assumptions!$C$68)^4 -> 1.360489 | H29: =(1+Assumptions!$C$68)^5 -> 1.4693281 | I29: =(1+Assumptions!$C$68)^6 -> 1.5868743 | J29: =(1+Assumptions!$C$68)^7 -> 1.7138243 | K29: =(1+Assumptions!$C$68)^8 -> 1.8509302 | L29: =(1+Assumptions!$C$68)^9 -> 1.9990046
A30: TOTAL SALARY & WAGE COST | B30: Rs Lakh | C30: =C28*C29 -> 1493.9 | D30: =D28*D29 -> 1857.168 | E30: =E28*E29 -> 2146.2926 | F30: =F28*F29 -> 2407.1837 | G30: =G28*G29 -> 2645.6068 | H30: =H28*H29 -> 2857.2554 | I30: =I28*I29 -> 3085.8358 | J30: =J28*J29 -> 3332.7027 | ... L30: =L28*L29 -> 3887.2644
A31: Average cost per employee | B31: Rs Lakh | C31: =C30/C14 -> 6.3570213 | D31: =D30/D14 -> 6.8278235 | E31: =E30/E14 -> 7.3503173 | F31: =F30/F14 -> 7.9708068 | G31: =G30/G14 -> 8.5618344 | H31: =H30/H14 -> 9.2467812 | I31: =I30/I14 -> 9.9865237 | J31: =J30/J14 -> 10.785446 | ... L31: =L30/L14 -> 12.580144
A32: Salary cost as % of revenue | B32: % | C32: =C30/'Revenue Build'!C$43 -> 0.49576523 | D32: =D30/'Revenue Build'!D$43 -> 0.36326696 | E32: =E30/'Revenue Build'!E$43 -> 0.29789434 | F32: =F30/'Revenue Build'!F$43 -> 0.27107205 | G32: =G30/'Revenue Build'!G$43 -> 0.25342375 | H32: =H30/'Revenue Build'!H$43 -> 0.24584781 | I32: =I30/'Revenue Build'!I$43 -> 0.24485435 | J32: =J30/'Revenue Build'!J$43 -> 0.24520258 | ... L32: =L30/'Revenue Build'!L$43 -> 0.24555047 | N32: Indian hospitals typically run 22-28% at maturity; higher in the ramp years

Sheet Operating Costs
A1: OPERATING COST BUILD-UP
A2: Classified into variable (scales with revenue) and fixed / semi-fixed. Rs Lakh.
A4: Cost head | B4: Basis | C4: Year 1 | D4: Year 2 | E4: Year 3 | F4: Year 4 | G4: Year 5 | H4: Year 6 | I4: Year 7 | J4: Year 8 | K4: Year 9 | L4: Year 10
A5: Financial year | C5: FY2029 | D5: FY2030 | E5: FY2031 | F5: FY2032 | G5: FY2033 | H5: FY2034 | I5: FY2035 | J5: FY2036 | K5: FY2037 | L5: FY2038
A6: Variable costs
A7: Consultant payout — fee-for-service | B7: % of IPD+OPD | C7: =Assumptions!$C$65*('Revenue Build'!C$15+'Revenue Build'!C$21) -> 292.71814 | D7: =Assumptions!$C$65*('Revenue Build'!D$15+'Revenue Build'!D$21) -> 496.81206 | E7: =Assumptions!$C$65*('Revenue Build'!E$15+'Revenue Build'!E$21) -> 697.15482 | F7: =Assumptions!$C$65*('Revenue Build'!F$15+'Revenue Build'!F$21) -> 856.94686 | G7: =Assumptions!$C$65*('Revenue Build'!G$15+'Revenue Build'!G$21) -> 1004.9533 | H7: =Assumptions!$C$65*('Revenue Build'!H$15+'Revenue Build'!H$21) -> 1116.2946 | I7: =Assumptions!$C$65*('Revenue Build'!I$15+'Revenue Build'!I$21) -> 1204.2479 | J7: =Assumptions!$C$65*('Revenue Build'!J$15+'Revenue Build'!J$21) -> 1296.8489 | ... L7: =Assumptions!$C$65*('Revenue Build'!L$15+'Revenue Build'!L$21) -> 1503.6338
A8: Consumables — drugs, implants, disposables, reagents | B8: % of revenue | C8: =Assumptions!$C$66*'Revenue Build'!C$43 -> 693.06394 | D8: =Assumptions!$C$66*'Revenue Build'!D$43 -> 1175.8533 | E8: =Assumptions!$C$66*'Revenue Build'!E$43 -> 1657.1222 | F8: =Assumptions!$C$66*'Revenue Build'!F$43 -> 2042.4542 | G8: =Assumptions!$C$66*'Revenue Build'!G$43 -> 2401.0755 | H8: =Assumptions!$C$66*'Revenue Build'!H$43 -> 2673.0714 | I8: =Assumptions!$C$66*'Revenue Build'!I$43 -> 2898.6303 | J8: =Assumptions!$C$66*'Revenue Build'!J$43 -> 3126.0748 | ... L8: =Assumptions!$C$66*'Revenue Build'!L$43 -> 3641.0878
A9: Total variable costs | B9: Rs Lakh | C9: =C7+C8 -> 985.78207 | D9: =D7+D8 -> 1672.6653 | E9: =E7+E8 -> 2354.277 | F9: =F7+F8 -> 2899.401 | G9: =G7+G8 -> 3406.0288 | H9: =H7+H8 -> 3789.366 | I9: =I7+I8 -> 4102.8782 | J9: =J7+J8 -> 4422.9237 | ... L9: =L7+L8 -> 5144.7216
A11: Fixed & semi-fixed costs
A12: Salaries & wages | B12: Rs Lakh | C12: =Manpower!C$30 -> 1493.9 | D12: =Manpower!D$30 -> 1857.168 | E12: =Manpower!E$30 -> 2146.2926 | F12: =Manpower!F$30 -> 2407.1837 | G12: =Manpower!G$30 -> 2645.6068 | H12: =Manpower!H$30 -> 2857.2554 | I12: =Manpower!I$30 -> 3085.8358 | J12: =Manpower!J$30 -> 3332.7027 | ... L12: =Manpower!L$30 -> 3887.2644
A13: Power & fuel | B13: Rs Lakh | C13: =Assumptions!C$72 -> 200 | D13: =Assumptions!D$72 -> 250 | E13: =Assumptions!E$72 -> 310 | F13: =Assumptions!F$72 -> 380 | G13: =Assumptions!G$72 -> 460 | H13: =Assumptions!H$72 -> 500 | I13: =Assumptions!I$72 -> 530 | J13: =Assumptions!J$72 -> 560 | ... L13: =Assumptions!L$72 -> 620
A14: Outsourced services | B14: Rs Lakh | C14: =Assumptions!C$73 -> 185 | D14: =Assumptions!D$73 -> 215 | E14: =Assumptions!E$73 -> 265 | F14: =Assumptions!F$73 -> 300 | G14: =Assumptions!G$73 -> 420 | H14: =Assumptions!H$73 -> 445 | I14: =Assumptions!I$73 -> 470 | J14: =Assumptions!J$73 -> 495 | ... L14: =Assumptions!L$73 -> 545
A15: Repairs & maintenance | B15: Rs Lakh | C15: =Assumptions!C$74 -> 120 | D15: =Assumptions!D$74 -> 145 | E15: =Assumptions!E$74 -> 190 | F15: =Assumptions!F$74 -> 240 | G15: =Assumptions!G$74 -> 300 | H15: =Assumptions!H$74 -> 330 | I15: =Assumptions!I$74 -> 355 | J15: =Assumptions!J$74 -> 380 | ... L15: =Assumptions!L$74 -> 430
A16: Administrative & other overheads | B16: Rs Lakh | C16: =Assumptions!C$75 -> 155 | D16: =Assumptions!D$75 -> 180 | E16: =Assumptions!E$75 -> 230 | F16: =Assumptions!F$75 -> 300 | G16: =Assumptions!G$75 -> 380 | H16: =Assumptions!H$75 -> 410 | I16: =Assumptions!I$75 -> 440 | J16: =Assumptions!J$75 -> 470 | ... L16: =Assumptions!L$75 -> 530
A17: Marketing & business development | B17: Rs Lakh | C17: =Assumptions!C$76 -> 170 | D17: =Assumptions!D$76 -> 175 | E17: =Assumptions!E$76 -> 180 | F17: =Assumptions!F$76 -> 185 | G17: =Assumptions!G$76 -> 190 | H17: =Assumptions!H$76 -> 200 | I17: =Assumptions!I$76 -> 210 | J17: =Assumptions!J$76 -> 220 | ... L17: =Assumptions!L$76 -> 240
A18: Insurance, rates & taxes, licences | B18: Rs Lakh | C18: =Assumptions!C$77 -> 90 | D18: =Assumptions!D$77 -> 100 | E18: =Assumptions!E$77 -> 120 | F18: =Assumptions!F$77 -> 140 | G18: =Assumptions!G$77 -> 160 | H18: =Assumptions!H$77 -> 172 | I18: =Assumptions!I$77 -> 184 | J18: =Assumptions!J$77 -> 196 | ... L18: =Assumptions!L$77 -> 220
A19: Total fixed & semi-fixed costs | B19: Rs Lakh | C19: =SUM(C12:C18) -> 2413.9 | D19: =SUM(D12:D18) -> 2922.168 | E19: =SUM(E12:E18) -> 3441.2926 | F19: =SUM(F12:F18) -> 3952.1837 | G19: =SUM(G12:G18) -> 4555.6068 | H19: =SUM(H12:H18) -> 4914.2554 | I19: =SUM(I12:I18) -> 5274.8358 | J19: =SUM(J12:J18) -> 5653.7027 | ... L19: =SUM(L12:L18) -> 6472.2644
A21: TOTAL OPERATING EXPENDITURE
A22: Total operating expenditure | B22: Rs Lakh | C22: =C9+C19 -> 3399.6821 | D22: =D9+D19 -> 4594.8333 | E22: =E9+E19 -> 5795.5696 | F22: =F9+F19 -> 6851.5847 | G22: =G9+G19 -> 7961.6357 | H22: =H9+H19 -> 8703.6213 | I22: =I9+I19 -> 9377.714 | J22: =J9+J19 -> 10076.626 | ... L22: =L9+L19 -> 11616.986
A23: Operating expenditure as % of revenue | B23: % | C23: =C22/'Revenue Build'!C$43 -> 1.1282175 | D23: =D22/'Revenue Build'!D$43 -> 0.89876152 | E23: =E22/'Revenue Build'!E$43 -> 0.80439514 | F23: =F22/'Revenue Build'!F$43 -> 0.77155439 | G23: =G22/'Revenue Build'!G$43 -> 0.76264832 | H23: =H22/'Revenue Build'!H$43 -> 0.74888868 | I23: =I22/'Revenue Build'!I$43 -> 0.74410118 | J23: =J22/'Revenue Build'!J$43 -> 0.74138471 | ... L23: =L22/'Revenue Build'!L$43 -> 0.73382102
A25: EBITDA
A26: EBITDA | B26: Rs Lakh | C26: ='Revenue Build'!C$43-C22 -> -386.36061 | D26: ='Revenue Build'!D$43-D22 -> 517.57216 | E26: ='Revenue Build'!E$43-E22 -> 1409.3094 | F26: ='Revenue Build'!F$43-F22 -> 2028.6508 | G26: ='Revenue Build'!G$43-G22 -> 2477.8231 | H26: ='Revenue Build'!H$43-H22 -> 2918.4282 | I26: ='Revenue Build'!I$43-I22 -> 3225.0265 | J26: ='Revenue Build'!J$43-J22 -> 3515.0033 | ... L26: ='Revenue Build'!L$43-L22 -> 4213.8306
A27: EBITDA margin | B27: % | C27: =C26/'Revenue Build'!C$43 -> -0.12821752 | D27: =D26/'Revenue Build'!D$43 -> 0.10123848 | E27: =E26/'Revenue Build'!E$43 -> 0.19560486 | F27: =F26/'Revenue Build'!F$43 -> 0.22844561 | G27: =G26/'Revenue Build'!G$43 -> 0.23735168 | H27: =H26/'Revenue Build'!H$43 -> 0.25111132 | I27: =I26/'Revenue Build'!I$43 -> 0.25589882 | J27: =J26/'Revenue Build'!J$43 -> 0.25861529 | ... L27: =L26/'Revenue Build'!L$43 -> 0.26617898 | N27: ICRA: sector operating margin 22-24%. A well-run tier-2 asset reaches 25-27% at maturity.
A28: EBITDA per operational bed | B28: Rs Lakh | C28: =C26/Assumptions!$C$5 -> -3.8636061 | D28: =D26/Assumptions!$C$5 -> 5.1757216 | E28: =E26/Assumptions!$C$5 -> 14.093094 | F28: =F26/Assumptions!$C$5 -> 20.286508 | G28: =G26/Assumptions!$C$5 -> 24.778231 | H28: =H26/Assumptions!$C$5 -> 29.184282 | I28: =I26/Assumptions!$C$5 -> 32.250265 | J28: =J26/Assumptions!$C$5 -> 35.150033 | ... L28: =L26/Assumptions!$C$5 -> 42.138306
A30: Cost structure analysis
A31: Variable costs as % of revenue | B31: % | C31: =C9/'Revenue Build'!C$43 -> 0.32714136 | D31: =D9/'Revenue Build'!D$43 -> 0.32717775 | E31: =E9/'Revenue Build'!E$43 -> 0.32676149 | F31: =F9/'Revenue Build'!F$43 -> 0.32650047 | G31: =G9/'Revenue Build'!G$43 -> 0.32626489 | H31: =H9/'Revenue Build'!H$43 -> 0.32604972 | I31: =I9/'Revenue Build'!I$43 -> 0.32555445 | J31: =J9/'Revenue Build'!J$43 -> 0.32541526 | ... L31: =L9/'Revenue Build'!L$43 -> 0.32498144
A32: Fixed costs as % of revenue | B32: % | C32: =C19/'Revenue Build'!C$43 -> 0.80107616 | D32: =D19/'Revenue Build'!D$43 -> 0.57158377 | E32: =E19/'Revenue Build'!E$43 -> 0.47763365 | F32: =F19/'Revenue Build'!F$43 -> 0.44505392 | G32: =G19/'Revenue Build'!G$43 -> 0.43638343 | H32: =H19/'Revenue Build'!H$43 -> 0.42283896 | I32: =I19/'Revenue Build'!I$43 -> 0.41854673 | J32: =J19/'Revenue Build'!J$43 -> 0.41596945 | ... L32: =L19/'Revenue Build'!L$43 -> 0.40883958 | N32: Falls sharply as occupancy ramps — this is the operating leverage that makes hospitals attractive
A33: Contribution margin ratio | B33: % | C33: =1-C31 -> 0.67285864 | D33: =1-D31 -> 0.67282225 | E33: =1-E31 -> 0.67323851 | F33: =1-F31 -> 0.67349953 | G33: =1-G31 -> 0.67373511 | H33: =1-H31 -> 0.67395028 | I33: =1-I31 -> 0.67444555 | J33: =1-J31 -> 0.67458474 | ... L33: =1-L31 -> 0.67501856

Sheet Working Capital
A1: WORKING CAPITAL
A2: Receivables are driven by the payer mix — the single largest working-capital lever in an Indian hospital. Rs Lakh.
A4: Particulars | B4: Basis | C4: Year 1 | D4: Year 2 | E4: Year 3 | F4: Year 4 | G4: Year 5 | H4: Year 6 | I4: Year 7 | J4: Year 8 | K4: Year 9 | L4: Year 10
A5: Financial year | C5: FY2029 | D5: FY2030 | E5: FY2031 | F5: FY2032 | G5: FY2033 | H5: FY2034 | I5: FY2035 | J5: FY2036 | K5: FY2037 | L5: FY2038
A6: Current assets
A7: Debtor days (weighted by payer mix) | B7: days | C7: =Assumptions!$C$80 -> 47.95 | D7: =Assumptions!$C$80 -> 47.95 | E7: =Assumptions!$C$80 -> 47.95 | F7: =Assumptions!$C$80 -> 47.95 | G7: =Assumptions!$C$80 -> 47.95 | H7: =Assumptions!$C$80 -> 47.95 | I7: =Assumptions!$C$80 -> 47.95 | J7: =Assumptions!$C$80 -> 47.95 | ... L7: =Assumptions!$C$80 -> 47.95
A8: Trade receivables | B8: Rs Lakh | C8: ='Revenue Build'!C$43*C7/365 -> 395.85963 | D8: ='Revenue Build'!D$43*D7/365 -> 671.61601 | E8: ='Revenue Build'!E$43*E7/365 -> 946.50397 | F8: ='Revenue Build'!F$43*F7/365 -> 1166.5953 | G8: ='Revenue Build'!G$43*G7/365 -> 1371.4303 | H8: ='Revenue Build'!H$43*H7/365 -> 1526.7871 | I8: ='Revenue Build'!I$43*I7/365 -> 1655.6203 | J8: ='Revenue Build'!J$43*J7/365 -> 1785.5305 | ... L8: ='Revenue Build'!L$43*L7/365 -> 2079.6922
A9: Inventory (pharmacy, implants, reagents) | B9: Rs Lakh | C9: ='Operating Costs'!C$8*Assumptions!$C$81/365 -> 47.470133 | D9: ='Operating Costs'!D$8*Assumptions!$C$81/365 -> 80.537895 | E9: ='Operating Costs'!E$8*Assumptions!$C$81/365 -> 113.50152 | F9: ='Operating Costs'!F$8*Assumptions!$C$81/365 -> 139.89412 | G9: ='Operating Costs'!G$8*Assumptions!$C$81/365 -> 164.45723 | H9: ='Operating Costs'!H$8*Assumptions!$C$81/365 -> 183.08708 | I9: ='Operating Costs'!I$8*Assumptions!$C$81/365 -> 198.53632 | J9: ='Operating Costs'!J$8*Assumptions!$C$81/365 -> 214.11471 | ... L9: ='Operating Costs'!L$8*Assumptions!$C$81/365 -> 249.38958
A10: Other current assets (advances, deposits, prepaid) | B10: Rs Lakh | C10: ='Revenue Build'!C$43*Assumptions!$C$83/365 -> 99.068103 | D10: ='Revenue Build'!D$43*Assumptions!$C$83/365 -> 168.07908 | E10: ='Revenue Build'!E$43*Assumptions!$C$83/365 -> 236.87273 | F10: ='Revenue Build'!F$43*Assumptions!$C$83/365 -> 291.95295 | G10: ='Revenue Build'!G$43*Assumptions!$C$83/365 -> 343.21508 | H10: ='Revenue Build'!H$43*Assumptions!$C$83/365 -> 382.09478 | I10: ='Revenue Build'!I$43*Assumptions!$C$83/365 -> 414.33667 | J10: ='Revenue Build'!J$43*Assumptions!$C$83/365 -> 446.8481 | ... L10: ='Revenue Build'!L$43*Assumptions!$C$83/365 -> 520.4652
A11: Total current assets (excl. cash) | B11: Rs Lakh | C11: =C8+C9+C10 -> 542.39786 | D11: =D8+D9+D10 -> 920.23299 | E11: =E8+E9+E10 -> 1296.8782 | F11: =F8+F9+F10 -> 1598.4424 | G11: =G8+G9+G10 -> 1879.1026 | H11: =H8+H9+H10 -> 2091.9689 | I11: =I8+I9+I10 -> 2268.4933 | J11: =J8+J9+J10 -> 2446.4933 | ... L11: =L8+L9+L10 -> 2849.547
A13: Current liabilities
A14: Trade payables | B14: Rs Lakh | C14: =('Operating Costs'!C$8+'Operating Costs'!C$14)*Assumptions!$C$82/365 -> 108.25446 | D14: =('Operating Costs'!D$8+'Operating Costs'!D$14)*Assumptions!$C$82/365 -> 171.47506 | E14: =('Operating Costs'!E$8+'Operating Costs'!E$14)*Assumptions!$C$82/365 -> 236.97397 | F14: =('Operating Costs'!F$8+'Operating Costs'!F$14)*Assumptions!$C$82/365 -> 288.79572 | G14: =('Operating Costs'!G$8+'Operating Costs'!G$14)*Assumptions!$C$82/365 -> 347.80383 | H14: =('Operating Costs'!H$8+'Operating Costs'!H$14)*Assumptions!$C$82/365 -> 384.41976 | I14: =('Operating Costs'!I$8+'Operating Costs'!I$14)*Assumptions!$C$82/365 -> 415.31059 | J14: =('Operating Costs'!J$8+'Operating Costs'!J$14)*Assumptions!$C$82/365 -> 446.43388 | ... L14: =('Operating Costs'!L$8+'Operating Costs'!L$14)*Assumptions!$C$82/365 -> 516.09302
A15: Other current liabilities (statutory dues, provisions, accruals) | B15: Rs Lakh | C15: ='Revenue Build'!C$43*Assumptions!$C$84/365 -> 148.60215 | D15: ='Revenue Build'!D$43*Assumptions!$C$84/365 -> 252.11863 | E15: ='Revenue Build'!E$43*Assumptions!$C$84/365 -> 355.3091 | F15: ='Revenue Build'!F$43*Assumptions!$C$84/365 -> 437.92942 | G15: ='Revenue Build'!G$43*Assumptions!$C$84/365 -> 514.82262 | H15: ='Revenue Build'!H$43*Assumptions!$C$84/365 -> 573.14217 | I15: ='Revenue Build'!I$43*Assumptions!$C$84/365 -> 621.50501 | J15: ='Revenue Build'!J$43*Assumptions!$C$84/365 -> 670.27215 | ... L15: ='Revenue Build'!L$43*Assumptions!$C$84/365 -> 780.6978
A16: Total current liabilities (excl. borrowings) | B16: Rs Lakh | C16: =C14+C15 -> 256.85661 | D16: =D14+D15 -> 423.59369 | E16: =E14+E15 -> 592.28307 | F16: =F14+F15 -> 726.72514 | G16: =G14+G15 -> 862.62645 | H16: =H14+H15 -> 957.56193 | I16: =I14+I15 -> 1036.8156 | J16: =J14+J15 -> 1116.706 | ... L16: =L14+L15 -> 1296.7908
A18: NET WORKING CAPITAL
A19: Net working capital | B19: Rs Lakh | C19: =C11-C16 -> 285.54125 | D19: =D11-D16 -> 496.6393 | E19: =E11-E16 -> 704.59515 | F19: =F11-F16 -> 871.71725 | G19: =G11-G16 -> 1016.4761 | H19: =H11-H16 -> 1134.407 | I19: =I11-I16 -> 1231.6777 | J19: =J11-J16 -> 1329.7873 | ... L19: =L11-L16 -> 1552.7562
A20: (Increase) / decrease in net working capital | B20: Rs Lakh | C20: =C19 -> 285.54125 | D20: =D19-C19 -> 211.09805 | E20: =E19-D19 -> 207.95585 | F20: =F19-E19 -> 167.1221 | G20: =G19-F19 -> 144.75887 | H20: =H19-G19 -> 117.93087 | I20: =I19-H19 -> 97.270701 | J20: =J19-I19 -> 98.109618 | K20: =K19-J19 -> 108.70371 | L20: =L19-K19 -> 114.26515 | N20: A cash OUTFLOW when positive — growth consumes working capital
A21: Net working capital in days of revenue | B21: days | C21: =C19/'Revenue Build'!C$43*365 -> 34.587268 | D21: =D19/'Revenue Build'!D$43*365 -> 35.457544 | E21: =E19/'Revenue Build'!E$43*365 -> 35.694872 | F21: =F19/'Revenue Build'!F$43*365 -> 35.82977 | G21: =G19/'Revenue Build'!G$43*365 -> 35.539561 | H21: =H19/'Revenue Build'!H$43*365 -> 35.626982 | I21: =I19/'Revenue Build'!I$43*365 -> 35.671794 | J21: =J19/'Revenue Build'!J$43*365 -> 35.711124 | ... L21: =L19/'Revenue Build'!L$43*365 -> 35.800806
A22: Cash conversion cycle | B22: days | C22: =C7+Assumptions!$C$81-Assumptions!$C$82 -> 27.95 | D22: =D7+Assumptions!$C$81-Assumptions!$C$82 -> 27.95 | E22: =E7+Assumptions!$C$81-Assumptions!$C$82 -> 27.95 | F22: =F7+Assumptions!$C$81-Assumptions!$C$82 -> 27.95 | G22: =G7+Assumptions!$C$81-Assumptions!$C$82 -> 27.95 | H22: =H7+Assumptions!$C$81-Assumptions!$C$82 -> 27.95 | I22: =I7+Assumptions!$C$81-Assumptions!$C$82 -> 27.95 | J22: =J7+Assumptions!$C$81-Assumptions!$C$82 -> 27.95 | ... L22: =L7+Assumptions!$C$81-Assumptions!$C$82 -> 27.95 | N22: Debtor days + inventory days - creditor days
A24: Why this matters: switch the Control Panel payer mix to 'Government-heavy' and watch debtor days jump from 48 to 64.
A25: On roughly Rs 100 Cr of mature revenue that is about Rs 4.5 Cr of additional permanent working capital — funded by debt,
A26: at 11.5%. Government schemes look like free volume until you price the receivable.

Sheet Repayment Schedule
A1: TERM LOAN — QUARTERLY REPAYMENT SCHEDULE
A2: 6 construction quarters (drawdown) + 12 moratorium quarters + 28 quarterly instalments = 46 quarters, ~11.5 years door-to-door. Rs Lakh.
A5: Sanctioned term loan | C5: ='Capex & Funding'!$C$32 -> 7754.2557 | E5: Moratorium: interest is serviced from the promoter support facility during construction and
A6: Interest rate p.a. | C6: =Assumptions!$C$106 -> 0.1075 | E6: the 36 months after COD. Principal repayment begins in operating Year 4, at quarter 19 overall.
A7: Quarterly rate | C7: =$C$6/4 -> 0.026875 | E7: The ladder is back-ended deliberately, to match the occupancy ramp rather than fight it.
A9: Qtr | B9: Phase | C9: Opening principal | D9: Drawdown | E9: Principal repaid | F9: Interest accrued | G9: Total debt service | H9: Closing principal | I9: Cumulative repaid
A10: Q1 | B10: Construction | C10: =0 -> 0 | D10: =$C$5*0.06 -> 465.25534 | E10: =0 -> 0 | F10: =(C10+D10/2-E10/2)*$C$7 -> 6.2518687 | G10: =E10+F10 -> 6.2518687 | H10: =C10+D10-E10 -> 465.25534 | I10: =E10 -> 0
A11: Q2 | B11: Construction | C11: =H10 -> 465.25534 | D11: =$C$5*0.12 -> 930.51069 | E11: =0 -> 0 | F11: =(C11+D11/2-E11/2)*$C$7 -> 25.007475 | G11: =E11+F11 -> 25.007475 | H11: =C11+D11-E11 -> 1395.766 | I11: =I10+E11 -> 0
A12: Q3 | B12: Construction | C12: =H11 -> 1395.766 | D12: =$C$5*0.2 -> 1550.8511 | E12: =0 -> 0 | F12: =(C12+D12/2-E12/2)*$C$7 -> 58.350774 | G12: =E12+F12 -> 58.350774 | H12: =C12+D12-E12 -> 2946.6172 | I12: =I11+E12 -> 0
A13: Q4 | B13: Construction | C13: =H12 -> 2946.6172 | D13: =$C$5*0.24 -> 1861.0214 | E13: =0 -> 0 | F13: =(C13+D13/2-E13/2)*$C$7 -> 104.19781 | G13: =E13+F13 -> 104.19781 | H13: =C13+D13-E13 -> 4807.6386 | I13: =I12+E13 -> 0
A14: Q5 | B14: Construction | C14: =H13 -> 4807.6386 | D14: =$C$5*0.22 -> 1705.9363 | E14: =0 -> 0 | F14: =(C14+D14/2-E14/2)*$C$7 -> 152.1288 | G14: =E14+F14 -> 152.1288 | H14: =C14+D14-E14 -> 6513.5748 | I14: =I13+E14 -> 0
A15: Q6 | B15: Construction | C15: =H14 -> 6513.5748 | D15: =$C$5*0.16 -> 1240.6809 | E15: =0 -> 0 | F15: =(C15+D15/2-E15/2)*$C$7 -> 191.72397 | G15: =E15+F15 -> 191.72397 | H15: =C15+D15-E15 -> 7754.2557 | I15: =I14+E15 -> 0
A16: Q7 | B16: Moratorium | C16: =H15 -> 7754.2557 | D16: =0 -> 0 | E16: =0 -> 0 | F16: =(C16+D16/2-E16/2)*$C$7 -> 208.39562 | G16: =E16+F16 -> 208.39562 | H16: =C16+D16-E16 -> 7754.2557 | I16: =I15+E16 -> 0
A17: Q8 | B17: Moratorium | C17: =H16 -> 7754.2557 | D17: =0 -> 0 | E17: =0 -> 0 | F17: =(C17+D17/2-E17/2)*$C$7 -> 208.39562 | G17: =E17+F17 -> 208.39562 | H17: =C17+D17-E17 -> 7754.2557 | I17: =I16+E17 -> 0
A18: Q9 | B18: Moratorium | C18: =H17 -> 7754.2557 | D18: =0 -> 0 | E18: =0 -> 0 | F18: =(C18+D18/2-E18/2)*$C$7 -> 208.39562 | G18: =E18+F18 -> 208.39562 | H18: =C18+D18-E18 -> 7754.2557 | I18: =I17+E18 -> 0
A19: Q10 | B19: Moratorium | C19: =H18 -> 7754.2557 | D19: =0 -> 0 | E19: =0 -> 0 | F19: =(C19+D19/2-E19/2)*$C$7 -> 208.39562 | G19: =E19+F19 -> 208.39562 | H19: =C19+D19-E19 -> 7754.2557 | I19: =I18+E19 -> 0
A20: Q11 | B20: Moratorium | C20: =H19 -> 7754.2557 | D20: =0 -> 0 | E20: =0 -> 0 | F20: =(C20+D20/2-E20/2)*$C$7 -> 208.39562 | G20: =E20+F20 -> 208.39562 | H20: =C20+D20-E20 -> 7754.2557 | I20: =I19+E20 -> 0
A21: Q12 | B21: Moratorium | C21: =H20 -> 7754.2557 | D21: =0 -> 0 | E21: =0 -> 0 | F21: =(C21+D21/2-E21/2)*$C$7 -> 208.39562 | G21: =E21+F21 -> 208.39562 | H21: =C21+D21-E21 -> 7754.2557 | I21: =I20+E21 -> 0
A22: Q13 | B22: Moratorium | C22: =H21 -> 7754.2557 | D22: =0 -> 0 | E22: =0 -> 0 | F22: =(C22+D22/2-E22/2)*$C$7 -> 208.39562 | G22: =E22+F22 -> 208.39562 | H22: =C22+D22-E22 -> 7754.2557 | I22: =I21+E22 -> 0
A23: Q14 | B23: Moratorium | C23: =H22 -> 7754.2557 | D23: =0 -> 0 | E23: =0 -> 0 | F23: =(C23+D23/2-E23/2)*$C$7 -> 208.39562 | G23: =E23+F23 -> 208.39562 | H23: =C23+D23-E23 -> 7754.2557 | I23: =I22+E23 -> 0
A24: Q15 | B24: Moratorium | C24: =H23 -> 7754.2557 | D24: =0 -> 0 | E24: =0 -> 0 | F24: =(C24+D24/2-E24/2)*$C$7 -> 208.39562 | G24: =E24+F24 -> 208.39562 | H24: =C24+D24-E24 -> 7754.2557 | I24: =I23+E24 -> 0
A25: Q16 | B25: Moratorium | C25: =H24 -> 7754.2557 | D25: =0 -> 0 | E25: =0 -> 0 | F25: =(C25+D25/2-E25/2)*$C$7 -> 208.39562 | G25: =E25+F25 -> 208.39562 | H25: =C25+D25-E25 -> 7754.2557 | I25: =I24+E25 -> 0
A26: Q17 | B26: Moratorium | C26: =H25 -> 7754.2557 | D26: =0 -> 0 | E26: =0 -> 0 | F26: =(C26+D26/2-E26/2)*$C$7 -> 208.39562 | G26: =E26+F26 -> 208.39562 | H26: =C26+D26-E26 -> 7754.2557 | I26: =I25+E26 -> 0
A27: Q18 | B27: Moratorium | C27: =H26 -> 7754.2557 | D27: =0 -> 0 | E27: =0 -> 0 | F27: =(C27+D27/2-E27/2)*$C$7 -> 208.39562 | G27: =E27+F27 -> 208.39562 | H27: =C27+D27-E27 -> 7754.2557 | I27: =I26+E27 -> 0
A28: Q19 | B28: Repayment | C28: =H27 -> 7754.2557 | D28: =0 -> 0 | E28: =$C$5*0.015 -> 116.31384 | F28: =(C28+D28/2-E28/2)*$C$7 -> 206.83266 | G28: =E28+F28 -> 323.14649 | H28: =C28+D28-E28 -> 7637.9419 | I28: =I27+E28 -> 116.31384
A29: Q20 | B29: Repayment | C29: =H28 -> 7637.9419 | D29: =0 -> 0 | E29: =$C$5*0.015 -> 116.31384 | F29: =(C29+D29/2-E29/2)*$C$7 -> 203.70672 | G29: =E29+F29 -> 320.02056 | H29: =C29+D29-E29 -> 7521.6281 | I29: =I28+E29 -> 232.62767
A30: Q21 | B30: Repayment | C30: =H29 -> 7521.6281 | D30: =0 -> 0 | E30: =$C$5*0.015 -> 116.31384 | F30: =(C30+D30/2-E30/2)*$C$7 -> 200.58079 | G30: =E30+F30 -> 316.89462 | H30: =C30+D30-E30 -> 7405.3142 | I30: =I29+E30 -> 348.94151
A31: Q22 | B31: Repayment | C31: =H30 -> 7405.3142 | D31: =0 -> 0 | E31: =$C$5*0.015 -> 116.31384 | F31: =(C31+D31/2-E31/2)*$C$7 -> 197.45485 | G31: =E31+F31 -> 313.76869 | H31: =C31+D31-E31 -> 7289.0004 | I31: =I30+E31 -> 465.25534
A32: Q23 | B32: Repayment | C32: =H31 -> 7289.0004 | D32: =0 -> 0 | E32: =$C$5*0.025 -> 193.85639 | F32: =(C32+D32/2-E32/2)*$C$7 -> 193.28694 | G32: =E32+F32 -> 387.14333 | H32: =C32+D32-E32 -> 7095.144 | I32: =I31+E32 -> 659.11174
A33: Q24 | B33: Repayment | C33: =H32 -> 7095.144 | D33: =0 -> 0 | E33: =$C$5*0.025 -> 193.85639 | F33: =(C33+D33/2-E33/2)*$C$7 -> 188.07705 | G33: =E33+F33 -> 381.93344 | H33: =C33+D33-E33 -> 6901.2876 | I33: =I32+E33 -> 852.96813
A34: Q25 | B34: Repayment | C34: =H33 -> 6901.2876 | D34: =0 -> 0 | E34: =$C$5*0.025 -> 193.85639 | F34: =(C34+D34/2-E34/2)*$C$7 -> 182.86716 | G34: =E34+F34 -> 376.72355 | H34: =C34+D34-E34 -> 6707.4312 | I34: =I33+E34 -> 1046.8245
A35: Q26 | B35: Repayment | C35: =H34 -> 6707.4312 | D35: =0 -> 0 | E35: =$C$5*0.025 -> 193.85639 | F35: =(C35+D35/2-E35/2)*$C$7 -> 177.65727 | G35: =E35+F35 -> 371.51366 | H35: =C35+D35-E35 -> 6513.5748 | I35: =I34+E35 -> 1240.6809
A36: Q27 | B36: Repayment | C36: =H35 -> 6513.5748 | D36: =0 -> 0 | E36: =$C$5*0.0325 -> 252.01331 | F36: =(C36+D36/2-E36/2)*$C$7 -> 171.66589 | G36: =E36+F36 -> 423.67921 | H36: =C36+D36-E36 -> 6261.5615 | I36: =I35+E36 -> 1492.6942
A37: Q28 | B37: Repayment | C37: =H36 -> 6261.5615 | D37: =0 -> 0 | E37: =$C$5*0.0325 -> 252.01331 | F37: =(C37+D37/2-E37/2)*$C$7 -> 164.89304 | G37: =E37+F37 -> 416.90635 | H37: =C37+D37-E37 -> 6009.5482 | I37: =I36+E37 -> 1744.7075
A38: Q29 | B38: Repayment | C38: =H37 -> 6009.5482 | D38: =0 -> 0 | E38: =$C$5*0.0325 -> 252.01331 | F38: =(C38+D38/2-E38/2)*$C$7 -> 158.12018 | G38: =E38+F38 -> 410.13349 | H38: =C38+D38-E38 -> 5757.5349 | I38: =I37+E38 -> 1996.7208
A39: Q30 | B39: Repayment | C39: =H38 -> 5757.5349 | D39: =0 -> 0 | E39: =$C$5*0.0325 -> 252.01331 | F39: =(C39+D39/2-E39/2)*$C$7 -> 151.34732 | G39: =E39+F39 -> 403.36063 | H39: =C39+D39-E39 -> 5505.5216 | I39: =I38+E39 -> 2248.7342
A40: Q31 | B40: Repayment | C40: =H39 -> 5505.5216 | D40: =0 -> 0 | E40: =$C$5*0.0375 -> 290.78459 | F40: =(C40+D40/2-E40/2)*$C$7 -> 144.05347 | G40: =E40+F40 -> 434.83806 | H40: =C40+D40-E40 -> 5214.737 | I40: =I39+E40 -> 2539.5188
A41: Q32 | B41: Repayment | C41: =H40 -> 5214.737 | D41: =0 -> 0 | E41: =$C$5*0.0375 -> 290.78459 | F41: =(C41+D41/2-E41/2)*$C$7 -> 136.23864 | G41: =E41+F41 -> 427.02323 | H41: =C41+D41-E41 -> 4923.9524 | I41: =I40+E41 -> 2830.3033
A42: Q33 | B42: Repayment | C42: =H41 -> 4923.9524 | D42: =0 -> 0 | E42: =$C$5*0.0375 -> 290.78459 | F42: =(C42+D42/2-E42/2)*$C$7 -> 128.4238 | G42: =E42+F42 -> 419.20839 | H42: =C42+D42-E42 -> 4633.1678 | I42: =I41+E42 -> 3121.0879
A43: Q34 | B43: Repayment | C43: =H42 -> 4633.1678 | D43: =0 -> 0 | E43: =$C$5*0.0375 -> 290.78459 | F43: =(C43+D43/2-E43/2)*$C$7 -> 120.60897 | G43: =E43+F43 -> 411.39356 | H43: =C43+D43-E43 -> 4342.3832 | I43: =I42+E43 -> 3411.8725
A44: Q35 | B44: Repayment | C44: =H43 -> 4342.3832 | D44: =0 -> 0 | E44: =$C$5*0.0425 -> 329.55587 | F44: =(C44+D44/2-E44/2)*$C$7 -> 112.27314 | G44: =E44+F44 -> 441.82901 | H44: =C44+D44-E44 -> 4012.8273 | I44: =I43+E44 -> 3741.4284
A45: Q36 | B45: Repayment | C45: =H44 -> 4012.8273 | D45: =0 -> 0 | E45: =$C$5*0.0425 -> 329.55587 | F45: =(C45+D45/2-E45/2)*$C$7 -> 103.41633 | G45: =E45+F45 -> 432.9722 | H45: =C45+D45-E45 -> 3683.2715 | I45: =I44+E45 -> 4070.9843
A46: Q37 | B46: Repayment | C46: =H45 -> 3683.2715 | D46: =0 -> 0 | E46: =$C$5*0.0425 -> 329.55587 | F46: =(C46+D46/2-E46/2)*$C$7 -> 94.559514 | G46: =E46+F46 -> 424.11538 | H46: =C46+D46-E46 -> 3353.7156 | I46: =I45+E46 -> 4400.5401
A47: Q38 | B47: Repayment | C47: =H46 -> 3353.7156 | D47: =0 -> 0 | E47: =$C$5*0.0425 -> 329.55587 | F47: =(C47+D47/2-E47/2)*$C$7 -> 85.7027 | G47: =E47+F47 -> 415.25857 | H47: =C47+D47-E47 -> 3024.1597 | I47: =I46+E47 -> 4730.096
A48: Q39 | B48: Repayment | C48: =H47 -> 3024.1597 | D48: =0 -> 0 | E48: =$C$5*0.0475 -> 368.32715 | F48: =(C48+D48/2-E48/2)*$C$7 -> 76.324897 | G48: =E48+F48 -> 444.65204 | H48: =C48+D48-E48 -> 2655.8326 | I48: =I47+E48 -> 5098.4231
A49: Q40 | B49: Repayment | C49: =H48 -> 2655.8326 | D49: =0 -> 0 | E49: =$C$5*0.0475 -> 368.32715 | F49: =(C49+D49/2-E49/2)*$C$7 -> 66.426105 | G49: =E49+F49 -> 434.75325 | H49: =C49+D49-E49 -> 2287.5054 | I49: =I48+E49 -> 5466.7503
A50: Q41 | B50: Repayment | C50: =H49 -> 2287.5054 | D50: =0 -> 0 | E50: =$C$5*0.0475 -> 368.32715 | F50: =(C50+D50/2-E50/2)*$C$7 -> 56.527313 | G50: =E50+F50 -> 424.85446 | H50: =C50+D50-E50 -> 1919.1783 | I50: =I49+E50 -> 5835.0774
A51: Q42 | B51: Repayment | C51: =H50 -> 1919.1783 | D51: =0 -> 0 | E51: =$C$5*0.0475 -> 368.32715 | F51: =(C51+D51/2-E51/2)*$C$7 -> 46.628521 | G51: =E51+F51 -> 414.95567 | H51: =C51+D51-E51 -> 1550.8511 | I51: =I50+E51 -> 6203.4046
A52: Q43 | B52: Repayment | C52: =H51 -> 1550.8511 | D52: =0 -> 0 | E52: =$C$5*0.05 -> 387.71279 | F52: =(C52+D52/2-E52/2)*$C$7 -> 36.469234 | G52: =E52+F52 -> 424.18202 | H52: =C52+D52-E52 -> 1163.1384 | I52: =I51+E52 -> 6591.1174
A53: Q44 | B53: Repayment | C53: =H52 -> 1163.1384 | D53: =0 -> 0 | E53: =$C$5*0.05 -> 387.71279 | F53: =(C53+D53/2-E53/2)*$C$7 -> 26.049453 | G53: =E53+F53 -> 413.76224 | H53: =C53+D53-E53 -> 775.42557 | I53: =I52+E53 -> 6978.8302
A54: Q45 | B54: Repayment | C54: =H53 -> 775.42557 | D54: =0 -> 0 | E54: =$C$5*0.05 -> 387.71279 | F54: =(C54+D54/2-E54/2)*$C$7 -> 15.629672 | G54: =E54+F54 -> 403.34246 | H54: =C54+D54-E54 -> 387.71279 | I54: =I53+E54 -> 7366.5429
A55: Q46 | B55: Repayment | C55: =H54 -> 387.71279 | D55: =0 -> 0 | E55: =$C$5*0.05 -> 387.71279 | F55: =(C55+D55/2-E55/2)*$C$7 -> 5.2098906 | G55: =E55+F55 -> 392.92268 | H55: =C55+D55-E55 -> -1.8189894e-12 | I55: =I54+E55 -> 7754.2557
A56: Total | D56: =SUM(D10:D55) -> 7754.2557 | E56: =SUM(E10:E55) -> 7754.2557 | F56: =SUM(F10:F55) -> 6489.4397 | G56: =SUM(G10:G55) -> 14243.695
A58: Integrity check — total principal repaid must equal the sanction | E58: =IF(ABS(E56-C5)<1,"OK","ERROR") -> OK
A59: Number of principal instalments | E59: =COUNTIF(E10:E55,">0") -> 28
A60: Total interest paid over the life of the loan | E60: =F56 -> 6489.4397
A61: Total interest as % of sanction | E61: =F56/C5 -> 0.8368875

Sheet Debt Schedule
A1: DEBT SCHEDULE — ANNUAL
A2: Term loan plus the working-capital facility. Operating Year 1 begins after COD. Rs Lakh.
A4: Particulars | B4: Basis | C4: Year 1 | D4: Year 2 | E4: Year 3 | F4: Year 4 | G4: Year 5 | H4: Year 6 | I4: Year 7 | J4: Year 8 | K4: Year 9 | L4: Year 10
A5: Financial year | C5: FY2029 | D5: FY2030 | E5: FY2031 | F5: FY2032 | G5: FY2033 | H5: FY2034 | I5: FY2035 | J5: FY2036 | K5: FY2037 | L5: FY2038
A6: Term loan
A7: Opening balance | B7: Rs Lakh | C7: ='Capex & Funding'!$C$32 -> 7754.2557 | D7: =C11 -> 7754.2557 | E7: =D11 -> 7754.2557 | F7: =E11 -> 7754.2557 | G7: =F11 -> 7289.0004 | H7: =G11 -> 6513.5748 | I7: =H11 -> 5505.5216 | J7: =I11 -> 4342.3832 | K7: =J11 -> 3024.1597 | L7: =K11 -> 1550.8511
A8: Repayment ladder — % of sanction | B8: % | C8: =Assumptions!C$118 -> 0 | D8: =Assumptions!D$118 -> 0 | E8: =Assumptions!E$118 -> 0 | F8: =Assumptions!F$118 -> 0.06 | G8: =Assumptions!G$118 -> 0.1 | H8: =Assumptions!H$118 -> 0.13 | I8: =Assumptions!I$118 -> 0.15 | J8: =Assumptions!J$118 -> 0.17 | ... L8: =Assumptions!L$118 -> 0.2
A9: Principal repaid | B9: Rs Lakh | C9: ='Capex & Funding'!$C$32*C8 -> 0 | D9: ='Capex & Funding'!$C$32*D8 -> 0 | E9: ='Capex & Funding'!$C$32*E8 -> 0 | F9: ='Capex & Funding'!$C$32*F8 -> 465.25534 | G9: ='Capex & Funding'!$C$32*G8 -> 775.42557 | H9: ='Capex & Funding'!$C$32*H8 -> 1008.0532 | I9: ='Capex & Funding'!$C$32*I8 -> 1163.1384 | J9: ='Capex & Funding'!$C$32*J8 -> 1318.2235 | ... L9: ='Capex & Funding'!$C$32*L8 -> 1550.8511
A10: Interest on term loan | B10: Rs Lakh | C10: =(C7-C9/2)*Assumptions!$C$106 -> 833.58249 | D10: =(D7-D9/2)*Assumptions!$C$106 -> 833.58249 | E10: =(E7-E9/2)*Assumptions!$C$106 -> 833.58249 | F10: =(F7-F9/2)*Assumptions!$C$106 -> 808.57502 | G10: =(G7-G9/2)*Assumptions!$C$106 -> 741.88842 | H10: =(H7-H9/2)*Assumptions!$C$106 -> 646.02643 | I10: =(I7-I9/2)*Assumptions!$C$106 -> 529.32488 | J10: =(J7-J9/2)*Assumptions!$C$106 -> 395.95168 | ... L10: =(L7-L9/2)*Assumptions!$C$106 -> 83.358249 | N10: Interest on the average balance during the year
A11: Closing balance | B11: Rs Lakh | C11: =MAX(C7-C9,0) -> 7754.2557 | D11: =MAX(D7-D9,0) -> 7754.2557 | E11: =MAX(E7-E9,0) -> 7754.2557 | F11: =MAX(F7-F9,0) -> 7289.0004 | G11: =MAX(G7-G9,0) -> 6513.5748 | H11: =MAX(H7-H9,0) -> 5505.5216 | I11: =MAX(I7-I9,0) -> 4342.3832 | J11: =MAX(J7-J9,0) -> 3024.1597 | ... L11: =MAX(L7-L9,0) -> 0
A13: Working-capital facility (cash credit)
A14: Sanctioned limit | B14: Rs Lakh | C14: =Assumptions!$C$113 -> 900 | D14: =Assumptions!$C$113 -> 900 | E14: =Assumptions!$C$113 -> 900 | F14: =Assumptions!$C$113 -> 900 | G14: =Assumptions!$C$113 -> 900 | H14: =Assumptions!$C$113 -> 900 | I14: =Assumptions!$C$113 -> 900 | J14: =Assumptions!$C$113 -> 900 | ... L14: =Assumptions!$C$113 -> 900
A15: Utilisation | B15: % | C15: =Assumptions!C$119 -> 0.35 | D15: =Assumptions!D$119 -> 0.55 | E15: =Assumptions!E$119 -> 0.7 | F15: =Assumptions!F$119 -> 0.75 | G15: =Assumptions!G$119 -> 0.8 | H15: =Assumptions!H$119 -> 0.8 | I15: =Assumptions!I$119 -> 0.8 | J15: =Assumptions!J$119 -> 0.8 | ... L15: =Assumptions!L$119 -> 0.8
A16: Amount drawn | B16: Rs Lakh | C16: =C14*C15 -> 315 | D16: =D14*D15 -> 495 | E16: =E14*E15 -> 630 | F16: =F14*F15 -> 675 | G16: =G14*G15 -> 720 | H16: =H14*H15 -> 720 | I16: =I14*I15 -> 720 | J16: =J14*J15 -> 720 | ... L16: =L14*L15 -> 720
A17: Interest on working-capital facility | B17: Rs Lakh | C17: =C16*Assumptions!$C$114 -> 36.225 | D17: =D16*Assumptions!$C$114 -> 56.925 | E17: =E16*Assumptions!$C$114 -> 72.45 | F17: =F16*Assumptions!$C$114 -> 77.625 | G17: =G16*Assumptions!$C$114 -> 82.8 | H17: =H16*Assumptions!$C$114 -> 82.8 | I17: =I16*Assumptions!$C$114 -> 82.8 | J17: =J16*Assumptions!$C$114 -> 82.8 | ... L17: =L16*Assumptions!$C$114 -> 82.8
A18: Change in working-capital borrowing | B18: Rs Lakh | C18: =C16 -> 315 | D18: =D16-C16 -> 180 | E18: =E16-D16 -> 135 | F18: =F16-E16 -> 45 | G18: =G16-F16 -> 45 | H18: =H16-G16 -> 0 | I18: =I16-H16 -> 0 | J18: =J16-I16 -> 0 | K18: =K16-J16 -> 0 | L18: =L16-K16 -> 0
A20: TOTAL BORROWINGS & FINANCE COST
A21: Total borrowings (closing) | B21: Rs Lakh | C21: =C11+C16 -> 8069.2557 | D21: =D11+D16 -> 8249.2557 | E21: =E11+E16 -> 8384.2557 | F21: =F11+F16 -> 7964.0004 | G21: =G11+G16 -> 7233.5748 | H21: =H11+H16 -> 6225.5216 | I21: =I11+I16 -> 5062.3832 | J21: =J11+J16 -> 3744.1597 | ... L21: =L11+L16 -> 720
A22: Total finance cost | B22: Rs Lakh | C22: =C10+C17 -> 869.80749 | D22: =D10+D17 -> 890.50749 | E22: =E10+E17 -> 906.03249 | F22: =F10+F17 -> 886.20002 | G22: =G10+G17 -> 824.68842 | H22: =H10+H17 -> 728.82643 | I22: =I10+I17 -> 612.12488 | J22: =J10+J17 -> 478.75168 | ... L22: =L10+L17 -> 166.15825
A23: Total debt service (term-loan interest + principal) | B23: Rs Lakh | C23: =C10+C9 -> 833.58249 | D23: =D10+D9 -> 833.58249 | E23: =E10+E9 -> 833.58249 | F23: =F10+F9 -> 1273.8304 | G23: =G10+G9 -> 1517.314 | H23: =H10+H9 -> 1654.0797 | I23: =I10+I9 -> 1692.4632 | J23: =J10+J9 -> 1714.1752 | ... L23: =L10+L9 -> 1634.2094
A24: Effective blended cost of debt | B24: % | C24: =IFERROR(C22/((C7+C11)/2+C16),0) -> 0.10779278 | D24: =IFERROR(D22/((D7+D11)/2+D16),0) -> 0.10795004 | E24: =IFERROR(E22/((E7+E11)/2+E16),0) -> 0.10806356 | F24: =IFERROR(F22/((F7+F11)/2+F16),0) -> 0.10811763 | G24: =IFERROR(G22/((G7+G11)/2+G16),0) -> 0.10820854 | H24: =IFERROR(H22/((H7+H11)/2+H16),0) -> 0.10830243 | I24: =IFERROR(I22/((I7+I11)/2+I16),0) -> 0.10845678 | J24: =IFERROR(J22/((J7+J11)/2+J16),0) -> 0.10872636 | ... L24: =IFERROR(L22/((L7+L11)/2+L16),0) -> 0.11111101

Sheet P&L
A1: PROFIT & LOSS STATEMENT
A2: Rs Lakh. Tax computed under s.115BAA with business-loss carry-forward.
A4: Particulars | B4: Note | C4: Year 1 | D4: Year 2 | E4: Year 3 | F4: Year 4 | G4: Year 5 | H4: Year 6 | I4: Year 7 | J4: Year 8 | K4: Year 9 | L4: Year 10
A5: Financial year | C5: FY2029 | D5: FY2030 | E5: FY2031 | F5: FY2032 | G5: FY2033 | H5: FY2034 | I5: FY2035 | J5: FY2036 | K5: FY2037 | L5: FY2038
A6: Revenue from operations | B6: Rs Lakh | C6: ='Revenue Build'!C$43 -> 3013.3215 | D6: ='Revenue Build'!D$43 -> 5112.4055 | E6: ='Revenue Build'!E$43 -> 7204.879 | F6: ='Revenue Build'!F$43 -> 8880.2355 | G6: ='Revenue Build'!G$43 -> 10439.459 | H6: ='Revenue Build'!H$43 -> 11622.05 | I6: ='Revenue Build'!I$43 -> 12602.74 | J6: ='Revenue Build'!J$43 -> 13591.63 | ... L6: ='Revenue Build'!L$43 -> 15830.817
A8: Operating expenditure
A9: Consultant payout | B9: Rs Lakh | C9: ='Operating Costs'!C$7 -> 292.71814 | D9: ='Operating Costs'!D$7 -> 496.81206 | E9: ='Operating Costs'!E$7 -> 697.15482 | F9: ='Operating Costs'!F$7 -> 856.94686 | G9: ='Operating Costs'!G$7 -> 1004.9533 | H9: ='Operating Costs'!H$7 -> 1116.2946 | I9: ='Operating Costs'!I$7 -> 1204.2479 | J9: ='Operating Costs'!J$7 -> 1296.8489 | ... L9: ='Operating Costs'!L$7 -> 1503.6338
A10: Consumables — drugs, implants, disposables | B10: Rs Lakh | C10: ='Operating Costs'!C$8 -> 693.06394 | D10: ='Operating Costs'!D$8 -> 1175.8533 | E10: ='Operating Costs'!E$8 -> 1657.1222 | F10: ='Operating Costs'!F$8 -> 2042.4542 | G10: ='Operating Costs'!G$8 -> 2401.0755 | H10: ='Operating Costs'!H$8 -> 2673.0714 | I10: ='Operating Costs'!I$8 -> 2898.6303 | J10: ='Operating Costs'!J$8 -> 3126.0748 | ... L10: ='Operating Costs'!L$8 -> 3641.0878
A11: Employee benefit expense | B11: Rs Lakh | C11: ='Operating Costs'!C$12 -> 1493.9 | D11: ='Operating Costs'!D$12 -> 1857.168 | E11: ='Operating Costs'!E$12 -> 2146.2926 | F11: ='Operating Costs'!F$12 -> 2407.1837 | G11: ='Operating Costs'!G$12 -> 2645.6068 | H11: ='Operating Costs'!H$12 -> 2857.2554 | I11: ='Operating Costs'!I$12 -> 3085.8358 | J11: ='Operating Costs'!J$12 -> 3332.7027 | ... L11: ='Operating Costs'!L$12 -> 3887.2644
A12: Power & fuel | B12: Rs Lakh | C12: ='Operating Costs'!C$13 -> 200 | D12: ='Operating Costs'!D$13 -> 250 | E12: ='Operating Costs'!E$13 -> 310 | F12: ='Operating Costs'!F$13 -> 380 | G12: ='Operating Costs'!G$13 -> 460 | H12: ='Operating Costs'!H$13 -> 500 | I12: ='Operating Costs'!I$13 -> 530 | J12: ='Operating Costs'!J$13 -> 560 | ... L12: ='Operating Costs'!L$13 -> 620
A13: Outsourced services | B13: Rs Lakh | C13: ='Operating Costs'!C$14 -> 185 | D13: ='Operating Costs'!D$14 -> 215 | E13: ='Operating Costs'!E$14 -> 265 | F13: ='Operating Costs'!F$14 -> 300 | G13: ='Operating Costs'!G$14 -> 420 | H13: ='Operating Costs'!H$14 -> 445 | I13: ='Operating Costs'!I$14 -> 470 | J13: ='Operating Costs'!J$14 -> 495 | ... L13: ='Operating Costs'!L$14 -> 545
A14: Repairs & maintenance | B14: Rs Lakh | C14: ='Operating Costs'!C$15 -> 120 | D14: ='Operating Costs'!D$15 -> 145 | E14: ='Operating Costs'!E$15 -> 190 | F14: ='Operating Costs'!F$15 -> 240 | G14: ='Operating Costs'!G$15 -> 300 | H14: ='Operating Costs'!H$15 -> 330 | I14: ='Operating Costs'!I$15 -> 355 | J14: ='Operating Costs'!J$15 -> 380 | ... L14: ='Operating Costs'!L$15 -> 430
A15: Administrative & other expenses | B15: Rs Lakh | C15: ='Operating Costs'!C$16 -> 155 | D15: ='Operating Costs'!D$16 -> 180 | E15: ='Operating Costs'!E$16 -> 230 | F15: ='Operating Costs'!F$16 -> 300 | G15: ='Operating Costs'!G$16 -> 380 | H15: ='Operating Costs'!H$16 -> 410 | I15: ='Operating Costs'!I$16 -> 440 | J15: ='Operating Costs'!J$16 -> 470 | ... L15: ='Operating Costs'!L$16 -> 530
A16: Marketing & business development | B16: Rs Lakh | C16: ='Operating Costs'!C$17 -> 170 | D16: ='Operating Costs'!D$17 -> 175 | E16: ='Operating Costs'!E$17 -> 180 | F16: ='Operating Costs'!F$17 -> 185 | G16: ='Operating Costs'!G$17 -> 190 | H16: ='Operating Costs'!H$17 -> 200 | I16: ='Operating Costs'!I$17 -> 210 | J16: ='Operating Costs'!J$17 -> 220 | ... L16: ='Operating Costs'!L$17 -> 240
A17: Insurance, rates & taxes | B17: Rs Lakh | C17: ='Operating Costs'!C$18 -> 90 | D17: ='Operating Costs'!D$18 -> 100 | E17: ='Operating Costs'!E$18 -> 120 | F17: ='Operating Costs'!F$18 -> 140 | G17: ='Operating Costs'!G$18 -> 160 | H17: ='Operating Costs'!H$18 -> 172 | I17: ='Operating Costs'!I$18 -> 184 | J17: ='Operating Costs'!J$18 -> 196 | ... L17: ='Operating Costs'!L$18 -> 220
A18: Total operating expenditure | B18: Rs Lakh | C18: =SUM(C9:C17) -> 3399.6821 | D18: =SUM(D9:D17) -> 4594.8333 | E18: =SUM(E9:E17) -> 5795.5696 | F18: =SUM(F9:F17) -> 6851.5847 | G18: =SUM(G9:G17) -> 7961.6357 | H18: =SUM(H9:H17) -> 8703.6213 | I18: =SUM(I9:I17) -> 9377.714 | J18: =SUM(J9:J17) -> 10076.626 | ... L18: =SUM(L9:L17) -> 11616.986
A20: EBITDA | B20: Rs Lakh | C20: =C6-C18 -> -386.36061 | D20: =D6-D18 -> 517.57216 | E20: =E6-E18 -> 1409.3094 | F20: =F6-F18 -> 2028.6508 | G20: =G6-G18 -> 2477.8231 | H20: =H6-H18 -> 2918.4282 | I20: =I6-I18 -> 3225.0265 | J20: =J6-J18 -> 3515.0033 | ... L20: =L6-L18 -> 4213.8306
A21: EBITDA margin | B21: % | C21: =C20/C6 -> -0.12821752 | D21: =D20/D6 -> 0.10123848 | E21: =E20/E6 -> 0.19560486 | F21: =F20/F6 -> 0.22844561 | G21: =G20/G6 -> 0.23735168 | H21: =H20/H6 -> 0.25111132 | I21: =I20/I6 -> 0.25589882 | J21: =J20/J6 -> 0.25861529 | ... L21: =L20/L6 -> 0.26617898
A23: Depreciation & amortisation | B23: Rs Lakh | C23: =Depreciation!C$18 -> 613.87346 | D23: =Depreciation!D$18 -> 613.87346 | E23: =Depreciation!E$18 -> 655.12346 | F23: =Depreciation!F$18 -> 669.53322 | G23: =Depreciation!G$18 -> 687.29369 | H23: =Depreciation!H$18 -> 618.17261 | I23: =Depreciation!I$18 -> 607.24881 | J23: =Depreciation!J$18 -> 632.45429 | ... L23: =Depreciation!L$18 -> 689.00565
A24: EBIT / Operating profit | B24: Rs Lakh | C24: =C20-C23 -> -1000.2341 | D24: =D20-D23 -> -96.301299 | E24: =E20-E23 -> 754.18591 | F24: =F20-F23 -> 1359.1176 | G24: =G20-G23 -> 1790.5294 | H24: =H20-H23 -> 2300.2556 | I24: =I20-I23 -> 2617.7777 | J24: =J20-J23 -> 2882.549 | ... L24: =L20-L23 -> 3524.8249
A25: EBIT margin | B25: % | C25: =C24/C6 -> -0.33193739 | D25: =D24/D6 -> -0.018836788 | E25: =E24/E6 -> 0.10467711 | F25: =F24/F6 -> 0.15304972 | G25: =G24/G6 -> 0.17151554 | H25: =H24/H6 -> 0.19792168 | I25: =I24/I6 -> 0.20771495 | J25: =J24/J6 -> 0.21208266 | ... L25: =L24/L6 -> 0.22265591
A27: Finance cost | B27: Rs Lakh | C27: ='Debt Schedule'!C$22 -> 869.80749 | D27: ='Debt Schedule'!D$22 -> 890.50749 | E27: ='Debt Schedule'!E$22 -> 906.03249 | F27: ='Debt Schedule'!F$22 -> 886.20002 | G27: ='Debt Schedule'!G$22 -> 824.68842 | H27: ='Debt Schedule'!H$22 -> 728.82643 | I27: ='Debt Schedule'!I$22 -> 612.12488 | J27: ='Debt Schedule'!J$22 -> 478.75168 | ... L27: ='Debt Schedule'!L$22 -> 166.15825
A28: Profit before tax (PBT) | B28: Rs Lakh | C28: =C24-C27 -> -1870.0416 | D28: =D24-D27 -> -986.80879 | E28: =E24-E27 -> -151.84658 | F28: =F24-F27 -> 472.91759 | G28: =G24-G27 -> 965.84095 | H28: =H24-H27 -> 1571.4292 | I28: =I24-I27 -> 2005.6528 | J28: =J24-J27 -> 2403.7973 | ... L28: =L24-L27 -> 3358.6667
A30: Taxation — s.115BAA with loss carry-forward
A31: Accumulated loss brought forward | B31: Rs Lakh | C31: =0 -> 0 | D31: =C33 -> -1870.0416 | E31: =D33 -> -2856.8504 | F31: =E33 -> -3008.6969 | G31: =F33 -> -2535.7793 | H31: =G33 -> -1569.9384 | I31: =H33 -> 0 | J31: =I33 -> 0 | K31: =J33 -> 0 | L31: =K33 -> 0
A32: Taxable profit after set-off | B32: Rs Lakh | C32: =MAX(C28+C31,0) -> 0 | D32: =MAX(D28+D31,0) -> 0 | E32: =MAX(E28+E31,0) -> 0 | F32: =MAX(F28+F31,0) -> 0 | G32: =MAX(G28+G31,0) -> 0 | H32: =MAX(H28+H31,0) -> 1.4907729 | I32: =MAX(I28+I31,0) -> 2005.6528 | J32: =MAX(J28+J31,0) -> 2403.7973 | ... L32: =MAX(L28+L31,0) -> 3358.6667
A33: Accumulated loss carried forward | B33: Rs Lakh | C33: =MIN(C28+C31,0) -> -1870.0416 | D33: =MIN(D28+D31,0) -> -2856.8504 | E33: =MIN(E28+E31,0) -> -3008.6969 | F33: =MIN(F28+F31,0) -> -2535.7793 | G33: =MIN(G28+G31,0) -> -1569.9384 | H33: =MIN(H28+H31,0) -> 0 | I33: =MIN(I28+I31,0) -> 0 | J33: =MIN(J28+J31,0) -> 0 | ... L33: =MIN(L28+L31,0) -> 0
A34: Current tax @ 25.168% | B34: Rs Lakh | C34: =C32*Assumptions!$C$98 -> 0 | D34: =D32*Assumptions!$C$98 -> 0 | E34: =E32*Assumptions!$C$98 -> 0 | F34: =F32*Assumptions!$C$98 -> 0 | G34: =G32*Assumptions!$C$98 -> 0 | H34: =H32*Assumptions!$C$98 -> 0.37519772 | I34: =I32*Assumptions!$C$98 -> 504.78269 | J34: =J32*Assumptions!$C$98 -> 604.9877 | ... L34: =L32*Assumptions!$C$98 -> 845.30923
A35: Effective tax rate | B35: % | C35: =IFERROR(IF(C28>0,C34/C28,0),0) -> 0 | D35: =IFERROR(IF(D28>0,D34/D28,0),0) -> 0 | E35: =IFERROR(IF(E28>0,E34/E28,0),0) -> 0 | F35: =IFERROR(IF(F28>0,F34/F28,0),0) -> 0 | G35: =IFERROR(IF(G28>0,G34/G28,0),0) -> 0 | H35: =IFERROR(IF(H28>0,H34/H28,0),0) -> 0.00023876209 | I35: =IFERROR(IF(I28>0,I34/I28,0),0) -> 0.25168 | J35: =IFERROR(IF(J28>0,J34/J28,0),0) -> 0.25168 | ... L35: =IFERROR(IF(L28>0,L34/L28,0),0) -> 0.25168
A37: PROFIT AFTER TAX
A38: Profit after tax (PAT) | B38: Rs Lakh | C38: =C28-C34 -> -1870.0416 | D38: =D28-D34 -> -986.80879 | E38: =E28-E34 -> -151.84658 | F38: =F28-F34 -> 472.91759 | G38: =G28-G34 -> 965.84095 | H38: =H28-H34 -> 1571.054 | I38: =I28-I34 -> 1500.8701 | J38: =J28-J34 -> 1798.8096 | ... L38: =L28-L34 -> 2513.3575
A39: PAT margin | B39: % | C39: =C38/C6 -> -0.62059146 | D39: =D38/D6 -> -0.1930224 | E39: =E38/E6 -> -0.021075522 | F39: =F38/F6 -> 0.053255073 | G39: =G38/G6 -> 0.092518298 | H39: =H38/H6 -> 0.13517874 | I39: =I38/I6 -> 0.11909077 | J39: =J38/J6 -> 0.13234687 | ... L39: =L38/L6 -> 0.1587636
A40: Cumulative PAT | B40: Rs Lakh | C40: =C38 -> -1870.0416 | D40: =C40+D38 -> -2856.8504 | E40: =D40+E38 -> -3008.6969 | F40: =E40+F38 -> -2535.7793 | G40: =F40+G38 -> -1569.9384 | H40: =G40+H38 -> 1.1155752 | I40: =H40+I38 -> 1501.9857 | J40: =I40+J38 -> 3300.7952 | K40: =J40+K38 -> 5448.1636 | L40: =K40+L38 -> 7961.5211
A42: Common-size P&L (% of revenue)
A43: Consultant payout | B43: % | C43: =C9/C6 -> 0.097141357 | D43: =D9/D6 -> 0.09717775 | E43: =E9/E6 -> 0.096761489 | F43: =F9/F6 -> 0.096500465 | G43: =G9/G6 -> 0.096264889 | H43: =H9/H6 -> 0.096049717 | I43: =I9/I6 -> 0.095554446 | J43: =J9/J6 -> 0.095415261 | ... L43: =L9/L6 -> 0.094981442
A44: Consumables | B44: % | C44: =C10/C6 -> 0.23 | D44: =D10/D6 -> 0.23 | E44: =E10/E6 -> 0.23 | F44: =F10/F6 -> 0.23 | G44: =G10/G6 -> 0.23 | H44: =H10/H6 -> 0.23 | I44: =I10/I6 -> 0.23 | J44: =J10/J6 -> 0.23 | ... L44: =L10/L6 -> 0.23
A45: Employee benefits | B45: % | C45: =C11/C6 -> 0.49576523 | D45: =D11/D6 -> 0.36326696 | E45: =E11/E6 -> 0.29789434 | F45: =F11/F6 -> 0.27107205 | G45: =G11/G6 -> 0.25342375 | H45: =H11/H6 -> 0.24584781 | I45: =I11/I6 -> 0.24485435 | J45: =J11/J6 -> 0.24520258 | ... L45: =L11/L6 -> 0.24555047
A46: Power & fuel | B46: % | C46: =C12/C6 -> 0.066371943 | D46: =D12/D6 -> 0.04890066 | E46: =E12/E6 -> 0.043026399 | F46: =F12/F6 -> 0.042791658 | G46: =G12/G6 -> 0.044063587 | H46: =H12/H6 -> 0.043021672 | I46: =I12/I6 -> 0.042054345 | J46: =J12/J6 -> 0.041201829 | ... L46: =L12/L6 -> 0.03916412
A47: Outsourced services | B47: % | C47: =C13/C6 -> 0.061394047 | D47: =D13/D6 -> 0.042054567 | E47: =E13/E6 -> 0.036780632 | F47: =F13/F6 -> 0.033782888 | G47: =G13/G6 -> 0.040231971 | H47: =H13/H6 -> 0.038289288 | I47: =I13/I6 -> 0.037293476 | J47: =J13/J6 -> 0.036419474 | ... L47: =L13/L6 -> 0.034426525
A48: Repairs & maintenance | B48: % | C48: =C14/C6 -> 0.039823166 | D48: =D14/D6 -> 0.028362383 | E48: =E14/E6 -> 0.026371019 | F48: =F14/F6 -> 0.02702631 | G48: =G14/G6 -> 0.028737122 | H48: =H14/H6 -> 0.028394303 | I48: =I14/I6 -> 0.028168477 | J48: =J14/J6 -> 0.027958384 | ... L48: =L14/L6 -> 0.027162212
A49: Administrative & other | B49: % | C49: =C15/C6 -> 0.051438256 | D49: =D15/D6 -> 0.035208475 | E49: =E15/E6 -> 0.031922812 | F49: =F15/F6 -> 0.033782888 | G49: =G15/G6 -> 0.036400355 | H49: =H15/H6 -> 0.035277771 | I49: =I15/I6 -> 0.034913041 | J49: =J15/J6 -> 0.034580106 | ... L49: =L15/L6 -> 0.033479006
A50: Marketing | B50: % | C50: =C16/C6 -> 0.056416151 | D50: =D16/D6 -> 0.034230462 | E50: =E16/E6 -> 0.024983071 | F50: =F16/F6 -> 0.020832781 | G50: =G16/G6 -> 0.018200177 | H50: =H16/H6 -> 0.017208669 | I50: =I16/I6 -> 0.016663043 | J50: =J16/J6 -> 0.016186433 | ... L50: =L16/L6 -> 0.015160305
A51: Insurance & taxes | B51: % | C51: =C17/C6 -> 0.029867374 | D51: =D17/D6 -> 0.019560264 | E51: =E17/E6 -> 0.01665538 | F51: =F17/F6 -> 0.015765348 | G51: =G17/G6 -> 0.015326465 | H51: =H17/H6 -> 0.014799455 | I51: =I17/I6 -> 0.014599999 | J51: =J17/J6 -> 0.01442064 | ... L51: =L17/L6 -> 0.013896946
A52: Depreciation & amortisation | B52: % | C52: =C23/C6 -> 0.20371987 | D52: =D23/D6 -> 0.12007527 | E52: =E23/E6 -> 0.090927753 | F52: =F23/F6 -> 0.075395885 | G52: =G23/G6 -> 0.065836142 | H52: =H23/H6 -> 0.053189638 | I52: =I23/I6 -> 0.04818387 | J52: =J23/J6 -> 0.046532631 | ... L52: =L23/L6 -> 0.043523064
A53: Finance cost | B53: % | C53: =C27/C6 -> 0.28865407 | D53: =D27/D6 -> 0.17418561 | E53: =E27/E6 -> 0.12575263 | F53: =F27/F6 -> 0.099794652 | G53: =G27/G6 -> 0.078997239 | H53: =H27/H6 -> 0.062710663 | I53: =I27/I6 -> 0.048570776 | J53: =J27/J6 -> 0.035224009 | ... L53: =L27/L6 -> 0.010495874

Sheet Cash Flow
A1: CASH FLOW STATEMENT
A2: Rs Lakh. Opening cash in Year 1 = promoter support facility + margin money, less the upfront fee.
A4: Particulars | B4: Note | C4: Year 1 | D4: Year 2 | E4: Year 3 | F4: Year 4 | G4: Year 5 | H4: Year 6 | I4: Year 7 | J4: Year 8 | K4: Year 9 | L4: Year 10
A5: Financial year | C5: FY2029 | D5: FY2030 | E5: FY2031 | F5: FY2032 | G5: FY2033 | H5: FY2034 | I5: FY2035 | J5: FY2036 | K5: FY2037 | L5: FY2038
A6: A. Cash flow from operations
A7: EBITDA | B7: Rs Lakh | C7: ='P&L'!C$20 -> -386.36061 | D7: ='P&L'!D$20 -> 517.57216 | E7: ='P&L'!E$20 -> 1409.3094 | F7: ='P&L'!F$20 -> 2028.6508 | G7: ='P&L'!G$20 -> 2477.8231 | H7: ='P&L'!H$20 -> 2918.4282 | I7: ='P&L'!I$20 -> 3225.0265 | J7: ='P&L'!J$20 -> 3515.0033 | ... L7: ='P&L'!L$20 -> 4213.8306
A8: Less: current tax paid | B8: Rs Lakh | C8: =-'P&L'!C$34 -> 0 | D8: =-'P&L'!D$34 -> 0 | E8: =-'P&L'!E$34 -> 0 | F8: =-'P&L'!F$34 -> 0 | G8: =-'P&L'!G$34 -> 0 | H8: =-'P&L'!H$34 -> -0.37519772 | I8: =-'P&L'!I$34 -> -504.78269 | J8: =-'P&L'!J$34 -> -604.9877 | ... L8: =-'P&L'!L$34 -> -845.30923
A9: Less: increase in net working capital | B9: Rs Lakh | C9: =-'Working Capital'!C$20 -> -285.54125 | D9: =-'Working Capital'!D$20 -> -211.09805 | E9: =-'Working Capital'!E$20 -> -207.95585 | F9: =-'Working Capital'!F$20 -> -167.1221 | G9: =-'Working Capital'!G$20 -> -144.75887 | H9: =-'Working Capital'!H$20 -> -117.93087 | I9: =-'Working Capital'!I$20 -> -97.270701 | J9: =-'Working Capital'!J$20 -> -98.109618 | ... L9: =-'Working Capital'!L$20 -> -114.26515
A10: Net cash from operating activities | B10: Rs Lakh | C10: =SUM(C7:C9) -> -671.90186 | D10: =SUM(D7:D9) -> 306.47411 | E10: =SUM(E7:E9) -> 1201.3535 | F10: =SUM(F7:F9) -> 1861.5287 | G10: =SUM(G7:G9) -> 2333.0642 | H10: =SUM(H7:H9) -> 2800.1221 | I10: =SUM(I7:I9) -> 2622.9731 | J10: =SUM(J7:J9) -> 2811.9059 | ... L10: =SUM(L7:L9) -> 3254.2562
A12: B. Cash flow from investing
A13: Capital expenditure (maintenance + expansion) | B13: Rs Lakh | C13: =-Depreciation!C$8 -> 0 | D13: =-Depreciation!D$8 -> 0 | E13: =-Depreciation!E$8 -> -694.09758 | F13: =-Depreciation!F$8 -> -177.60471 | G13: =-Depreciation!G$8 -> -208.78917 | H13: =-Depreciation!H$8 -> -232.44099 | I13: =-Depreciation!I$8 -> -252.05481 | J13: =-Depreciation!J$8 -> -271.83259 | ... L13: =-Depreciation!L$8 -> -316.61633
A14: Net cash used in investing activities | B14: Rs Lakh | C14: =C13 -> 0 | D14: =D13 -> 0 | E14: =E13 -> -694.09758 | F14: =F13 -> -177.60471 | G14: =G13 -> -208.78917 | H14: =H13 -> -232.44099 | I14: =I13 -> -252.05481 | J14: =J13 -> -271.83259 | ... L14: =L13 -> -316.61633
A16: C. Cash flow from financing
A17: Finance cost paid | B17: Rs Lakh | C17: =-'P&L'!C$27 -> -869.80749 | D17: =-'P&L'!D$27 -> -890.50749 | E17: =-'P&L'!E$27 -> -906.03249 | F17: =-'P&L'!F$27 -> -886.20002 | G17: =-'P&L'!G$27 -> -824.68842 | H17: =-'P&L'!H$27 -> -728.82643 | I17: =-'P&L'!I$27 -> -612.12488 | J17: =-'P&L'!J$27 -> -478.75168 | ... L17: =-'P&L'!L$27 -> -166.15825
A18: Term loan principal repaid | B18: Rs Lakh | C18: =-'Debt Schedule'!C$9 -> 0 | D18: =-'Debt Schedule'!D$9 -> 0 | E18: =-'Debt Schedule'!E$9 -> 0 | F18: =-'Debt Schedule'!F$9 -> -465.25534 | G18: =-'Debt Schedule'!G$9 -> -775.42557 | H18: =-'Debt Schedule'!H$9 -> -1008.0532 | I18: =-'Debt Schedule'!I$9 -> -1163.1384 | J18: =-'Debt Schedule'!J$9 -> -1318.2235 | ... L18: =-'Debt Schedule'!L$9 -> -1550.8511
A19: Change in working-capital borrowing | B19: Rs Lakh | C19: ='Debt Schedule'!C$18 -> 315 | D19: ='Debt Schedule'!D$18 -> 180 | E19: ='Debt Schedule'!E$18 -> 135 | F19: ='Debt Schedule'!F$18 -> 45 | G19: ='Debt Schedule'!G$18 -> 45 | H19: ='Debt Schedule'!H$18 -> 0 | I19: ='Debt Schedule'!I$18 -> 0 | J19: ='Debt Schedule'!J$18 -> 0 | ... L19: ='Debt Schedule'!L$18 -> 0
A20: Net cash from financing activities | B20: Rs Lakh | C20: =SUM(C17:C19) -> -554.80749 | D20: =SUM(D17:D19) -> -710.50749 | E20: =SUM(E17:E19) -> -771.03249 | F20: =SUM(F17:F19) -> -1306.4554 | G20: =SUM(G17:G19) -> -1555.114 | H20: =SUM(H17:H19) -> -1736.8797 | I20: =SUM(I17:I19) -> -1775.2632 | J20: =SUM(J17:J19) -> -1796.9752 | ... L20: =SUM(L17:L19) -> -1717.0094
A22: MOVEMENT IN CASH
A23: Net increase / (decrease) in cash | B23: Rs Lakh | C23: =C10+C14+C20 -> -1226.7094 | D23: =D10+D14+D20 -> -404.03338 | E23: =E10+E14+E20 -> -263.77655 | F23: =F10+F14+F20 -> 377.46865 | G23: =G10+G14+G20 -> 569.16103 | H23: =H10+H14+H20 -> 830.80147 | I23: =I10+I14+I20 -> 595.65503 | J23: =J10+J14+J20 -> 743.09819 | ... L23: =L10+L14+L20 -> 1220.6305
A24: Opening cash & bank balance | B24: Rs Lakh | C24: =Assumptions!$C$112+'Capex & Funding'!$C$17-'Capex & Funding'!$C$42 -> 2052.4574 | D24: =C25 -> 825.74809 | E24: =D25 -> 421.71471 | F24: =E25 -> 157.93816 | G24: =F25 -> 535.40682 | H24: =G25 -> 1104.5678 | I24: =H25 -> 1935.3693 | J24: =I25 -> 2531.0243 | K24: =J25 -> 3274.1225 | L24: =K25 -> 4205.4352
A25: Closing cash & bank balance | B25: Rs Lakh | C25: =C24+C23 -> 825.74809 | D25: =D24+D23 -> 421.71471 | E25: =E24+E23 -> 157.93816 | F25: =F24+F23 -> 535.40682 | G25: =G24+G23 -> 1104.5678 | H25: =H24+H23 -> 1935.3693 | I25: =I24+I23 -> 2531.0243 | J25: =J24+J23 -> 3274.1225 | ... L25: =L24+L23 -> 5426.0657
A26: Minimum-cash covenant test (Rs 150 L) | C26: =IF(C25>=Assumptions!$C$85,"PASS","BREACH") -> PASS | D26: =IF(D25>=Assumptions!$C$85,"PASS","BREACH") -> PASS | E26: =IF(E25>=Assumptions!$C$85,"PASS","BREACH") -> PASS | F26: =IF(F25>=Assumptions!$C$85,"PASS","BREACH") -> PASS | G26: =IF(G25>=Assumptions!$C$85,"PASS","BREACH") -> PASS | H26: =IF(H25>=Assumptions!$C$85,"PASS","BREACH") -> PASS | I26: =IF(I25>=Assumptions!$C$85,"PASS","BREACH") -> PASS | J26: =IF(J25>=Assumptions!$C$85,"PASS","BREACH") -> PASS | ... L26: =IF(L25>=Assumptions!$C$85,"PASS","BREACH") -> PASS
A28: Free cash flow measures
A29: Free cash flow to firm (FCFF) — unlevered | B29: Rs Lakh | C29: ='P&L'!C$20-'Returns & IRR'!C$10-'Working Capital'!C$20-Depreciation!C$8 -> -671.90186 | D29: ='P&L'!D$20-'Returns & IRR'!D$10-'Working Capital'!D$20-Depreciation!D$8 -> 306.47411 | E29: ='P&L'!E$20-'Returns & IRR'!E$10-'Working Capital'!E$20-Depreciation!E$8 -> 507.25594 | F29: ='P&L'!F$20-'Returns & IRR'!F$10-'Working Capital'!F$20-Depreciation!F$8 -> 1428.0238 | G29: ='P&L'!G$20-'Returns & IRR'!G$10-'Working Capital'!G$20-Depreciation!G$8 -> 1673.6346 | H29: ='P&L'!H$20-'Returns & IRR'!H$10-'Working Capital'!H$20-Depreciation!H$8 -> 1989.128 | I29: ='P&L'!I$20-'Returns & IRR'!I$10-'Working Capital'!I$20-Depreciation!I$8 -> 2216.8587 | J29: ='P&L'!J$20-'Returns & IRR'!J$10-'Working Capital'!J$20-Depreciation!J$8 -> 2419.5811 | ... L29: ='P&L'!L$20-'Returns & IRR'!L$10-'Working Capital'!L$20-Depreciation!L$8 -> 2895.8212 | N29: EBITDA less notional tax on EBIT, less change in WC, less capex. Ignores financing.
A30: Free cash flow to equity (FCFE) — levered | B30: Rs Lakh | C30: ='P&L'!C$38+'P&L'!C$23-'Debt Schedule'!C$9-'Working Capital'!C$20-Depreciation!C$8+'Debt Schedule'!C$18 -> -1226.7094 | D30: ='P&L'!D$38+'P&L'!D$23-'Debt Schedule'!D$9-'Working Capital'!D$20-Depreciation!D$8+'Debt Schedule'!D$18 -> -404.03338 | E30: ='P&L'!E$38+'P&L'!E$23-'Debt Schedule'!E$9-'Working Capital'!E$20-Depreciation!E$8+'Debt Schedule'!E$18 -> -263.77655 | F30: ='P&L'!F$38+'P&L'!F$23-'Debt Schedule'!F$9-'Working Capital'!F$20-Depreciation!F$8+'Debt Schedule'!F$18 -> 377.46865 | G30: ='P&L'!G$38+'P&L'!G$23-'Debt Schedule'!G$9-'Working Capital'!G$20-Depreciation!G$8+'Debt Schedule'!G$18 -> 569.16103 | H30: ='P&L'!H$38+'P&L'!H$23-'Debt Schedule'!H$9-'Working Capital'!H$20-Depreciation!H$8+'Debt Schedule'!H$18 -> 830.80147 | I30: ='P&L'!I$38+'P&L'!I$23-'Debt Schedule'!I$9-'Working Capital'!I$20-Depreciation!I$8+'Debt Schedule'!I$18 -> 595.65503 | J30: ='P&L'!J$38+'P&L'!J$23-'Debt Schedule'!J$9-'Working Capital'!J$20-Depreciation!J$8+'Debt Schedule'!J$18 -> 743.09819 | ... L30: ='P&L'!L$38+'P&L'!L$23-'Debt Schedule'!L$9-'Working Capital'!L$20-Depreciation!L$8+'Debt Schedule'!L$18 -> 1220.6305 | N30: What is actually available to the shareholder
A31: Cumulative FCFE | B31: Rs Lakh | C31: =C30 -> -1226.7094 | D31: =C31+D30 -> -1630.7427 | E31: =D31+E30 -> -1894.5193 | F31: =E31+F30 -> -1517.0506 | G31: =F31+G30 -> -947.8896 | H31: =G31+H30 -> -117.08813 | I31: =H31+I30 -> 478.5669 | J31: =I31+J30 -> 1221.6651 | K31: =J31+K30 -> 2152.9778 | L31: =K31+L30 -> 3373.6082

Sheet Balance Sheet
A1: BALANCE SHEET
A2: Rs Lakh. The balance check at the bottom must read OK in every year.
A4: Particulars | B4: Note | C4: Year 1 | D4: Year 2 | E4: Year 3 | F4: Year 4 | G4: Year 5 | H4: Year 6 | I4: Year 7 | J4: Year 8 | K4: Year 9 | L4: Year 10
A5: Financial year | C5: FY2029 | D5: FY2030 | E5: FY2031 | F5: FY2032 | G5: FY2033 | H5: FY2034 | I5: FY2035 | J5: FY2036 | K5: FY2037 | L5: FY2038
A6: EQUITY & LIABILITIES
A7: Shareholders' funds
A8: Share capital & promoter contribution | B8: Rs Lakh | C8: ='Capex & Funding'!$C$33+Assumptions!$C$112 -> 5103.2525 | D8: ='Capex & Funding'!$C$33+Assumptions!$C$112 -> 5103.2525 | E8: ='Capex & Funding'!$C$33+Assumptions!$C$112 -> 5103.2525 | F8: ='Capex & Funding'!$C$33+Assumptions!$C$112 -> 5103.2525 | G8: ='Capex & Funding'!$C$33+Assumptions!$C$112 -> 5103.2525 | H8: ='Capex & Funding'!$C$33+Assumptions!$C$112 -> 5103.2525 | I8: ='Capex & Funding'!$C$33+Assumptions!$C$112 -> 5103.2525 | J8: ='Capex & Funding'!$C$33+Assumptions!$C$112 -> 5103.2525 | ... L8: ='Capex & Funding'!$C$33+Assumptions!$C$112 -> 5103.2525 | N8: Equity in the cost of project plus the promoter support facility
A9: Reserves & surplus | B9: Rs Lakh | C9: ='P&L'!C$38-'Capex & Funding'!$C$42 -> -1947.5841 | D9: =C9+'P&L'!D$38 -> -2934.3929 | E9: =D9+'P&L'!E$38 -> -3086.2395 | F9: =E9+'P&L'!F$38 -> -2613.3219 | G9: =F9+'P&L'!G$38 -> -1647.481 | H9: =G9+'P&L'!H$38 -> -76.426982 | I9: =H9+'P&L'!I$38 -> 1424.4431 | J9: =I9+'P&L'!J$38 -> 3223.2527 | K9: =J9+'P&L'!K$38 -> 5370.6211 | L9: =K9+'P&L'!L$38 -> 7883.9785 | N9: Upfront loan fee written off in Year 1
A10: Net worth | B10: Rs Lakh | C10: =C8+C9 -> 3155.6683 | D10: =D8+D9 -> 2168.8595 | E10: =E8+E9 -> 2017.013 | F10: =F8+F9 -> 2489.9305 | G10: =G8+G9 -> 3455.7715 | H10: =H8+H9 -> 5026.8255 | I10: =I8+I9 -> 6527.6956 | J10: =J8+J9 -> 8326.5051 | ... L10: =L8+L9 -> 12987.231
A12: Non-current liabilities
A13: Long-term borrowings (term loan) | B13: Rs Lakh | C13: ='Debt Schedule'!C$11 -> 7754.2557 | D13: ='Debt Schedule'!D$11 -> 7754.2557 | E13: ='Debt Schedule'!E$11 -> 7754.2557 | F13: ='Debt Schedule'!F$11 -> 7289.0004 | G13: ='Debt Schedule'!G$11 -> 6513.5748 | H13: ='Debt Schedule'!H$11 -> 5505.5216 | I13: ='Debt Schedule'!I$11 -> 4342.3832 | J13: ='Debt Schedule'!J$11 -> 3024.1597 | ... L13: ='Debt Schedule'!L$11 -> 0
A15: Current liabilities
A16: Short-term borrowings (working-capital facility) | B16: Rs Lakh | C16: ='Debt Schedule'!C$16 -> 315 | D16: ='Debt Schedule'!D$16 -> 495 | E16: ='Debt Schedule'!E$16 -> 630 | F16: ='Debt Schedule'!F$16 -> 675 | G16: ='Debt Schedule'!G$16 -> 720 | H16: ='Debt Schedule'!H$16 -> 720 | I16: ='Debt Schedule'!I$16 -> 720 | J16: ='Debt Schedule'!J$16 -> 720 | ... L16: ='Debt Schedule'!L$16 -> 720
A17: Trade payables | B17: Rs Lakh | C17: ='Working Capital'!C$14 -> 108.25446 | D17: ='Working Capital'!D$14 -> 171.47506 | E17: ='Working Capital'!E$14 -> 236.97397 | F17: ='Working Capital'!F$14 -> 288.79572 | G17: ='Working Capital'!G$14 -> 347.80383 | H17: ='Working Capital'!H$14 -> 384.41976 | I17: ='Working Capital'!I$14 -> 415.31059 | J17: ='Working Capital'!J$14 -> 446.43388 | ... L17: ='Working Capital'!L$14 -> 516.09302
A18: Other current liabilities & provisions | B18: Rs Lakh | C18: ='Working Capital'!C$15 -> 148.60215 | D18: ='Working Capital'!D$15 -> 252.11863 | E18: ='Working Capital'!E$15 -> 355.3091 | F18: ='Working Capital'!F$15 -> 437.92942 | G18: ='Working Capital'!G$15 -> 514.82262 | H18: ='Working Capital'!H$15 -> 573.14217 | I18: ='Working Capital'!I$15 -> 621.50501 | J18: ='Working Capital'!J$15 -> 670.27215 | ... L18: ='Working Capital'!L$15 -> 780.6978
A19: Total current liabilities | B19: Rs Lakh | C19: =C16+C17+C18 -> 571.85661 | D19: =D16+D17+D18 -> 918.59369 | E19: =E16+E17+E18 -> 1222.2831 | F19: =F16+F17+F18 -> 1401.7251 | G19: =G16+G17+G18 -> 1582.6265 | H19: =H16+H17+H18 -> 1677.5619 | I19: =I16+I17+I18 -> 1756.8156 | J19: =J16+J17+J18 -> 1836.706 | ... L19: =L16+L17+L18 -> 2016.7908
A21: TOTAL EQUITY & LIABILITIES | B21: Rs Lakh | C21: =C10+C13+C19 -> 11481.781 | D21: =D10+D13+D19 -> 10841.709 | E21: =E10+E13+E19 -> 10993.552 | F21: =F10+F13+F19 -> 11180.656 | G21: =G10+G13+G19 -> 11551.973 | H21: =H10+H13+H19 -> 12209.909 | I21: =I10+I13+I19 -> 12626.894 | J21: =J10+J13+J19 -> 13187.371 | ... L21: =L10+L13+L19 -> 15004.022
A23: ASSETS
A24: Non-current assets
A25: Property, plant & equipment (net block) | B25: Rs Lakh | C25: =Depreciation!C$22 -> 10113.635 | D25: =Depreciation!D$22 -> 9499.7613 | E25: =Depreciation!E$22 -> 9538.7354 | F25: =Depreciation!F$22 -> 9046.8069 | G25: =Depreciation!G$22 -> 8568.3024 | H25: =Depreciation!H$22 -> 8182.5707 | I25: =Depreciation!I$22 -> 7827.3767 | J25: =Depreciation!J$22 -> 7466.755 | ... L25: =Depreciation!L$22 -> 6728.4091
A27: Current assets
A28: Trade receivables | B28: Rs Lakh | C28: ='Working Capital'!C$8 -> 395.85963 | D28: ='Working Capital'!D$8 -> 671.61601 | E28: ='Working Capital'!E$8 -> 946.50397 | F28: ='Working Capital'!F$8 -> 1166.5953 | G28: ='Working Capital'!G$8 -> 1371.4303 | H28: ='Working Capital'!H$8 -> 1526.7871 | I28: ='Working Capital'!I$8 -> 1655.6203 | J28: ='Working Capital'!J$8 -> 1785.5305 | ... L28: ='Working Capital'!L$8 -> 2079.6922
A29: Inventories | B29: Rs Lakh | C29: ='Working Capital'!C$9 -> 47.470133 | D29: ='Working Capital'!D$9 -> 80.537895 | E29: ='Working Capital'!E$9 -> 113.50152 | F29: ='Working Capital'!F$9 -> 139.89412 | G29: ='Working Capital'!G$9 -> 164.45723 | H29: ='Working Capital'!H$9 -> 183.08708 | I29: ='Working Capital'!I$9 -> 198.53632 | J29: ='Working Capital'!J$9 -> 214.11471 | ... L29: ='Working Capital'!L$9 -> 249.38958
A30: Other current assets | B30: Rs Lakh | C30: ='Working Capital'!C$10 -> 99.068103 | D30: ='Working Capital'!D$10 -> 168.07908 | E30: ='Working Capital'!E$10 -> 236.87273 | F30: ='Working Capital'!F$10 -> 291.95295 | G30: ='Working Capital'!G$10 -> 343.21508 | H30: ='Working Capital'!H$10 -> 382.09478 | I30: ='Working Capital'!I$10 -> 414.33667 | J30: ='Working Capital'!J$10 -> 446.8481 | ... L30: ='Working Capital'!L$10 -> 520.4652
A31: Cash & bank balances | B31: Rs Lakh | C31: ='Cash Flow'!C$25 -> 825.74809 | D31: ='Cash Flow'!D$25 -> 421.71471 | E31: ='Cash Flow'!E$25 -> 157.93816 | F31: ='Cash Flow'!F$25 -> 535.40682 | G31: ='Cash Flow'!G$25 -> 1104.5678 | H31: ='Cash Flow'!H$25 -> 1935.3693 | I31: ='Cash Flow'!I$25 -> 2531.0243 | J31: ='Cash Flow'!J$25 -> 3274.1225 | ... L31: ='Cash Flow'!L$25 -> 5426.0657
A32: Total current assets | B32: Rs Lakh | C32: =C28+C29+C30+C31 -> 1368.146 | D32: =D28+D29+D30+D31 -> 1341.9477 | E32: =E28+E29+E30+E31 -> 1454.8164 | F32: =F28+F29+F30+F31 -> 2133.8492 | G32: =G28+G29+G30+G31 -> 2983.6704 | H32: =H28+H29+H30+H31 -> 4027.3382 | I32: =I28+I29+I30+I31 -> 4799.5176 | J32: =J28+J29+J30+J31 -> 5720.6159 | ... L32: =L28+L29+L30+L31 -> 8275.6127
A34: TOTAL ASSETS | B34: Rs Lakh | C34: =C25+C32 -> 11481.781 | D34: =D25+D32 -> 10841.709 | E34: =E25+E32 -> 10993.552 | F34: =F25+F32 -> 11180.656 | G34: =G25+G32 -> 11551.973 | H34: =H25+H32 -> 12209.909 | I34: =I25+I32 -> 12626.894 | J34: =J25+J32 -> 13187.371 | ... L34: =L25+L32 -> 15004.022
A36: BALANCE CHECK
A37: Assets less Equity & Liabilities | B37: Rs Lakh | C37: =C34-C21 -> 0 | D37: =D34-D21 -> 0 | E37: =E34-E21 -> 0 | F37: =F34-F21 -> 0 | G37: =G34-G21 -> 0 | H37: =H34-H21 -> 0 | I37: =I34-I21 -> 0 | J37: =J34-J21 -> 0 | ... L37: =L34-L21 -> 0
A38: Check | C38: =IF(ABS(C37)<0.01,"OK","ERROR") -> OK | D38: =IF(ABS(D37)<0.01,"OK","ERROR") -> OK | E38: =IF(ABS(E37)<0.01,"OK","ERROR") -> OK | F38: =IF(ABS(F37)<0.01,"OK","ERROR") -> OK | G38: =IF(ABS(G37)<0.01,"OK","ERROR") -> OK | H38: =IF(ABS(H37)<0.01,"OK","ERROR") -> OK | I38: =IF(ABS(I37)<0.01,"OK","ERROR") -> OK | J38: =IF(ABS(J37)<0.01,"OK","ERROR") -> OK | ... L38: =IF(ABS(L37)<0.01,"OK","ERROR") -> OK
A40: Balance sheet metrics
A41: Debt : Equity ratio | B41: x | C41: =IFERROR((C13+C16)/C10,0) -> 2.5570671 | D41: =IFERROR((D13+D16)/D10,0) -> 3.8034993 | E41: =IFERROR((E13+E16)/E10,0) -> 4.1567684 | F41: =IFERROR((F13+F16)/F10,0) -> 3.1984829 | G41: =IFERROR((G13+G16)/G10,0) -> 2.0931867 | H41: =IFERROR((H13+H16)/H10,0) -> 1.2384599 | I41: =IFERROR((I13+I16)/I10,0) -> 0.77552379 | J41: =IFERROR((J13+J16)/J10,0) -> 0.44966762 | ... L41: =IFERROR((L13+L16)/L10,0) -> 0.055439069
A42: Net debt | B42: Rs Lakh | C42: =C13+C16-C31 -> 7243.5076 | D42: =D13+D16-D31 -> 7827.541 | E42: =E13+E16-E31 -> 8226.3176 | F42: =F13+F16-F31 -> 7428.5936 | G42: =G13+G16-G31 -> 6129.007 | H42: =H13+H16-H31 -> 4290.1523 | I42: =I13+I16-I31 -> 2531.3589 | J42: =J13+J16-J31 -> 470.0372 | ... L42: =L13+L16-L31 -> -4706.0657
A43: Net debt / EBITDA | B43: x | C43: =IFERROR(IF('P&L'!C$20>0,C42/'P&L'!C$20,0),0) -> 0 | D43: =IFERROR(IF('P&L'!D$20>0,D42/'P&L'!D$20,0),0) -> 15.123574 | E43: =IFERROR(IF('P&L'!E$20>0,E42/'P&L'!E$20,0),0) -> 5.8371269 | F43: =IFERROR(IF('P&L'!F$20>0,F42/'P&L'!F$20,0),0) -> 3.6618394 | G43: =IFERROR(IF('P&L'!G$20>0,G42/'P&L'!G$20,0),0) -> 2.4735451 | H43: =IFERROR(IF('P&L'!H$20>0,H42/'P&L'!H$20,0),0) -> 1.4700215 | I43: =IFERROR(IF('P&L'!I$20>0,I42/'P&L'!I$20,0),0) -> 0.78491104 | J43: =IFERROR(IF('P&L'!J$20>0,J42/'P&L'!J$20,0),0) -> 0.13372312 | ... L43: =IFERROR(IF('P&L'!L$20>0,L42/'P&L'!L$20,0),0) -> -1.1168142 | N43: Lenders typically want this below 3.5x by the stabilised year
A44: Current ratio | B44: x | C44: =IFERROR(C32/C19,0) -> 2.3924633 | D44: =IFERROR(D32/D19,0) -> 1.4608719 | E44: =IFERROR(E32/E19,0) -> 1.1902451 | F44: =IFERROR(F32/F19,0) -> 1.5223022 | G44: =IFERROR(G32/G19,0) -> 1.8852651 | H44: =IFERROR(H32/H19,0) -> 2.4007091 | I44: =IFERROR(I32/I19,0) -> 2.7319416 | J44: =IFERROR(J32/J19,0) -> 3.1146061 | ... L44: =IFERROR(L32/L19,0) -> 4.103357
A45: Total outside liabilities / tangible net worth | B45: x | C45: =IFERROR((C13+C19)/C10,0) -> 2.6384624 | D45: =IFERROR((D13+D19)/D10,0) -> 3.9988064 | E45: =IFERROR((E13+E19)/E10,0) -> 4.450412 | F45: =IFERROR((F13+F19)/F10,0) -> 3.4903486 | G45: =IFERROR((G13+G19)/G10,0) -> 2.3428057 | H45: =IFERROR((H13+H19)/H10,0) -> 1.4289502 | I45: =IFERROR((I13+I19)/I10,0) -> 0.93435712 | J45: =IFERROR((J13+J19)/J10,0) -> 0.58378223 | ... L45: =IFERROR((L13+L19)/L10,0) -> 0.15529029

Sheet DSCR & Covenants
A1: DSCR & COVENANT COMPLIANCE
A2: Rs Lakh. Covenants are tested from the first principal-repayment year (Year 4), per lender convention.
A4: Particulars | B4: Basis | C4: Year 1 | D4: Year 2 | E4: Year 3 | F4: Year 4 | G4: Year 5 | H4: Year 6 | I4: Year 7 | J4: Year 8 | K4: Year 9 | L4: Year 10
A5: Financial year | C5: FY2029 | D5: FY2030 | E5: FY2031 | F5: FY2032 | G5: FY2033 | H5: FY2034 | I5: FY2035 | J5: FY2036 | K5: FY2037 | L5: FY2038
A6: Cash available for debt service (CFADS)
A7: EBITDA | B7: Rs Lakh | C7: ='P&L'!C$20 -> -386.36061 | D7: ='P&L'!D$20 -> 517.57216 | E7: ='P&L'!E$20 -> 1409.3094 | F7: ='P&L'!F$20 -> 2028.6508 | G7: ='P&L'!G$20 -> 2477.8231 | H7: ='P&L'!H$20 -> 2918.4282 | I7: ='P&L'!I$20 -> 3225.0265 | J7: ='P&L'!J$20 -> 3515.0033 | ... L7: ='P&L'!L$20 -> 4213.8306
A8: Less: tax paid | B8: Rs Lakh | C8: =-'P&L'!C$34 -> 0 | D8: =-'P&L'!D$34 -> 0 | E8: =-'P&L'!E$34 -> 0 | F8: =-'P&L'!F$34 -> 0 | G8: =-'P&L'!G$34 -> 0 | H8: =-'P&L'!H$34 -> -0.37519772 | I8: =-'P&L'!I$34 -> -504.78269 | J8: =-'P&L'!J$34 -> -604.9877 | ... L8: =-'P&L'!L$34 -> -845.30923
A9: Less: increase in working capital | B9: Rs Lakh | C9: =-'Working Capital'!C$20 -> -285.54125 | D9: =-'Working Capital'!D$20 -> -211.09805 | E9: =-'Working Capital'!E$20 -> -207.95585 | F9: =-'Working Capital'!F$20 -> -167.1221 | G9: =-'Working Capital'!G$20 -> -144.75887 | H9: =-'Working Capital'!H$20 -> -117.93087 | I9: =-'Working Capital'!I$20 -> -97.270701 | J9: =-'Working Capital'!J$20 -> -98.109618 | ... L9: =-'Working Capital'!L$20 -> -114.26515
A10: CFADS | B10: Rs Lakh | C10: =SUM(C7:C9) -> -671.90186 | D10: =SUM(D7:D9) -> 306.47411 | E10: =SUM(E7:E9) -> 1201.3535 | F10: =SUM(F7:F9) -> 1861.5287 | G10: =SUM(G7:G9) -> 2333.0642 | H10: =SUM(H7:H9) -> 2800.1221 | I10: =SUM(I7:I9) -> 2622.9731 | J10: =SUM(J7:J9) -> 2811.9059 | ... L10: =SUM(L7:L9) -> 3254.2562
A12: Debt service
A13: Term-loan interest | B13: Rs Lakh | C13: ='Debt Schedule'!C$10 -> 833.58249 | D13: ='Debt Schedule'!D$10 -> 833.58249 | E13: ='Debt Schedule'!E$10 -> 833.58249 | F13: ='Debt Schedule'!F$10 -> 808.57502 | G13: ='Debt Schedule'!G$10 -> 741.88842 | H13: ='Debt Schedule'!H$10 -> 646.02643 | I13: ='Debt Schedule'!I$10 -> 529.32488 | J13: ='Debt Schedule'!J$10 -> 395.95168 | ... L13: ='Debt Schedule'!L$10 -> 83.358249
A14: Term-loan principal | B14: Rs Lakh | C14: ='Debt Schedule'!C$9 -> 0 | D14: ='Debt Schedule'!D$9 -> 0 | E14: ='Debt Schedule'!E$9 -> 0 | F14: ='Debt Schedule'!F$9 -> 465.25534 | G14: ='Debt Schedule'!G$9 -> 775.42557 | H14: ='Debt Schedule'!H$9 -> 1008.0532 | I14: ='Debt Schedule'!I$9 -> 1163.1384 | J14: ='Debt Schedule'!J$9 -> 1318.2235 | ... L14: ='Debt Schedule'!L$9 -> 1550.8511
A15: Total debt service | B15: Rs Lakh | C15: =C13+C14 -> 833.58249 | D15: =D13+D14 -> 833.58249 | E15: =E13+E14 -> 833.58249 | F15: =F13+F14 -> 1273.8304 | G15: =G13+G14 -> 1517.314 | H15: =H13+H14 -> 1654.0797 | I15: =I13+I14 -> 1692.4632 | J15: =J13+J14 -> 1714.1752 | ... L15: =L13+L14 -> 1634.2094
A17: DEBT SERVICE COVERAGE RATIOS
A18: DSCR — cash basis (CFADS / debt service) | B18: x | C18: =IFERROR(C10/C15,0) -> -0.80604123 | D18: =IFERROR(D10/D15,0) -> 0.36765901 | E18: =IFERROR(E10/E15,0) -> 1.4411933 | F18: =IFERROR(F10/F15,0) -> 1.4613631 | G18: =IFERROR(G10/G15,0) -> 1.5376278 | H18: =IFERROR(H10/H15,0) -> 1.6928581 | I18: =IFERROR(I10/I15,0) -> 1.5497962 | J18: =IFERROR(J10/J15,0) -> 1.6403843 | ... L18: =IFERROR(L10/L15,0) -> 1.9913337
A19: DSCR — accrual basis ((PAT + dep + interest) / debt service) | B19: x | C19: =IFERROR(('P&L'!C$38+'P&L'!C$23+C13)/C15,0) -> -0.50695116 | D19: =IFERROR(('P&L'!D$38+'P&L'!D$23+D13)/D15,0) -> 0.55261137 | E19: =IFERROR(('P&L'!E$38+'P&L'!E$23+E13)/E15,0) -> 1.6037517 | F19: =IFERROR(('P&L'!F$38+'P&L'!F$23+F13)/F15,0) -> 1.5316214 | G19: =IFERROR(('P&L'!G$38+'P&L'!G$23+G13)/G15,0) -> 1.5784624 | H19: =IFERROR(('P&L'!H$38+'P&L'!H$23+H13)/H15,0) -> 1.714097 | I19: =IFERROR(('P&L'!I$38+'P&L'!I$23+I13)/I15,0) -> 1.5583463 | J19: =IFERROR(('P&L'!J$38+'P&L'!J$23+J13)/J15,0) -> 1.6493154 | ... L19: =IFERROR(('P&L'!L$38+'P&L'!L$23+L13)/L15,0) -> 2.0105877 | N19: The formulation most Indian sanction letters use
A20: Interest coverage ratio (EBITDA / finance cost) | B20: x | C20: =IFERROR(C7/'P&L'!C$27,0) -> -0.44419094 | D20: =IFERROR(D7/'P&L'!D$27,0) -> 0.58121034 | E20: =IFERROR(E7/'P&L'!E$27,0) -> 1.5554733 | F20: =IFERROR(F7/'P&L'!F$27,0) -> 2.2891568 | G20: =IFERROR(G7/'P&L'!G$27,0) -> 3.0045566 | H20: =IFERROR(H7/'P&L'!H$27,0) -> 4.0042843 | I20: =IFERROR(I7/'P&L'!I$27,0) -> 5.268576 | J20: =IFERROR(J7/'P&L'!J$27,0) -> 7.3420176 | ... L20: =IFERROR(L7/'P&L'!L$27,0) -> 25.360345
A21: Covenant tested this year? | C21: =IF(C14>0,"Yes","No - moratorium") -> No - moratorium | D21: =IF(D14>0,"Yes","No - moratorium") -> No - moratorium | E21: =IF(E14>0,"Yes","No - moratorium") -> No - moratorium | F21: =IF(F14>0,"Yes","No - moratorium") -> Yes | G21: =IF(G14>0,"Yes","No - moratorium") -> Yes | H21: =IF(H14>0,"Yes","No - moratorium") -> Yes | I21: =IF(I14>0,"Yes","No - moratorium") -> Yes | J21: =IF(J14>0,"Yes","No - moratorium") -> Yes | ... L21: =IF(L14>0,"Yes","No - moratorium") -> Yes
A22: DSCR covenant (>= 1.25x) | C22: =IF(C14<=0,"n/a",IF(C18>=Assumptions!$C$126,"PASS","BREACH")) -> n/a | D22: =IF(D14<=0,"n/a",IF(D18>=Assumptions!$C$126,"PASS","BREACH")) -> n/a | E22: =IF(E14<=0,"n/a",IF(E18>=Assumptions!$C$126,"PASS","BREACH")) -> n/a | F22: =IF(F14<=0,"n/a",IF(F18>=Assumptions!$C$126,"PASS","BREACH")) -> PASS | G22: =IF(G14<=0,"n/a",IF(G18>=Assumptions!$C$126,"PASS","BREACH")) -> PASS | H22: =IF(H14<=0,"n/a",IF(H18>=Assumptions!$C$126,"PASS","BREACH")) -> PASS | I22: =IF(I14<=0,"n/a",IF(I18>=Assumptions!$C$126,"PASS","BREACH")) -> PASS | J22: =IF(J14<=0,"n/a",IF(J18>=Assumptions!$C$126,"PASS","BREACH")) -> PASS | ... L22: =IF(L14<=0,"n/a",IF(L18>=Assumptions!$C$126,"PASS","BREACH")) -> PASS
A23: DSCR for covenant testing (99 where not tested) | B23: x | C23: =IF(C14>0,C18,99) -> 99 | D23: =IF(D14>0,D18,99) -> 99 | E23: =IF(E14>0,E18,99) -> 99 | F23: =IF(F14>0,F18,99) -> 1.4613631 | G23: =IF(G14>0,G18,99) -> 1.5376278 | H23: =IF(H14>0,H18,99) -> 1.6928581 | I23: =IF(I14>0,I18,99) -> 1.5497962 | J23: =IF(J14>0,J18,99) -> 1.6403843 | ... L23: =IF(L14>0,L18,99) -> 1.9913337 | N23: Helper row - lets MIN() ignore the moratorium years without an array formula
A25: Summary of the covenant package
A26: Minimum DSCR over the repayment period | C26: =MIN(C23:L23) -> 1.4613631
A27: Average DSCR over the repayment period | C27: =SUMIF(C14:L14,">0",C18:L18)/COUNTIF(C14:L14,">0") -> 1.6620079
A28: Number of covenant breaches | C28: =COUNTIF(C22:L22,"BREACH") -> 0
A29: Verdict | C29: =IF(C28=0,"BANKABLE - no covenant breach in any tested year","NOT BANKABLE AS STRUCTURED - "&C28&" breach year(s)") -> BANKABLE - no covenant breach in any tested year
A31: Other covenants
A32: Covenant | B32: Threshold | C32: Modelled | D32: Status
A33: Total debt / EBITDA (stabilised, Year 6 onward) | B33: <= 3.50x | C33: ='Balance Sheet'!H$43 -> 1.4700215 | D33: =IF(C33<=3.5,"PASS","BREACH") -> PASS
A34: Total outside liabilities / tangible net worth (Year 5 onward) | B34: <= 2.50x | C34: =MAX('Balance Sheet'!G45:L45) -> 2.3428057 | D34: =IF(C34<=2.5,"PASS","BREACH") -> PASS
A35: Current ratio (stabilised) | B35: >= 1.10x | C35: =MIN('Balance Sheet'!F$44:L$44) -> 1.5223022 | D35: =IF(C35>=1.1,"PASS","BREACH") -> PASS
A36: Promoter contribution to total funding | B36: >= 30% | C36: =('Capex & Funding'!$C$33+'Capex & Funding'!$C$38)/'Capex & Funding'!$C$39 -> 0.39690836 | D36: =IF(C36>=0.3,"PASS","BREACH") -> PASS
A37: Minimum cash balance maintained throughout | B37: >= Rs 150 L | C37: =MIN('Cash Flow'!C25:L25) -> 157.93816 | D37: =IF(C37>=150,"PASS","BREACH") -> PASS
A39: DISCLOSED EXCEPTION — leverage on a net-worth basis during the ramp years
A40: Peak TOL / TNW during Years 1-4 | B40: n/a | C40: =MAX('Balance Sheet'!C45:F45) -> 4.450412 | D40: DISCLOSED
A41: Year in which the peak occurs | C41: =MATCH(MAX('Balance Sheet'!C45:F45),'Balance Sheet'!C45:F45,0) -> 3
A43: This is a real constraint, not a modelling artefact, and it should be raised with the lender rather than
A44: discovered by them. Accumulated start-up losses of roughly Rs 25 Cr over Years 1-3 erode tangible net worth
A45: faster than the term loan amortises, so leverage measured against net worth peaks well above a conventional
A46: 2.50x covenant before collapsing to under 0.2x by Year 10. Every greenfield hospital does this; the ratio is
A47: simply the wrong lens during a ramp.
A49: Three ways the market handles it, in descending order of preference:
A50: 1. A covenant holiday on TOL/TNW until the start of Year 5, with DSCR and minimum-cash covenants
A51: carrying the credit discipline in the interim. This is the cleanest and the most commonly granted.
A52: 2. Counting the promoter's subordinated support loan as quasi-equity in the TNW computation, backed by a
A53: non-withdrawal undertaking for the tenor of the facility. Already reflected here, since that facility
A54: sits inside net worth on the Balance Sheet.
A55: 3. Sizing the promoter's Year-1 equity contribution larger so that net worth never falls far enough to
... A58: The recommendation is option 1 plus option 2, documented as a condition precedent in the sanction letter.

Sheet Returns & IRR
A1: RETURNS ANALYSIS
A2: Rs Lakh. Column B holds the t=0 investment; columns C-L hold operating Years 1-10.
A4: Particulars | B4: t = 0 | C4: Year 1 | D4: Year 2 | E4: Year 3 | F4: Year 4 | G4: Year 5 | H4: Year 6 | I4: Year 7 | J4: Year 8 | K4: Year 9 | L4: Year 10
A5: Financial year | C5: FY2029 | D5: FY2030 | E5: FY2031 | F5: FY2032 | G5: FY2033 | H5: FY2034 | I5: FY2035 | J5: FY2036 | K5: FY2037 | L5: FY2038
A6: Notional tax on EBIT (for the unlevered cash flow)
A7: Loss brought forward (unlevered basis) | B7: Rs Lakh | C7: =0 -> 0 | D7: =C9 -> -1000.2341 | E7: =D9 -> -1096.5354 | F7: =E9 -> -342.34946 | G7: =F9 -> 0 | H7: =G9 -> 0 | I7: =H9 -> 0 | J7: =I9 -> 0 | K7: =J9 -> 0 | L7: =K9 -> 0
A8: Taxable EBIT after set-off | B8: Rs Lakh | C8: =MAX('P&L'!C$24+C7,0) -> 0 | D8: =MAX('P&L'!D$24+D7,0) -> 0 | E8: =MAX('P&L'!E$24+E7,0) -> 0 | F8: =MAX('P&L'!F$24+F7,0) -> 1016.7681 | G8: =MAX('P&L'!G$24+G7,0) -> 1790.5294 | H8: =MAX('P&L'!H$24+H7,0) -> 2300.2556 | I8: =MAX('P&L'!I$24+I7,0) -> 2617.7777 | J8: =MAX('P&L'!J$24+J7,0) -> 2882.549 | ... L8: =MAX('P&L'!L$24+L7,0) -> 3524.8249
A9: Loss carried forward | B9: Rs Lakh | C9: =MIN('P&L'!C$24+C7,0) -> -1000.2341 | D9: =MIN('P&L'!D$24+D7,0) -> -1096.5354 | E9: =MIN('P&L'!E$24+E7,0) -> -342.34946 | F9: =MIN('P&L'!F$24+F7,0) -> 0 | G9: =MIN('P&L'!G$24+G7,0) -> 0 | H9: =MIN('P&L'!H$24+H7,0) -> 0 | I9: =MIN('P&L'!I$24+I7,0) -> 0 | J9: =MIN('P&L'!J$24+J7,0) -> 0 | ... L9: =MIN('P&L'!L$24+L7,0) -> 0
A10: Notional tax on EBIT | B10: Rs Lakh | C10: =C8*Assumptions!$C$98 -> 0 | D10: =D8*Assumptions!$C$98 -> 0 | E10: =E8*Assumptions!$C$98 -> 0 | F10: =F8*Assumptions!$C$98 -> 255.90021 | G10: =G8*Assumptions!$C$98 -> 450.64043 | H10: =H8*Assumptions!$C$98 -> 578.92833 | I10: =I8*Assumptions!$C$98 -> 658.84228 | J10: =J8*Assumptions!$C$98 -> 725.47992 | ... L10: =L8*Assumptions!$C$98 -> 887.12794
A12: A. PROJECT (UNLEVERED) RETURNS
A13: Free cash flow to firm | B13: Rs Lakh | C13: ='P&L'!C$20-C10-'Working Capital'!C$20-Depreciation!C$8 -> -671.90186 | D13: ='P&L'!D$20-D10-'Working Capital'!D$20-Depreciation!D$8 -> 306.47411 | E13: ='P&L'!E$20-E10-'Working Capital'!E$20-Depreciation!E$8 -> 507.25594 | F13: ='P&L'!F$20-F10-'Working Capital'!F$20-Depreciation!F$8 -> 1428.0238 | G13: ='P&L'!G$20-G10-'Working Capital'!G$20-Depreciation!G$8 -> 1673.6346 | H13: ='P&L'!H$20-H10-'Working Capital'!H$20-Depreciation!H$8 -> 1989.128 | I13: ='P&L'!I$20-I10-'Working Capital'!I$20-Depreciation!I$8 -> 2216.8587 | J13: ='P&L'!J$20-J10-'Working Capital'!J$20-Depreciation!J$8 -> 2419.5811 | ... L13: ='P&L'!L$20-L10-'Working Capital'!L$20-Depreciation!L$8 -> 2895.8212
A14: Terminal value at exit (Year 10 EBITDA x exit multiple) | B14: Rs Lakh | C14: =0 -> 0 | D14: =0 -> 0 | E14: =0 -> 0 | F14: =0 -> 0 | G14: =0 -> 0 | H14: =0 -> 0 | I14: =0 -> 0 | J14: =0 -> 0 | K14: =0 -> 0 | L14: ='P&L'!L$20*Assumptions!$C$124 -> 54779.798
A15: Initial investment (cost of project) | B15: =-'Capex & Funding'!$C$25 -> -11077.508 | C15: =0 -> 0 | D15: =0 -> 0 | E15: =0 -> 0 | F15: =0 -> 0 | G15: =0 -> 0 | H15: =0 -> 0 | I15: =0 -> 0 | J15: =0 -> 0 | ... L15: =0 -> 0
A16: Project cash flow | B16: =B15 -> -11077.508 | C16: =C13+C14 -> -671.90186 | D16: =D13+D14 -> 306.47411 | E16: =E13+E14 -> 507.25594 | F16: =F13+F14 -> 1428.0238 | G16: =G13+G14 -> 1673.6346 | H16: =H13+H14 -> 1989.128 | I16: =I13+I14 -> 2216.8587 | J16: =J13+J14 -> 2419.5811 | ... L16: =L13+L14 -> 57675.619
A17: Cumulative project cash flow | B17: Rs Lakh | C17: =$B$16+C16 -> -11749.41 | D17: =C17+D16 -> -11442.936 | E17: =D17+E16 -> -10935.68 | F17: =E17+F16 -> -9507.6562 | G17: =F17+G16 -> -7834.0216 | H17: =G17+H16 -> -5844.8936 | I17: =H17+I16 -> -3628.0349 | J17: =I17+J16 -> -1208.4538 | K17: =J17+K16 -> 1442.1454 | L17: =K17+L16 -> 59117.764
A19: Project IRR | C19: =IRR(B16:L16) -> 0.22129905 | E19: The return the ASSET earns, independent of how it is financed
A20: WACC / hurdle rate | C20: =Assumptions!$C$122 -> 0.125
A21: Spread over WACC | C21: =C19-C20 -> 0.096299053 | E21: Positive spread = value created
A22: Project NPV @ WACC | C22: =NPV(Assumptions!$C$122,C16:L16)+B16 -> 12319.378 | E22: Cash flows discounted from Year 1; the t=0 outflow added undiscounted
A23: NPV as % of investment | C23: =C22/-B16 -> 1.1121073
A24: Simple payback period | C24: =COUNTIF(C17:L17,"<0")+IFERROR(INDEX(C17:L17,1,COUNTIF(C17:L17,"<0"))/-INDEX(C16:L16,1,COUNTIF(C17:L17,"<0")+1)*-1,0) -> 7.5440828 | E24: Years until cumulative project cash flow turns positive
A26: B. EQUITY (LEVERED) RETURNS
A27: Free cash flow to equity | B27: Rs Lakh | C27: ='Cash Flow'!C$30 -> -1226.7094 | D27: ='Cash Flow'!D$30 -> -404.03338 | E27: ='Cash Flow'!E$30 -> -263.77655 | F27: ='Cash Flow'!F$30 -> 377.46865 | G27: ='Cash Flow'!G$30 -> 569.16103 | H27: ='Cash Flow'!H$30 -> 830.80147 | I27: ='Cash Flow'!I$30 -> 595.65503 | J27: ='Cash Flow'!J$30 -> 743.09819 | ... L27: ='Cash Flow'!L$30 -> 1220.6305
A28: Exit enterprise value | B28: Rs Lakh | C28: =0 -> 0 | D28: =0 -> 0 | E28: =0 -> 0 | F28: =0 -> 0 | G28: =0 -> 0 | H28: =0 -> 0 | I28: =0 -> 0 | J28: =0 -> 0 | K28: =0 -> 0 | L28: ='P&L'!L$20*Assumptions!$C$124 -> 54779.798
A29: Less: net debt at exit | B29: Rs Lakh | C29: =0 -> 0 | D29: =0 -> 0 | E29: =0 -> 0 | F29: =0 -> 0 | G29: =0 -> 0 | H29: =0 -> 0 | I29: =0 -> 0 | J29: =0 -> 0 | K29: =0 -> 0 | L29: =-'Balance Sheet'!L$42 -> 4706.0657
A30: Exit equity value | B30: Rs Lakh | C30: =C28+C29 -> 0 | D30: =D28+D29 -> 0 | E30: =E28+E29 -> 0 | F30: =F28+F29 -> 0 | G30: =G28+G29 -> 0 | H30: =H28+H29 -> 0 | I30: =I28+I29 -> 0 | J30: =J28+J29 -> 0 | ... L30: =L28+L29 -> 59485.863
A31: Equity invested at t = 0 | B31: =-('Capex & Funding'!$C$33+'Capex & Funding'!$C$38) -> -5103.2525 | C31: =0 -> 0 | D31: =0 -> 0 | E31: =0 -> 0 | F31: =0 -> 0 | G31: =0 -> 0 | H31: =0 -> 0 | I31: =0 -> 0 | J31: =0 -> 0 | ... L31: =0 -> 0
A32: Equity cash flow | B32: =B31 -> -5103.2525 | C32: =C27+C30 -> -1226.7094 | D32: =D27+D30 -> -404.03338 | E32: =E27+E30 -> -263.77655 | F32: =F27+F30 -> 377.46865 | G32: =G27+G30 -> 569.16103 | H32: =H27+H30 -> 830.80147 | I32: =I27+I30 -> 595.65503 | J32: =J27+J30 -> 743.09819 | ... L32: =L27+L30 -> 60706.494
A33: Cumulative equity cash flow | B33: Rs Lakh | C33: =$B$32+C32 -> -6329.9618 | D33: =C33+D32 -> -6733.9952 | E33: =D33+E32 -> -6997.7717 | F33: =E33+F32 -> -6620.3031 | G33: =F33+G32 -> -6051.1421 | H33: =G33+H32 -> -5220.3406 | I33: =H33+I32 -> -4624.6856 | J33: =I33+J32 -> -3881.5874 | K33: =J33+K32 -> -2950.2747 | L33: =K33+L32 -> 57756.219
A35: Equity IRR | C35: =IRR(B32:L32) -> 0.26910963 | E35: The return the SHAREHOLDER earns after debt service
A36: Target equity IRR (hurdle) | C36: =Assumptions!$C$125 -> 0.18
A37: Spread over hurdle | C37: =C35-C36 -> 0.08910963
A38: Equity NPV @ 16% cost of equity | C38: =NPV(0.16,C32:L32)+B32 -> 8633.9224
A39: Total cash returned to equity | C39: =SUM(C32:L32) -> 62859.471
A40: Money multiple (MOIC) | C40: =C39/-B32 -> 12.317531 | E40: Total cash out divided by cash in
A41: Equity payback period | C41: =COUNTIF(C33:L33,"<0") -> 9
A43: Reconciliation — why the equity IRR exceeds the project IRR
A44: Project IRR (asset return) | C44: =C19 -> 0.22129905
A45: Cost of debt, post-tax | C45: =Assumptions!$C$106*(1-Assumptions!$C$98) -> 0.0804444
A46: Positive spread (asset return less post-tax cost of debt) | C46: =C44-C45 -> 0.14085465
A47: Equity IRR (levered) | C47: =C35 -> 0.26910963
A48: Leverage amplifies the return whenever the asset out-earns the debt. It amplifies losses too — which is exactly what the Monte Carlo sheet quantifies.

Sheet Break-even
A1: BREAK-EVEN & LEVERAGE ANALYSIS
A2: Rs Lakh. Separates costs into variable and fixed to find the minimum viable occupancy.
A4: Particulars | B4: Unit | C4: Year 1 | D4: Year 2 | E4: Year 3 | F4: Year 4 | G4: Year 5 | H4: Year 6 | I4: Year 7 | J4: Year 8 | K4: Year 9 | L4: Year 10
A5: Financial year | C5: FY2029 | D5: FY2030 | E5: FY2031 | F5: FY2032 | G5: FY2033 | H5: FY2034 | I5: FY2035 | J5: FY2036 | K5: FY2037 | L5: FY2038
A6: Revenue | B6: Rs Lakh | C6: ='Revenue Build'!C$43 -> 3013.3215 | D6: ='Revenue Build'!D$43 -> 5112.4055 | E6: ='Revenue Build'!E$43 -> 7204.879 | F6: ='Revenue Build'!F$43 -> 8880.2355 | G6: ='Revenue Build'!G$43 -> 10439.459 | H6: ='Revenue Build'!H$43 -> 11622.05 | I6: ='Revenue Build'!I$43 -> 12602.74 | J6: ='Revenue Build'!J$43 -> 13591.63 | ... L6: ='Revenue Build'!L$43 -> 15830.817
A7: Variable costs | B7: Rs Lakh | C7: ='Operating Costs'!C$9 -> 985.78207 | D7: ='Operating Costs'!D$9 -> 1672.6653 | E7: ='Operating Costs'!E$9 -> 2354.277 | F7: ='Operating Costs'!F$9 -> 2899.401 | G7: ='Operating Costs'!G$9 -> 3406.0288 | H7: ='Operating Costs'!H$9 -> 3789.366 | I7: ='Operating Costs'!I$9 -> 4102.8782 | J7: ='Operating Costs'!J$9 -> 4422.9237 | ... L7: ='Operating Costs'!L$9 -> 5144.7216
A8: Contribution | B8: Rs Lakh | C8: =C6-C7 -> 2027.5394 | D8: =D6-D7 -> 3439.7402 | E8: =E6-E7 -> 4850.602 | F8: =F6-F7 -> 5980.8345 | G8: =G6-G7 -> 7033.4299 | H8: =H6-H7 -> 7832.6836 | I8: =I6-I7 -> 8499.8623 | J8: =J6-J7 -> 9168.7059 | ... L8: =L6-L7 -> 10686.095
A9: Contribution margin ratio | B9: % | C9: =C8/C6 -> 0.67285864 | D9: =D8/D6 -> 0.67282225 | E9: =E8/E6 -> 0.67323851 | F9: =F8/F6 -> 0.67349953 | G9: =G8/G6 -> 0.67373511 | H9: =H8/H6 -> 0.67395028 | I9: =I8/I6 -> 0.67444555 | J9: =J8/J6 -> 0.67458474 | ... L9: =L8/L6 -> 0.67501856 | N9: Every extra rupee of revenue contributes this much to fixed costs
A10: Fixed & semi-fixed costs | B10: Rs Lakh | C10: ='Operating Costs'!C$19 -> 2413.9 | D10: ='Operating Costs'!D$19 -> 2922.168 | E10: ='Operating Costs'!E$19 -> 3441.2926 | F10: ='Operating Costs'!F$19 -> 3952.1837 | G10: ='Operating Costs'!G$19 -> 4555.6068 | H10: ='Operating Costs'!H$19 -> 4914.2554 | I10: ='Operating Costs'!I$19 -> 5274.8358 | J10: ='Operating Costs'!J$19 -> 5653.7027 | ... L10: ='Operating Costs'!L$19 -> 6472.2644
A11: Depreciation | B11: Rs Lakh | C11: ='P&L'!C$23 -> 613.87346 | D11: ='P&L'!D$23 -> 613.87346 | E11: ='P&L'!E$23 -> 655.12346 | F11: ='P&L'!F$23 -> 669.53322 | G11: ='P&L'!G$23 -> 687.29369 | H11: ='P&L'!H$23 -> 618.17261 | I11: ='P&L'!I$23 -> 607.24881 | J11: ='P&L'!J$23 -> 632.45429 | ... L11: ='P&L'!L$23 -> 689.00565
A12: Finance cost | B12: Rs Lakh | C12: ='P&L'!C$27 -> 869.80749 | D12: ='P&L'!D$27 -> 890.50749 | E12: ='P&L'!E$27 -> 906.03249 | F12: ='P&L'!F$27 -> 886.20002 | G12: ='P&L'!G$27 -> 824.68842 | H12: ='P&L'!H$27 -> 728.82643 | I12: ='P&L'!I$27 -> 612.12488 | J12: ='P&L'!J$27 -> 478.75168 | ... L12: ='P&L'!L$27 -> 166.15825
A13: Principal repayment | B13: Rs Lakh | C13: ='Debt Schedule'!C$9 -> 0 | D13: ='Debt Schedule'!D$9 -> 0 | E13: ='Debt Schedule'!E$9 -> 0 | F13: ='Debt Schedule'!F$9 -> 465.25534 | G13: ='Debt Schedule'!G$9 -> 775.42557 | H13: ='Debt Schedule'!H$9 -> 1008.0532 | I13: ='Debt Schedule'!I$9 -> 1163.1384 | J13: ='Debt Schedule'!J$9 -> 1318.2235 | ... L13: ='Debt Schedule'!L$9 -> 1550.8511
A15: Break-even revenue
A16: Operating break-even (covers fixed cash costs only) | B16: Rs Lakh | C16: =C10/C9 -> 3587.5292 | D16: =D10/D9 -> 4343.1501 | E16: =E10/E9 -> 5111.5505 | F16: =F10/F9 -> 5868.1312 | G16: =G10/G9 -> 6761.718 | H16: =H10/H9 -> 7291.718 | I16: =I10/I9 -> 7820.9957 | J16: =J10/J9 -> 8381.0118 | ... L16: =L10/L9 -> 9588.2762
A17: Accounting break-even (fixed costs + depreciation + interest) | B17: Rs Lakh | C17: =(C10+C11+C12)/C9 -> 5792.5702 | D17: =(D10+D11+D12)/D9 -> 6579.0763 | E17: =(E10+E11+E12)/E9 -> 7430.4255 | F17: =(F10+F11+F12)/F9 -> 8178.056 | G17: =(G10+G11+G12)/G9 -> 9005.8969 | H17: =(H10+H11+H12)/H9 -> 9290.3803 | I17: =(I10+I11+I12)/I9 -> 9628.9604 | J17: =(J10+J11+J12)/J9 -> 10028.256 | ... L17: =(L10+L11+L12)/L9 -> 10855.151
A18: Cash break-even (fixed costs + interest + principal) | B18: Rs Lakh | C18: =(C10+C12+C13)/C9 -> 4880.2338 | D18: =(D10+D12+D13)/D9 -> 5666.6906 | E18: =(E10+E12+E13)/E9 -> 6457.3328 | F18: =(F10+F12+F13)/F9 -> 7874.7479 | G18: =(G10+G12+G13)/G9 -> 9136.7078 | H18: =(H10+H12+H13)/H9 -> 9868.8809 | I18: =(I10+I12+I13)/I9 -> 10453.177 | J18: =(J10+J12+J13)/J9 -> 11044.836 | ... L18: =(L10+L12+L13)/L9 -> 12131.924 | N18: The level of revenue at which the hospital can actually service its debt
A20: Break-even occupancy — the number the promoter should memorise
A21: Actual occupancy | B21: % | C21: ='Revenue Build'!C$8 -> 0.2736 | D21: ='Revenue Build'!D$8 -> 0.432 | E21: ='Revenue Build'!E$8 -> 0.5616 | F21: ='Revenue Build'!F$8 -> 0.6408 | G21: ='Revenue Build'!G$8 -> 0.6984 | H21: ='Revenue Build'!H$8 -> 0.72 | I21: ='Revenue Build'!I$8 -> 0.72 | J21: ='Revenue Build'!J$8 -> 0.72 | ... L21: ='Revenue Build'!L$8 -> 0.72
A22: Operating break-even occupancy | B22: % | C22: =C21*C16/C6 -> 0.32573623 | D22: =D21*D16/D6 -> 0.36699766 | E22: =E21*E16/E6 -> 0.39843095 | F22: =F21*F16/F6 -> 0.42344581 | G22: =G21*G16/G6 -> 0.45235907 | H22: =H21*H16/H6 -> 0.45173073 | I22: =I21*I16/I6 -> 0.44681686 | J22: =J21*J16/J6 -> 0.44397388 | ... L22: =L21*L16/L6 -> 0.43608356
A23: Accounting break-even occupancy | B23: % | C23: =C21*C17/C6 -> 0.52594694 | D23: =D21*D17/D6 -> 0.55593419 | E23: =E21*E17/E6 -> 0.57918071 | F23: =F21*F17/F6 -> 0.59013055 | G23: =G21*G17/G6 -> 0.60249468 | H23: =H21*H17/H6 -> 0.57555027 | I23: =I21*I17/I6 -> 0.55010666 | J23: =J21*J17/J6 -> 0.53123464 | ... L23: =L21*L17/L6 -> 0.49370218
A24: Cash break-even occupancy | B24: % | C24: =C21*C18/C6 -> 0.4431097 | D24: =D21*D18/D6 -> 0.47883728 | E24: =E21*E18/E6 -> 0.50333088 | F24: =F21*F18/F6 -> 0.56824376 | G24: =G21*G18/G6 -> 0.61124593 | H24: =H21*H18/H6 -> 0.61138908 | I24: =I21*I18/I6 -> 0.59719454 | J24: =J21*J18/J6 -> 0.58508672 | ... L24: =L21*L18/L6 -> 0.55177098
A25: Margin of safety (actual less cash break-even occupancy) | B25: pp | C25: =C21-C24 -> -0.1695097 | D25: =D21-D24 -> -0.046837277 | E25: =E21-E24 -> 0.058269117 | F25: =F21-F24 -> 0.072556238 | G25: =G21-G24 -> 0.087154066 | H25: =H21-H24 -> 0.10861092 | I25: =I21-I24 -> 0.12280546 | J25: =J21-J24 -> 0.13491328 | ... L25: =L21-L24 -> 0.16822902 | N25: Negative means the hospital cannot cover debt service at that year's occupancy
A27: Leverage
A28: Degree of operating leverage (contribution / EBIT) | B28: x | C28: =IFERROR(C8/'P&L'!C$24,0) -> -2.0270649 | D28: =IFERROR(D8/'P&L'!D$24,0) -> -35.718523 | E28: =IFERROR(E8/'P&L'!E$24,0) -> 6.4315734 | F28: =IFERROR(F8/'P&L'!F$24,0) -> 4.4005276 | G28: =IFERROR(G8/'P&L'!G$24,0) -> 3.9281287 | H28: =IFERROR(H8/'P&L'!H$24,0) -> 3.4051362 | I28: =IFERROR(I8/'P&L'!I$24,0) -> 3.2469764 | J28: =IFERROR(J8/'P&L'!J$24,0) -> 3.1807633 | ... L28: =IFERROR(L8/'P&L'!L$24,0) -> 3.0316669 | N28: A 1% change in revenue moves EBIT by this many %
A29: Degree of financial leverage (EBIT / PBT) | B29: x | C29: =IFERROR('P&L'!C$24/'P&L'!C$28,0) -> 0.53487264 | D29: =IFERROR('P&L'!D$24/'P&L'!D$28,0) -> 0.097588611 | E29: =IFERROR('P&L'!E$24/'P&L'!E$28,0) -> -4.9667624 | F29: =IFERROR('P&L'!F$24/'P&L'!F$28,0) -> 2.8738995 | G29: =IFERROR('P&L'!G$24/'P&L'!G$28,0) -> 1.8538553 | H29: =IFERROR('P&L'!H$24/'P&L'!H$28,0) -> 1.4637985 | I29: =IFERROR('P&L'!I$24/'P&L'!I$28,0) -> 1.3051998 | J29: =IFERROR('P&L'!J$24/'P&L'!J$28,0) -> 1.1991647 | ... L29: =IFERROR('P&L'!L$24/'P&L'!L$28,0) -> 1.0494715
A30: Degree of total leverage | B30: x | C30: =C28*C29 -> -1.0842216 | D30: =D28*D29 -> -3.485721 | E30: =E28*E29 -> -31.944097 | F30: =F28*F29 -> 12.646674 | G30: =G28*G29 -> 7.2821823 | H30: =H28*H29 -> 4.9844331 | I30: =I28*I29 -> 4.237953 | J30: =J28*J29 -> 3.8142592 | ... L30: =L28*L29 -> 3.181648 | N30: High total leverage is why hospital projects live or die on the occupancy ramp
A32: Reading this sheet: in the stabilised years the hospital breaks even on cash at roughly 55-60% occupancy against
A33: 72% actual — a margin of safety of about 12 percentage points. In Year 3 that margin is far thinner. The whole
A34: financing structure exists to carry the business across the gap between commissioning and that margin appearing.

Sheet Unit Economics
A1: UNIT ECONOMICS
A2: Per bed, per bed-day, per admission and per employee. The operating language of a hospital.
A4: Metric | B4: Unit | C4: Year 1 | D4: Year 2 | E4: Year 3 | F4: Year 4 | G4: Year 5 | H4: Year 6 | I4: Year 7 | J4: Year 8 | K4: Year 9 | L4: Year 10
A5: Financial year | C5: FY2029 | D5: FY2030 | E5: FY2031 | F5: FY2032 | G5: FY2033 | H5: FY2034 | I5: FY2035 | J5: FY2036 | K5: FY2037 | L5: FY2038
A6: Per operational bed (Rs Lakh p.a.)
A7: Revenue per bed | B7: Rs Lakh | C7: ='Revenue Build'!C$43/Assumptions!$C$5 -> 30.133215 | D7: ='Revenue Build'!D$43/Assumptions!$C$5 -> 51.124055 | E7: ='Revenue Build'!E$43/Assumptions!$C$5 -> 72.04879 | F7: ='Revenue Build'!F$43/Assumptions!$C$5 -> 88.802355 | G7: ='Revenue Build'!G$43/Assumptions!$C$5 -> 104.39459 | H7: ='Revenue Build'!H$43/Assumptions!$C$5 -> 116.2205 | I7: ='Revenue Build'!I$43/Assumptions!$C$5 -> 126.0274 | J7: ='Revenue Build'!J$43/Assumptions!$C$5 -> 135.9163 | ... L7: ='Revenue Build'!L$43/Assumptions!$C$5 -> 158.30817
A8: EBITDA per bed | B8: Rs Lakh | C8: ='Operating Costs'!C$26/Assumptions!$C$5 -> -3.8636061 | D8: ='Operating Costs'!D$26/Assumptions!$C$5 -> 5.1757216 | E8: ='Operating Costs'!E$26/Assumptions!$C$5 -> 14.093094 | F8: ='Operating Costs'!F$26/Assumptions!$C$5 -> 20.286508 | G8: ='Operating Costs'!G$26/Assumptions!$C$5 -> 24.778231 | H8: ='Operating Costs'!H$26/Assumptions!$C$5 -> 29.184282 | I8: ='Operating Costs'!I$26/Assumptions!$C$5 -> 32.250265 | J8: ='Operating Costs'!J$26/Assumptions!$C$5 -> 35.150033 | ... L8: ='Operating Costs'!L$26/Assumptions!$C$5 -> 42.138306
A9: Salary cost per bed | B9: Rs Lakh | C9: =Manpower!C$30/Assumptions!$C$5 -> 14.939 | D9: =Manpower!D$30/Assumptions!$C$5 -> 18.57168 | E9: =Manpower!E$30/Assumptions!$C$5 -> 21.462926 | F9: =Manpower!F$30/Assumptions!$C$5 -> 24.071837 | G9: =Manpower!G$30/Assumptions!$C$5 -> 26.456068 | H9: =Manpower!H$30/Assumptions!$C$5 -> 28.572554 | I9: =Manpower!I$30/Assumptions!$C$5 -> 30.858358 | J9: =Manpower!J$30/Assumptions!$C$5 -> 33.327027 | ... L9: =Manpower!L$30/Assumptions!$C$5 -> 38.872644
A10: Consumables per bed | B10: Rs Lakh | C10: ='Operating Costs'!C$8/Assumptions!$C$5 -> 6.9306394 | D10: ='Operating Costs'!D$8/Assumptions!$C$5 -> 11.758533 | E10: ='Operating Costs'!E$8/Assumptions!$C$5 -> 16.571222 | F10: ='Operating Costs'!F$8/Assumptions!$C$5 -> 20.424542 | G10: ='Operating Costs'!G$8/Assumptions!$C$5 -> 24.010755 | H10: ='Operating Costs'!H$8/Assumptions!$C$5 -> 26.730714 | I10: ='Operating Costs'!I$8/Assumptions!$C$5 -> 28.986303 | J10: ='Operating Costs'!J$8/Assumptions!$C$5 -> 31.260748 | ... L10: ='Operating Costs'!L$8/Assumptions!$C$5 -> 36.410878
A11: PAT per bed | B11: Rs Lakh | C11: ='P&L'!C$38/Assumptions!$C$5 -> -18.700416 | D11: ='P&L'!D$38/Assumptions!$C$5 -> -9.8680879 | E11: ='P&L'!E$38/Assumptions!$C$5 -> -1.5184658 | F11: ='P&L'!F$38/Assumptions!$C$5 -> 4.7291759 | G11: ='P&L'!G$38/Assumptions!$C$5 -> 9.6584095 | H11: ='P&L'!H$38/Assumptions!$C$5 -> 15.71054 | I11: ='P&L'!I$38/Assumptions!$C$5 -> 15.008701 | J11: ='P&L'!J$38/Assumptions!$C$5 -> 17.988096 | ... L11: ='P&L'!L$38/Assumptions!$C$5 -> 25.133575
A12: Capital employed per bed | B12: Rs Lakh | C12: ='Balance Sheet'!C$34/Assumptions!$C$5 -> 114.81781 | D12: ='Balance Sheet'!D$34/Assumptions!$C$5 -> 108.41709 | E12: ='Balance Sheet'!E$34/Assumptions!$C$5 -> 109.93552 | F12: ='Balance Sheet'!F$34/Assumptions!$C$5 -> 111.80656 | G12: ='Balance Sheet'!G$34/Assumptions!$C$5 -> 115.51973 | H12: ='Balance Sheet'!H$34/Assumptions!$C$5 -> 122.09909 | I12: ='Balance Sheet'!I$34/Assumptions!$C$5 -> 126.26894 | J12: ='Balance Sheet'!J$34/Assumptions!$C$5 -> 131.87371 | ... L12: ='Balance Sheet'!L$34/Assumptions!$C$5 -> 150.04022
A14: Per occupied bed-day (Rs)
A15: Revenue per occupied bed-day (total, incl. OPD & other) | B15: Rs | C15: ='Revenue Build'!C$43*100000/'Revenue Build'!C$9 -> 30174.252 | D15: ='Revenue Build'!D$43*100000/'Revenue Build'!D$9 -> 32422.663 | E15: ='Revenue Build'!E$43*100000/'Revenue Build'!E$9 -> 35148.495 | F15: ='Revenue Build'!F$43*100000/'Revenue Build'!F$9 -> 37967.248 | G15: ='Revenue Build'!G$43*100000/'Revenue Build'!G$9 -> 40952.544 | H15: ='Revenue Build'!H$43*100000/'Revenue Build'!H$9 -> 44223.933 | I15: ='Revenue Build'!I$43*100000/'Revenue Build'!I$9 -> 47955.633 | J15: ='Revenue Build'!J$43*100000/'Revenue Build'!J$9 -> 51718.53 | ... L15: ='Revenue Build'!L$43*100000/'Revenue Build'!L$9 -> 60239.028
A16: ARPOB — inpatient only (the reported metric) | B16: Rs | C16: ='Revenue Build'!C$14 -> 24088.5 | D16: ='Revenue Build'!D$14 -> 25895.138 | E16: ='Revenue Build'!E$14 -> 27837.273 | F16: ='Revenue Build'!F$14 -> 29925.068 | G16: ='Revenue Build'!G$14 -> 32169.448 | H16: ='Revenue Build'!H$14 -> 34582.157 | I16: ='Revenue Build'!I$14 -> 37175.819 | J16: ='Revenue Build'!J$14 -> 39964.005 | ... L16: ='Revenue Build'!L$14 -> 46183.404
A17: Operating cost per occupied bed-day | B17: Rs | C17: ='Operating Costs'!C$22*100000/'Revenue Build'!C$9 -> 34043.119 | D17: ='Operating Costs'!D$22*100000/'Revenue Build'!D$9 -> 29140.242 | E17: ='Operating Costs'!E$22*100000/'Revenue Build'!E$9 -> 28273.278 | F17: ='Operating Costs'!F$22*100000/'Revenue Build'!F$9 -> 29293.797 | G17: ='Operating Costs'!G$22*100000/'Revenue Build'!G$9 -> 31232.389 | H17: ='Operating Costs'!H$22*100000/'Revenue Build'!H$9 -> 33118.803 | I17: ='Operating Costs'!I$22*100000/'Revenue Build'!I$9 -> 35683.843 | J17: ='Operating Costs'!J$22*100000/'Revenue Build'!J$9 -> 38343.327 | ... L17: ='Operating Costs'!L$22*100000/'Revenue Build'!L$9 -> 44204.665
A18: EBITDA per occupied bed-day | B18: Rs | C18: =C15-C17 -> -3868.8677 | D18: =D15-D17 -> 3282.4211 | E18: =E15-E17 -> 6875.2164 | F18: =F15-F17 -> 8673.4511 | G18: =G15-G17 -> 9720.1551 | H18: =H15-H17 -> 11105.13 | I18: =I15-I17 -> 12271.79 | J18: =J15-J17 -> 13375.203 | ... L18: =L15-L17 -> 16034.363
A20: Per admission
A21: Average revenue per patient (ARPP) | B21: Rs | C21: ='Revenue Build'!C$58 -> 93945.15 | D21: ='Revenue Build'!D$58 -> 100991.04 | E21: ='Revenue Build'!E$58 -> 108565.36 | F21: ='Revenue Build'!F$58 -> 116707.77 | G21: ='Revenue Build'!G$58 -> 125460.85 | H21: ='Revenue Build'!H$58 -> 134870.41 | I21: ='Revenue Build'!I$58 -> 144985.69 | J21: ='Revenue Build'!J$58 -> 155859.62 | ... L21: ='Revenue Build'!L$58 -> 180115.27
A22: Annual admissions | B22: patients | C22: ='Revenue Build'!C$11 -> 2560.6154 | D22: ='Revenue Build'!D$11 -> 4043.0769 | E22: ='Revenue Build'!E$11 -> 5256 | F22: ='Revenue Build'!F$11 -> 5997.2308 | G22: ='Revenue Build'!G$11 -> 6536.3077 | H22: ='Revenue Build'!H$11 -> 6738.4615 | I22: ='Revenue Build'!I$11 -> 6738.4615 | J22: ='Revenue Build'!J$11 -> 6738.4615 | ... L22: ='Revenue Build'!L$11 -> 6738.4615
A23: Admissions per bed per year | B23: nos | C23: =C22/Assumptions!$C$5 -> 25.606154 | D23: =D22/Assumptions!$C$5 -> 40.430769 | E23: =E22/Assumptions!$C$5 -> 52.56 | F23: =F22/Assumptions!$C$5 -> 59.972308 | G23: =G22/Assumptions!$C$5 -> 65.363077 | H23: =H22/Assumptions!$C$5 -> 67.384615 | I23: =I22/Assumptions!$C$5 -> 67.384615 | J23: =J22/Assumptions!$C$5 -> 67.384615 | ... L23: =L22/Assumptions!$C$5 -> 67.384615 | N23: Bed turnover — the physical throughput of the asset
A25: Productivity & asset efficiency
A26: Revenue per employee | B26: Rs Lakh | C26: ='Revenue Build'!C$43/Manpower!C$14 -> 12.822645 | D26: ='Revenue Build'!D$43/Manpower!D$14 -> 18.795608 | E26: ='Revenue Build'!E$43/Manpower!E$14 -> 24.674243 | F26: ='Revenue Build'!F$43/Manpower!F$14 -> 29.404753 | G26: ='Revenue Build'!G$43/Manpower!G$14 -> 33.784656 | H26: ='Revenue Build'!H$43/Manpower!H$14 -> 37.611811 | I26: ='Revenue Build'!I$43/Manpower!I$14 -> 40.785568 | J26: ='Revenue Build'!J$43/Manpower!J$14 -> 43.985856 | ... L26: ='Revenue Build'!L$43/Manpower!L$14 -> 51.232416
A27: Asset turnover (revenue / total assets) | B27: x | C27: ='Revenue Build'!C$43/'Balance Sheet'!C$34 -> 0.26244374 | D27: ='Revenue Build'!D$43/'Balance Sheet'!D$34 -> 0.47154978 | E27: ='Revenue Build'!E$43/'Balance Sheet'!E$34 -> 0.65537318 | F27: ='Revenue Build'!F$43/'Balance Sheet'!F$34 -> 0.79424995 | G27: ='Revenue Build'!G$43/'Balance Sheet'!G$34 -> 0.90369489 | H27: ='Revenue Build'!H$43/'Balance Sheet'!H$34 -> 0.95185391 | I27: ='Revenue Build'!I$43/'Balance Sheet'!I$34 -> 0.99808711 | J27: ='Revenue Build'!J$43/'Balance Sheet'!J$34 -> 1.030655 | ... L27: ='Revenue Build'!L$43/'Balance Sheet'!L$34 -> 1.0551049 | N27: Indian hospitals mature at roughly 0.8-1.0x. Below 0.6x signals over-investment.
A28: Revenue / gross block | B28: x | C28: ='Revenue Build'!C$43/'Capex & Funding'!$C$72 -> 0.28089668 | D28: ='Revenue Build'!D$43/'Capex & Funding'!$C$72 -> 0.47656971 | E28: ='Revenue Build'!E$43/'Capex & Funding'!$C$72 -> 0.67162652 | F28: ='Revenue Build'!F$43/'Capex & Funding'!$C$72 -> 0.82780039 | G28: ='Revenue Build'!G$43/'Capex & Funding'!$C$72 -> 0.97314852 | H28: ='Revenue Build'!H$43/'Capex & Funding'!$C$72 -> 1.0833876 | I28: ='Revenue Build'!I$43/'Capex & Funding'!$C$72 -> 1.174806 | J28: ='Revenue Build'!J$43/'Capex & Funding'!$C$72 -> 1.2669885 | ... L28: ='Revenue Build'!L$43/'Capex & Funding'!$C$72 -> 1.4757217
A29: Return on capital employed (EBIT / capital employed) | B29: % | C29: =IFERROR('P&L'!C$24/('Balance Sheet'!C$10+'Balance Sheet'!C$13+'Balance Sheet'!C$16),0) -> -0.089108315 | D29: =IFERROR('P&L'!D$24/('Balance Sheet'!D$10+'Balance Sheet'!D$13+'Balance Sheet'!D$16),0) -> -0.0092436392 | E29: =IFERROR('P&L'!E$24/('Balance Sheet'!E$10+'Balance Sheet'!E$13+'Balance Sheet'!E$16),0) -> 0.07250903 | F29: =IFERROR('P&L'!F$24/('Balance Sheet'!F$10+'Balance Sheet'!F$13+'Balance Sheet'!F$16),0) -> 0.1300102 | G29: =IFERROR('P&L'!G$24/('Balance Sheet'!G$10+'Balance Sheet'!G$13+'Balance Sheet'!G$16),0) -> 0.16750597 | H29: =IFERROR('P&L'!H$24/('Balance Sheet'!H$10+'Balance Sheet'!H$13+'Balance Sheet'!H$16),0) -> 0.20442452 | I29: =IFERROR('P&L'!I$24/('Balance Sheet'!I$10+'Balance Sheet'!I$13+'Balance Sheet'!I$16),0) -> 0.22586366 | J29: =IFERROR('P&L'!J$24/('Balance Sheet'!J$10+'Balance Sheet'!J$13+'Balance Sheet'!J$16),0) -> 0.23880615 | ... L29: =IFERROR('P&L'!L$24/('Balance Sheet'!L$10+'Balance Sheet'!L$13+'Balance Sheet'!L$16),0) -> 0.25715077
A30: Return on equity (PAT / net worth) | B30: % | C30: =IFERROR('P&L'!C$38/'Balance Sheet'!C$10,0) -> -0.59259762 | D30: =IFERROR('P&L'!D$38/'Balance Sheet'!D$10,0) -> -0.45498972 | E30: =IFERROR('P&L'!E$38/'Balance Sheet'!E$10,0) -> -0.075282899 | F30: =IFERROR('P&L'!F$38/'Balance Sheet'!F$10,0) -> 0.18993204 | G30: =IFERROR('P&L'!G$38/'Balance Sheet'!G$10,0) -> 0.27948635 | H30: =IFERROR('P&L'!H$38/'Balance Sheet'!H$10,0) -> 0.31253402 | I30: =IFERROR('P&L'!I$38/'Balance Sheet'!I$10,0) -> 0.22992342 | J30: =IFERROR('P&L'!J$38/'Balance Sheet'!J$10,0) -> 0.21603416 | ... L30: =IFERROR('P&L'!L$38/'Balance Sheet'!L$10,0) -> 0.19352528
A31: Return on assets (PAT / total assets) | B31: % | C31: =IFERROR('P&L'!C$38/'Balance Sheet'!C$34,0) -> -0.16287034 | D31: =IFERROR('P&L'!D$38/'Balance Sheet'!D$34,0) -> -0.091019672 | E31: =IFERROR('P&L'!E$38/'Balance Sheet'!E$34,0) -> -0.013812332 | F31: =IFERROR('P&L'!F$38/'Balance Sheet'!F$34,0) -> 0.042297839 | G31: =IFERROR('P&L'!G$38/'Balance Sheet'!G$34,0) -> 0.083608313 | H31: =IFERROR('P&L'!H$38/'Balance Sheet'!H$34,0) -> 0.12867041 | I31: =IFERROR('P&L'!I$38/'Balance Sheet'!I$34,0) -> 0.11886296 | J31: =IFERROR('P&L'!J$38/'Balance Sheet'!J$34,0) -> 0.13640396 | ... L31: =IFERROR('P&L'!L$38/'Balance Sheet'!L$34,0) -> 0.16751225
A33: Payer-mix economics (active mix) | C33: Share | D33: Realisation | E33: Debtor days
A34: Cash / self-pay — share of revenue | C34: ='Control Panel'!$E$41 -> 0.4 | D34: ='Control Panel'!$F$41 -> 1 | E34: ='Control Panel'!$G$41 -> 3
A35: Private insurance / TPA — share of revenue | C35: ='Control Panel'!$E$42 -> 0.35 | D35: ='Control Panel'!$F$42 -> 0.94 | E35: ='Control Panel'!$G$42 -> 55
A36: Government schemes — share of revenue | C36: ='Control Panel'!$E$43 -> 0.25 | D36: ='Control Panel'!$F$43 -> 0.72 | E36: ='Control Panel'!$G$43 -> 110

Sheet Ratio Dashboard
A1: RATIO DASHBOARD
A2: Every ratio a lender, auditor or investor will ask for, in one place.
A4: Ratio | B4: Unit | C4: Year 1 | D4: Year 2 | E4: Year 3 | F4: Year 4 | G4: Year 5 | H4: Year 6 | I4: Year 7 | J4: Year 8 | K4: Year 9 | L4: Year 10
A5: Financial year | C5: FY2029 | D5: FY2030 | E5: FY2031 | F5: FY2032 | G5: FY2033 | H5: FY2034 | I5: FY2035 | J5: FY2036 | K5: FY2037 | L5: FY2038
A6: 1. Growth
A7: Revenue growth | B7: % | C7: ='Revenue Build'!C$44 -> 0 | D7: ='Revenue Build'!D$44 -> 0.69660142 | E7: ='Revenue Build'!E$44 -> 0.40929334 | F7: ='Revenue Build'!F$44 -> 0.23253083 | G7: ='Revenue Build'!G$44 -> 0.17558354 | H7: ='Revenue Build'!H$44 -> 0.11328085 | I7: ='Revenue Build'!I$44 -> 0.084381925 | J7: ='Revenue Build'!J$44 -> 0.078466201 | ... L7: ='Revenue Build'!L$44 -> 0.078096164
A8: EBITDA growth | B8: % | C8: =0 -> 0 | D8: =IFERROR('P&L'!D$20/'P&L'!C$20-1,0) -> -2.339609 | E8: =IFERROR('P&L'!E$20/'P&L'!D$20-1,0) -> 1.7229234 | F8: =IFERROR('P&L'!F$20/'P&L'!E$20-1,0) -> 0.43946451 | G8: =IFERROR('P&L'!G$20/'P&L'!F$20-1,0) -> 0.22141427 | H8: =IFERROR('P&L'!H$20/'P&L'!G$20-1,0) -> 0.17781945 | I8: =IFERROR('P&L'!I$20/'P&L'!H$20-1,0) -> 0.10505596 | J8: =IFERROR('P&L'!J$20/'P&L'!I$20-1,0) -> 0.089914547 | K8: =IFERROR('P&L'!K$20/'P&L'!J$20-1,0) -> 0.097560887 | L8: =IFERROR('P&L'!L$20/'P&L'!K$20-1,0) -> 0.092251667
A9: Bed-day growth | B9: % | C9: =0 -> 0 | D9: ='Revenue Build'!D$9/'Revenue Build'!C$9-1 -> 0.57894737 | E9: ='Revenue Build'!E$9/'Revenue Build'!D$9-1 -> 0.3 | F9: ='Revenue Build'!F$9/'Revenue Build'!E$9-1 -> 0.14102564 | G9: ='Revenue Build'!G$9/'Revenue Build'!F$9-1 -> 0.08988764 | H9: ='Revenue Build'!H$9/'Revenue Build'!G$9-1 -> 0.030927835 | I9: ='Revenue Build'!I$9/'Revenue Build'!H$9-1 -> 0 | J9: ='Revenue Build'!J$9/'Revenue Build'!I$9-1 -> 0 | K9: ='Revenue Build'!K$9/'Revenue Build'!J$9-1 -> 0 | L9: ='Revenue Build'!L$9/'Revenue Build'!K$9-1 -> 0
A11: 2. Profitability
A12: Gross contribution margin | B12: % | C12: ='Break-even'!C$9 -> 0.67285864 | D12: ='Break-even'!D$9 -> 0.67282225 | E12: ='Break-even'!E$9 -> 0.67323851 | F12: ='Break-even'!F$9 -> 0.67349953 | G12: ='Break-even'!G$9 -> 0.67373511 | H12: ='Break-even'!H$9 -> 0.67395028 | I12: ='Break-even'!I$9 -> 0.67444555 | J12: ='Break-even'!J$9 -> 0.67458474 | ... L12: ='Break-even'!L$9 -> 0.67501856
A13: EBITDA margin | B13: % | C13: ='P&L'!C$21 -> -0.12821752 | D13: ='P&L'!D$21 -> 0.10123848 | E13: ='P&L'!E$21 -> 0.19560486 | F13: ='P&L'!F$21 -> 0.22844561 | G13: ='P&L'!G$21 -> 0.23735168 | H13: ='P&L'!H$21 -> 0.25111132 | I13: ='P&L'!I$21 -> 0.25589882 | J13: ='P&L'!J$21 -> 0.25861529 | ... L13: ='P&L'!L$21 -> 0.26617898
A14: EBIT margin | B14: % | C14: ='P&L'!C$25 -> -0.33193739 | D14: ='P&L'!D$25 -> -0.018836788 | E14: ='P&L'!E$25 -> 0.10467711 | F14: ='P&L'!F$25 -> 0.15304972 | G14: ='P&L'!G$25 -> 0.17151554 | H14: ='P&L'!H$25 -> 0.19792168 | I14: ='P&L'!I$25 -> 0.20771495 | J14: ='P&L'!J$25 -> 0.21208266 | ... L14: ='P&L'!L$25 -> 0.22265591
A15: PBT margin | B15: % | C15: =IFERROR('P&L'!C$28/'P&L'!C$6,0) -> -0.62059146 | D15: =IFERROR('P&L'!D$28/'P&L'!D$6,0) -> -0.1930224 | E15: =IFERROR('P&L'!E$28/'P&L'!E$6,0) -> -0.021075522 | F15: =IFERROR('P&L'!F$28/'P&L'!F$6,0) -> 0.053255073 | G15: =IFERROR('P&L'!G$28/'P&L'!G$6,0) -> 0.092518298 | H15: =IFERROR('P&L'!H$28/'P&L'!H$6,0) -> 0.13521102 | I15: =IFERROR('P&L'!I$28/'P&L'!I$6,0) -> 0.15914418 | J15: =IFERROR('P&L'!J$28/'P&L'!J$6,0) -> 0.17685865 | ... L15: =IFERROR('P&L'!L$28/'P&L'!L$6,0) -> 0.21216004
A16: PAT margin | B16: % | C16: ='P&L'!C$39 -> -0.62059146 | D16: ='P&L'!D$39 -> -0.1930224 | E16: ='P&L'!E$39 -> -0.021075522 | F16: ='P&L'!F$39 -> 0.053255073 | G16: ='P&L'!G$39 -> 0.092518298 | H16: ='P&L'!H$39 -> 0.13517874 | I16: ='P&L'!I$39 -> 0.11909077 | J16: ='P&L'!J$39 -> 0.13234687 | ... L16: ='P&L'!L$39 -> 0.1587636
A17: Return on equity (ROE) | B17: % | C17: ='Unit Economics'!C$30 -> -0.59259762 | D17: ='Unit Economics'!D$30 -> -0.45498972 | E17: ='Unit Economics'!E$30 -> -0.075282899 | F17: ='Unit Economics'!F$30 -> 0.18993204 | G17: ='Unit Economics'!G$30 -> 0.27948635 | H17: ='Unit Economics'!H$30 -> 0.31253402 | I17: ='Unit Economics'!I$30 -> 0.22992342 | J17: ='Unit Economics'!J$30 -> 0.21603416 | ... L17: ='Unit Economics'!L$30 -> 0.19352528
A18: Return on capital employed (ROCE) | B18: % | C18: ='Unit Economics'!C$29 -> -0.089108315 | D18: ='Unit Economics'!D$29 -> -0.0092436392 | E18: ='Unit Economics'!E$29 -> 0.07250903 | F18: ='Unit Economics'!F$29 -> 0.1300102 | G18: ='Unit Economics'!G$29 -> 0.16750597 | H18: ='Unit Economics'!H$29 -> 0.20442452 | I18: ='Unit Economics'!I$29 -> 0.22586366 | J18: ='Unit Economics'!J$29 -> 0.23880615 | ... L18: ='Unit Economics'!L$29 -> 0.25715077
A19: Return on assets (ROA) | B19: % | C19: ='Unit Economics'!C$31 -> -0.16287034 | D19: ='Unit Economics'!D$31 -> -0.091019672 | E19: ='Unit Economics'!E$31 -> -0.013812332 | F19: ='Unit Economics'!F$31 -> 0.042297839 | G19: ='Unit Economics'!G$31 -> 0.083608313 | H19: ='Unit Economics'!H$31 -> 0.12867041 | I19: ='Unit Economics'!I$31 -> 0.11886296 | J19: ='Unit Economics'!J$31 -> 0.13640396 | ... L19: ='Unit Economics'!L$31 -> 0.16751225
A21: 3. Leverage & solvency
A22: Debt : Equity | B22: x | C22: ='Balance Sheet'!C$41 -> 2.5570671 | D22: ='Balance Sheet'!D$41 -> 3.8034993 | E22: ='Balance Sheet'!E$41 -> 4.1567684 | F22: ='Balance Sheet'!F$41 -> 3.1984829 | G22: ='Balance Sheet'!G$41 -> 2.0931867 | H22: ='Balance Sheet'!H$41 -> 1.2384599 | I22: ='Balance Sheet'!I$41 -> 0.77552379 | J22: ='Balance Sheet'!J$41 -> 0.44966762 | ... L22: ='Balance Sheet'!L$41 -> 0.055439069
A23: Total outside liabilities / tangible net worth | B23: x | C23: ='Balance Sheet'!C$45 -> 2.6384624 | D23: ='Balance Sheet'!D$45 -> 3.9988064 | E23: ='Balance Sheet'!E$45 -> 4.450412 | F23: ='Balance Sheet'!F$45 -> 3.4903486 | G23: ='Balance Sheet'!G$45 -> 2.3428057 | H23: ='Balance Sheet'!H$45 -> 1.4289502 | I23: ='Balance Sheet'!I$45 -> 0.93435712 | J23: ='Balance Sheet'!J$45 -> 0.58378223 | ... L23: ='Balance Sheet'!L$45 -> 0.15529029
A24: Net debt / EBITDA | B24: x | C24: ='Balance Sheet'!C$43 -> 0 | D24: ='Balance Sheet'!D$43 -> 15.123574 | E24: ='Balance Sheet'!E$43 -> 5.8371269 | F24: ='Balance Sheet'!F$43 -> 3.6618394 | G24: ='Balance Sheet'!G$43 -> 2.4735451 | H24: ='Balance Sheet'!H$43 -> 1.4700215 | I24: ='Balance Sheet'!I$43 -> 0.78491104 | J24: ='Balance Sheet'!J$43 -> 0.13372312 | ... L24: ='Balance Sheet'!L$43 -> -1.1168142
A25: Term loan outstanding / gross block | B25: x | C25: ='Balance Sheet'!C$13/'Capex & Funding'!$C$72 -> 0.72283848 | D25: ='Balance Sheet'!D$13/'Capex & Funding'!$C$72 -> 0.72283848 | E25: ='Balance Sheet'!E$13/'Capex & Funding'!$C$72 -> 0.72283848 | F25: ='Balance Sheet'!F$13/'Capex & Funding'!$C$72 -> 0.67946817 | G25: ='Balance Sheet'!G$13/'Capex & Funding'!$C$72 -> 0.60718432 | H25: ='Balance Sheet'!H$13/'Capex & Funding'!$C$72 -> 0.51321532 | I25: ='Balance Sheet'!I$13/'Capex & Funding'!$C$72 -> 0.40478955 | J25: ='Balance Sheet'!J$13/'Capex & Funding'!$C$72 -> 0.28190701 | ... L25: ='Balance Sheet'!L$13/'Capex & Funding'!$C$72 -> 0 | N25: Security cover proxy
A27: 4. Coverage
A28: DSCR — cash basis | B28: x | C28: ='DSCR & Covenants'!C$18 -> -0.80604123 | D28: ='DSCR & Covenants'!D$18 -> 0.36765901 | E28: ='DSCR & Covenants'!E$18 -> 1.4411933 | F28: ='DSCR & Covenants'!F$18 -> 1.4613631 | G28: ='DSCR & Covenants'!G$18 -> 1.5376278 | H28: ='DSCR & Covenants'!H$18 -> 1.6928581 | I28: ='DSCR & Covenants'!I$18 -> 1.5497962 | J28: ='DSCR & Covenants'!J$18 -> 1.6403843 | ... L28: ='DSCR & Covenants'!L$18 -> 1.9913337
A29: DSCR — accrual basis | B29: x | C29: ='DSCR & Covenants'!C$19 -> -0.50695116 | D29: ='DSCR & Covenants'!D$19 -> 0.55261137 | E29: ='DSCR & Covenants'!E$19 -> 1.6037517 | F29: ='DSCR & Covenants'!F$19 -> 1.5316214 | G29: ='DSCR & Covenants'!G$19 -> 1.5784624 | H29: ='DSCR & Covenants'!H$19 -> 1.714097 | I29: ='DSCR & Covenants'!I$19 -> 1.5583463 | J29: ='DSCR & Covenants'!J$19 -> 1.6493154 | ... L29: ='DSCR & Covenants'!L$19 -> 2.0105877
A30: Interest coverage (EBITDA / finance cost) | B30: x | C30: ='DSCR & Covenants'!C$20 -> -0.44419094 | D30: ='DSCR & Covenants'!D$20 -> 0.58121034 | E30: ='DSCR & Covenants'!E$20 -> 1.5554733 | F30: ='DSCR & Covenants'!F$20 -> 2.2891568 | G30: ='DSCR & Covenants'!G$20 -> 3.0045566 | H30: ='DSCR & Covenants'!H$20 -> 4.0042843 | I30: ='DSCR & Covenants'!I$20 -> 5.268576 | J30: ='DSCR & Covenants'!J$20 -> 7.3420176 | ... L30: ='DSCR & Covenants'!L$20 -> 25.360345
A31: Fixed charge coverage | B31: x | C31: =IFERROR('P&L'!C$20/('P&L'!C$27+'Debt Schedule'!C$9),0) -> -0.44419094 | D31: =IFERROR('P&L'!D$20/('P&L'!D$27+'Debt Schedule'!D$9),0) -> 0.58121034 | E31: =IFERROR('P&L'!E$20/('P&L'!E$27+'Debt Schedule'!E$9),0) -> 1.5554733 | F31: =IFERROR('P&L'!F$20/('P&L'!F$27+'Debt Schedule'!F$9),0) -> 1.5010861 | G31: =IFERROR('P&L'!G$20/('P&L'!G$27+'Debt Schedule'!G$9),0) -> 1.5485291 | H31: =IFERROR('P&L'!H$20/('P&L'!H$27+'Debt Schedule'!H$9),0) -> 1.6802708 | I31: =IFERROR('P&L'!I$20/('P&L'!I$27+'Debt Schedule'!I$9),0) -> 1.8166469 | J31: =IFERROR('P&L'!J$20/('P&L'!J$27+'Debt Schedule'!J$9),0) -> 1.9560667 | ... L31: =IFERROR('P&L'!L$20/('P&L'!L$27+'Debt Schedule'!L$9),0) -> 2.4541686
A33: 5. Liquidity
A34: Current ratio | B34: x | C34: ='Balance Sheet'!C$44 -> 2.3924633 | D34: ='Balance Sheet'!D$44 -> 1.4608719 | E34: ='Balance Sheet'!E$44 -> 1.1902451 | F34: ='Balance Sheet'!F$44 -> 1.5223022 | G34: ='Balance Sheet'!G$44 -> 1.8852651 | H34: ='Balance Sheet'!H$44 -> 2.4007091 | I34: ='Balance Sheet'!I$44 -> 2.7319416 | J34: ='Balance Sheet'!J$44 -> 3.1146061 | ... L34: ='Balance Sheet'!L$44 -> 4.103357
A35: Quick ratio | B35: x | C35: =IFERROR(('Balance Sheet'!C$32-'Balance Sheet'!C$29)/'Balance Sheet'!C$19,0) -> 2.3094527 | D35: =IFERROR(('Balance Sheet'!D$32-'Balance Sheet'!D$29)/'Balance Sheet'!D$19,0) -> 1.3731967 | E35: =IFERROR(('Balance Sheet'!E$32-'Balance Sheet'!E$29)/'Balance Sheet'!E$19,0) -> 1.0973848 | F35: =IFERROR(('Balance Sheet'!F$32-'Balance Sheet'!F$29)/'Balance Sheet'!F$19,0) -> 1.4225008 | G35: =IFERROR(('Balance Sheet'!G$32-'Balance Sheet'!G$29)/'Balance Sheet'!G$19,0) -> 1.781351 | H35: =IFERROR(('Balance Sheet'!H$32-'Balance Sheet'!H$29)/'Balance Sheet'!H$19,0) -> 2.2915703 | I35: =IFERROR(('Balance Sheet'!I$32-'Balance Sheet'!I$29)/'Balance Sheet'!I$19,0) -> 2.6189324 | J35: =IFERROR(('Balance Sheet'!J$32-'Balance Sheet'!J$29)/'Balance Sheet'!J$19,0) -> 2.9980308 | ... L35: =IFERROR(('Balance Sheet'!L$32-'Balance Sheet'!L$29)/'Balance Sheet'!L$19,0) -> 3.9797003
A36: Cash & bank balance | B36: Rs Lakh | C36: ='Cash Flow'!C$25 -> 825.74809 | D36: ='Cash Flow'!D$25 -> 421.71471 | E36: ='Cash Flow'!E$25 -> 157.93816 | F36: ='Cash Flow'!F$25 -> 535.40682 | G36: ='Cash Flow'!G$25 -> 1104.5678 | H36: ='Cash Flow'!H$25 -> 1935.3693 | I36: ='Cash Flow'!I$25 -> 2531.0243 | J36: ='Cash Flow'!J$25 -> 3274.1225 | ... L36: ='Cash Flow'!L$25 -> 5426.0657
A38: 6. Efficiency / activity
A39: Debtor days | B39: days | C39: ='Working Capital'!C$7 -> 47.95 | D39: ='Working Capital'!D$7 -> 47.95 | E39: ='Working Capital'!E$7 -> 47.95 | F39: ='Working Capital'!F$7 -> 47.95 | G39: ='Working Capital'!G$7 -> 47.95 | H39: ='Working Capital'!H$7 -> 47.95 | I39: ='Working Capital'!I$7 -> 47.95 | J39: ='Working Capital'!J$7 -> 47.95 | ... L39: ='Working Capital'!L$7 -> 47.95
A40: Inventory days | B40: days | C40: =Assumptions!$C$81 -> 25 | D40: =Assumptions!$C$81 -> 25 | E40: =Assumptions!$C$81 -> 25 | F40: =Assumptions!$C$81 -> 25 | G40: =Assumptions!$C$81 -> 25 | H40: =Assumptions!$C$81 -> 25 | I40: =Assumptions!$C$81 -> 25 | J40: =Assumptions!$C$81 -> 25 | ... L40: =Assumptions!$C$81 -> 25
A41: Creditor days | B41: days | C41: =Assumptions!$C$82 -> 45 | D41: =Assumptions!$C$82 -> 45 | E41: =Assumptions!$C$82 -> 45 | F41: =Assumptions!$C$82 -> 45 | G41: =Assumptions!$C$82 -> 45 | H41: =Assumptions!$C$82 -> 45 | I41: =Assumptions!$C$82 -> 45 | J41: =Assumptions!$C$82 -> 45 | ... L41: =Assumptions!$C$82 -> 45
A42: Cash conversion cycle | B42: days | C42: ='Working Capital'!C$22 -> 27.95 | D42: ='Working Capital'!D$22 -> 27.95 | E42: ='Working Capital'!E$22 -> 27.95 | F42: ='Working Capital'!F$22 -> 27.95 | G42: ='Working Capital'!G$22 -> 27.95 | H42: ='Working Capital'!H$22 -> 27.95 | I42: ='Working Capital'!I$22 -> 27.95 | J42: ='Working Capital'!J$22 -> 27.95 | ... L42: ='Working Capital'!L$22 -> 27.95
A43: Net working capital / revenue | B43: % | C43: ='Working Capital'!C$19/'Revenue Build'!C$43 -> 0.094759638 | D43: ='Working Capital'!D$19/'Revenue Build'!D$43 -> 0.097143957 | E43: ='Working Capital'!E$19/'Revenue Build'!E$43 -> 0.097794169 | F43: ='Working Capital'!F$19/'Revenue Build'!F$43 -> 0.098163754 | G43: ='Working Capital'!G$19/'Revenue Build'!G$43 -> 0.097368661 | H43: ='Working Capital'!H$19/'Revenue Build'!H$43 -> 0.09760817 | I43: ='Working Capital'!I$19/'Revenue Build'!I$43 -> 0.097730941 | J43: ='Working Capital'!J$19/'Revenue Build'!J$43 -> 0.097838695 | ... L43: ='Working Capital'!L$19/'Revenue Build'!L$43 -> 0.098084401
A44: Asset turnover | B44: x | C44: ='Unit Economics'!C$27 -> 0.26244374 | D44: ='Unit Economics'!D$27 -> 0.47154978 | E44: ='Unit Economics'!E$27 -> 0.65537318 | F44: ='Unit Economics'!F$27 -> 0.79424995 | G44: ='Unit Economics'!G$27 -> 0.90369489 | H44: ='Unit Economics'!H$27 -> 0.95185391 | I44: ='Unit Economics'!I$27 -> 0.99808711 | J44: ='Unit Economics'!J$27 -> 1.030655 | ... L44: ='Unit Economics'!L$27 -> 1.0551049
A46: 7. Operating KPIs
A47: Occupancy | B47: % | C47: ='Revenue Build'!C$8 -> 0.2736 | D47: ='Revenue Build'!D$8 -> 0.432 | E47: ='Revenue Build'!E$8 -> 0.5616 | F47: ='Revenue Build'!F$8 -> 0.6408 | G47: ='Revenue Build'!G$8 -> 0.6984 | H47: ='Revenue Build'!H$8 -> 0.72 | I47: ='Revenue Build'!I$8 -> 0.72 | J47: ='Revenue Build'!J$8 -> 0.72 | ... L47: ='Revenue Build'!L$8 -> 0.72
A48: ARPOB (net, inpatient) | B48: Rs | C48: ='Revenue Build'!C$14 -> 24088.5 | D48: ='Revenue Build'!D$14 -> 25895.138 | E48: ='Revenue Build'!E$14 -> 27837.273 | F48: ='Revenue Build'!F$14 -> 29925.068 | G48: ='Revenue Build'!G$14 -> 32169.448 | H48: ='Revenue Build'!H$14 -> 34582.157 | I48: ='Revenue Build'!I$14 -> 37175.819 | J48: ='Revenue Build'!J$14 -> 39964.005 | ... L48: ='Revenue Build'!L$14 -> 46183.404
A49: ALOS | B49: days | C49: ='Revenue Build'!C$10 -> 3.9 | D49: ='Revenue Build'!D$10 -> 3.9 | E49: ='Revenue Build'!E$10 -> 3.9 | F49: ='Revenue Build'!F$10 -> 3.9 | G49: ='Revenue Build'!G$10 -> 3.9 | H49: ='Revenue Build'!H$10 -> 3.9 | I49: ='Revenue Build'!I$10 -> 3.9 | J49: ='Revenue Build'!J$10 -> 3.9 | ... L49: ='Revenue Build'!L$10 -> 3.9
A50: Admissions per bed | B50: nos | C50: ='Unit Economics'!C$23 -> 25.606154 | D50: ='Unit Economics'!D$23 -> 40.430769 | E50: ='Unit Economics'!E$23 -> 52.56 | F50: ='Unit Economics'!F$23 -> 59.972308 | G50: ='Unit Economics'!G$23 -> 65.363077 | H50: ='Unit Economics'!H$23 -> 67.384615 | I50: ='Unit Economics'!I$23 -> 67.384615 | J50: ='Unit Economics'!J$23 -> 67.384615 | ... L50: ='Unit Economics'!L$23 -> 67.384615
A51: OPD footfall per day | B51: nos | C51: ='Revenue Build'!C$18 -> 100 | D51: ='Revenue Build'!D$18 -> 160 | E51: ='Revenue Build'!E$18 -> 220 | F51: ='Revenue Build'!F$18 -> 260 | G51: ='Revenue Build'!G$18 -> 290 | H51: ='Revenue Build'!H$18 -> 310 | I51: ='Revenue Build'!I$18 -> 325 | J51: ='Revenue Build'!J$18 -> 335 | ... L51: ='Revenue Build'!L$18 -> 355
A52: Staff per bed | B52: ratio | C52: =Manpower!C$15 -> 2.35 | D52: =Manpower!D$15 -> 2.72 | E52: =Manpower!E$15 -> 2.92 | F52: =Manpower!F$15 -> 3.02 | G52: =Manpower!G$15 -> 3.09 | H52: =Manpower!H$15 -> 3.09 | I52: =Manpower!I$15 -> 3.09 | J52: =Manpower!J$15 -> 3.09 | ... L52: =Manpower!L$15 -> 3.09
A53: Salary cost as % of revenue | B53: % | C53: =Manpower!C$32 -> 0.49576523 | D53: =Manpower!D$32 -> 0.36326696 | E53: =Manpower!E$32 -> 0.29789434 | F53: =Manpower!F$32 -> 0.27107205 | G53: =Manpower!G$32 -> 0.25342375 | H53: =Manpower!H$32 -> 0.24584781 | I53: =Manpower!I$32 -> 0.24485435 | J53: =Manpower!J$32 -> 0.24520258 | ... L53: =Manpower!L$32 -> 0.24555047
A54: Consumables as % of revenue | B54: % | C54: =Assumptions!$C$66 -> 0.23 | D54: =Assumptions!$C$66 -> 0.23 | E54: =Assumptions!$C$66 -> 0.23 | F54: =Assumptions!$C$66 -> 0.23 | G54: =Assumptions!$C$66 -> 0.23 | H54: =Assumptions!$C$66 -> 0.23 | I54: =Assumptions!$C$66 -> 0.23 | J54: =Assumptions!$C$66 -> 0.23 | ... L54: =Assumptions!$C$66 -> 0.23
A56: 8. DuPont decomposition of ROE
A57: PAT margin | B57: % | C57: ='P&L'!C$39 -> -0.62059146 | D57: ='P&L'!D$39 -> -0.1930224 | E57: ='P&L'!E$39 -> -0.021075522 | F57: ='P&L'!F$39 -> 0.053255073 | G57: ='P&L'!G$39 -> 0.092518298 | H57: ='P&L'!H$39 -> 0.13517874 | I57: ='P&L'!I$39 -> 0.11909077 | J57: ='P&L'!J$39 -> 0.13234687 | ... L57: ='P&L'!L$39 -> 0.1587636
A58: x Asset turnover | B58: x | C58: ='Unit Economics'!C$27 -> 0.26244374 | D58: ='Unit Economics'!D$27 -> 0.47154978 | E58: ='Unit Economics'!E$27 -> 0.65537318 | F58: ='Unit Economics'!F$27 -> 0.79424995 | G58: ='Unit Economics'!G$27 -> 0.90369489 | H58: ='Unit Economics'!H$27 -> 0.95185391 | I58: ='Unit Economics'!I$27 -> 0.99808711 | J58: ='Unit Economics'!J$27 -> 1.030655 | ... L58: ='Unit Economics'!L$27 -> 1.0551049
A59: x Equity multiplier (assets / net worth) | B59: x | C59: =IFERROR('Balance Sheet'!C$34/'Balance Sheet'!C$10,0) -> 3.6384624 | D59: =IFERROR('Balance Sheet'!D$34/'Balance Sheet'!D$10,0) -> 4.9988064 | E59: =IFERROR('Balance Sheet'!E$34/'Balance Sheet'!E$10,0) -> 5.450412 | F59: =IFERROR('Balance Sheet'!F$34/'Balance Sheet'!F$10,0) -> 4.4903486 | G59: =IFERROR('Balance Sheet'!G$34/'Balance Sheet'!G$10,0) -> 3.3428057 | H59: =IFERROR('Balance Sheet'!H$34/'Balance Sheet'!H$10,0) -> 2.4289502 | I59: =IFERROR('Balance Sheet'!I$34/'Balance Sheet'!I$10,0) -> 1.9343571 | J59: =IFERROR('Balance Sheet'!J$34/'Balance Sheet'!J$10,0) -> 1.5837822 | ... L59: =IFERROR('Balance Sheet'!L$34/'Balance Sheet'!L$10,0) -> 1.1552903
A60: = Return on equity | B60: % | C60: =C57*C58*C59 -> -0.59259762 | D60: =D57*D58*D59 -> -0.45498972 | E60: =E57*E58*E59 -> -0.075282899 | F60: =F57*F58*F59 -> 0.18993204 | G60: =G57*G58*G59 -> 0.27948635 | H60: =H57*H58*H59 -> 0.31253402 | I60: =I57*I58*I59 -> 0.22992342 | J60: =J57*J58*J59 -> 0.21603416 | ... L60: =L57*L58*L59 -> 0.19352528 | N60: Cross-check: should equal the ROE reported above

Sheet Valuation (DCF)
A1: DISCOUNTED CASH FLOW VALUATION
A2: Rs Lakh. Enterprise value from unlevered free cash flow, with two independent terminal-value methods.
A4: Particulars | B4: Unit | C4: Year 1 | D4: Year 2 | E4: Year 3 | F4: Year 4 | G4: Year 5 | H4: Year 6 | I4: Year 7 | J4: Year 8 | K4: Year 9 | L4: Year 10
A5: Financial year | C5: FY2029 | D5: FY2030 | E5: FY2031 | F5: FY2032 | G5: FY2033 | H5: FY2034 | I5: FY2035 | J5: FY2036 | K5: FY2037 | L5: FY2038
A6: Free cash flow to firm (FCFF) | B6: Rs Lakh | C6: ='Returns & IRR'!C$13 -> -671.90186 | D6: ='Returns & IRR'!D$13 -> 306.47411 | E6: ='Returns & IRR'!E$13 -> 507.25594 | F6: ='Returns & IRR'!F$13 -> 1428.0238 | G6: ='Returns & IRR'!G$13 -> 1673.6346 | H6: ='Returns & IRR'!H$13 -> 1989.128 | I6: ='Returns & IRR'!I$13 -> 2216.8587 | J6: ='Returns & IRR'!J$13 -> 2419.5811 | ... L6: ='Returns & IRR'!L$13 -> 2895.8212
A7: Discount factor at WACC | B7: x | C7: =1/(1+Assumptions!$C$122)^1 -> 0.88888889 | D7: =1/(1+Assumptions!$C$122)^2 -> 0.79012346 | E7: =1/(1+Assumptions!$C$122)^3 -> 0.70233196 | F7: =1/(1+Assumptions!$C$122)^4 -> 0.62429508 | G7: =1/(1+Assumptions!$C$122)^5 -> 0.55492896 | H7: =1/(1+Assumptions!$C$122)^6 -> 0.49327018 | I7: =1/(1+Assumptions!$C$122)^7 -> 0.43846239 | J7: =1/(1+Assumptions!$C$122)^8 -> 0.38974434 | K7: =1/(1+Assumptions!$C$122)^9 -> 0.34643942 | L7: =1/(1+Assumptions!$C$122)^10 -> 0.30794615
A8: Present value of FCFF | B8: Rs Lakh | C8: =C6*C7 -> -597.2461 | D8: =D6*D7 -> 242.15239 | E8: =E6*E7 -> 356.26206 | F8: =F6*F7 -> 891.50823 | G8: =G6*G7 -> 928.74829 | H8: =H6*H7 -> 981.17754 | I8: =I6*I7 -> 972.00915 | J8: =J6*J7 -> 943.01806 | ... L8: =L6*L7 -> 891.75697
A10: Sum of PV of FCFF, Years 1-10 | C10: =SUM(C8:L8) -> 6527.6586
A12: METHOD 1 — GORDON GROWTH TERMINAL VALUE
A13: Terminal year FCFF (Year 10) | C13: =L6 -> 2895.8212
A14: Terminal growth rate (g) | C14: =Assumptions!$C$123 -> 0.05 | E14: Broadly nominal GDP growth less a margin
A15: WACC | C15: =Assumptions!$C$122 -> 0.125
A16: Terminal value at end of Year 10 | C16: =C13*(1+C14)/(C15-C14) -> 40541.496 | E16: TV = FCFF10 x (1+g) / (WACC - g)
A17: Discount factor for Year 10 | C17: =L7 -> 0.30794615
A18: Present value of terminal value | C18: =C16*C17 -> 12484.598
A19: ENTERPRISE VALUE — Gordon growth | C19: =C10+C18 -> 19012.256
A20: Terminal value as % of enterprise value | C20: =C18/C19 -> 0.6566605 | E20: Above ~75% means the valuation rests almost entirely on an assumption about perpetuity
A22: METHOD 2 — EXIT MULTIPLE TERMINAL VALUE
A23: Year 10 EBITDA | C23: ='P&L'!L$20 -> 4213.8306
A24: Exit EV/EBITDA multiple | C24: =Assumptions!$C$124 -> 13 | E24: Unlisted 100-bed tier-2 asset. Listed Indian hospital chains trade far higher.
A25: Terminal value at end of Year 10 | C25: =C23*C24 -> 54779.798
A26: Present value of terminal value | C26: =C25*L7 -> 16869.228
A27: ENTERPRISE VALUE — exit multiple | C27: =C10+C26 -> 23396.886
A28: Terminal value as % of enterprise value | C28: =C26/C27 -> 0.72100311
A30: VALUATION SUMMARY
A31: Enterprise value — Gordon growth | C31: =C19 -> 19012.256
A32: Enterprise value — exit multiple | C32: =C27 -> 23396.886
A33: Enterprise value — midpoint | C33: =AVERAGE(C19,C27) -> 21204.571
A34: Less: net debt drawn at financial closure | C34: ='Capex & Funding'!$C$32-'Capex & Funding'!$C$17 -> 7404.2557
A35: EQUITY VALUE — midpoint | C35: =C33-C34 -> 13800.315 | E35: What the promoter's stake is worth on a DCF basis today
A36: Cost of project (the price actually paid to build it) | C36: ='Capex & Funding'!$C$25 -> 11077.508
A37: Value created over cost | C37: =C33-C36 -> 10127.063 | E37: EV midpoint less cost of project
A38: Value created as % of cost | C38: =C37/C36 -> 0.91420046 | E38: This should broadly reconcile to project NPV / investment
A39: Cross-check — project NPV from the Returns sheet | C39: ='Returns & IRR'!$C$22 -> 12319.378 | E39: Small differences arise because the NPV uses the exit-multiple terminal value only
A41: WACC build-up
A42: Risk-free rate (10-year G-Sec) | C42: 0.068 | E42: Indicative
A43: Equity risk premium — India | C43: 0.07
A44: Beta — healthcare facilities, relevered | C44: 1.15
A45: Size / illiquidity premium — unlisted single-asset | C45: 0.03 | E45: A 100-bed single-site hospital is not a diversified listed chain
A46: Cost of equity | C46: =C42+C44*C43+C45 -> 0.1785 | E46: Rf + Beta x ERP + size premium
A47: Pre-tax cost of debt | C47: =Assumptions!$C$106 -> 0.1075
A48: Post-tax cost of debt | C48: =C47*(1-Assumptions!$C$98) -> 0.0804444
A49: Target equity weight | C49: 0.4 | E49: Long-run target structure, not the day-one structure
A50: Target debt weight | C50: =1-C49 -> 0.6
A51: WACC — calculated | C51: =C46*C49+C48*C50 -> 0.11966664
A52: WACC — used in the model | C52: =Assumptions!$C$122 -> 0.125

Sheet Scenario Summary
A1: SCENARIO SUMMARY
A2: Values computed by re-running the full model at each scenario. Switch the Control Panel to make any one of these live.
A4: Metric | B4: Base | C4: Optimistic | D4: Pessimistic | E4: Lender Stress
A5: Cost of project (Rs Lakh) | B5: 11077.508 | C5: 10750.874 | D5: 11807.235 | E5: 12594.432
A6: Term debt (Rs Lakh) | B6: 7754.2557 | C6: 7525.6115 | D6: 8265.0647 | E6: 8816.1026
A7: Total promoter contribution (Rs Lakh) | B7: 5103.2525 | C7: 5005.2621 | D7: 5322.1706 | E7: 5558.3297
A9: Revenue — Year 1 (Rs Lakh) | B9: 3013.3215 | C9: 3751.6879 | D9: 2250.975 | E9: 1789.519
A10: Revenue — Year 5 (Rs Lakh) | B10: 10439.459 | C10: 13180.258 | D10: 7393.3951 | E10: 5754.5392
A11: Revenue — Year 10 (Rs Lakh) | B11: 15830.817 | C11: 20303.859 | D11: 10563.085 | E11: 8059.6524
A12: EBITDA — Year 5 (Rs Lakh) | B12: 2477.8231 | C12: 4565.7985 | D12: 203.76428 | E12: -1023.0525
A13: EBITDA — Year 10 (Rs Lakh) | B13: 4213.8306 | C13: 7681.2338 | D13: 165.20072 | E13: -1906.1281
A14: EBITDA margin — Year 5 | B14: 0.23735168 | C14: 0.34641191 | D14: 0.027560312 | E14: -0.17778182
A15: EBITDA margin — Year 10 | B15: 0.26617898 | C15: 0.37831399 | D15: 0.015639438 | E15: -0.23650252
A16: PAT — Year 5 (Rs Lakh) | B16: 965.84095 | C16: 2348.4171 | D16: -1448.8181 | E16: -2854.2746
A17: PAT — Year 10 (Rs Lakh) | B17: 2513.3575 | C17: 5094.9527 | D17: -691.20646 | E17: -2793.4007
A19: First EBITDA-positive year | B19: 2 | C19: 1 | D19: 4 | E19: n.m.
A20: First PAT-positive year | B20: 4 | C20: 2 | D20: n.m. | E20: n.m.
A21: Occupancy — Year 5 | B21: 0.6984 | C21: 0.83226 | D21: 0.546304 | E21: 0.438828
A22: Net ARPOB — Year 5 (Rs) | B22: 32169.448 | C22: 35245.507 | D22: 27026.199 | E22: 24389.987
A23: Cash break-even occupancy — Year 5 | B23: 0.61124593 | C23: 0.55150029 | D23: 0.72074791 | E23: 0.78766044
A25: Minimum DSCR (post-moratorium) | B25: 1.4613631 | C25: 2.5164688 | D25: 0.0372337 | E25: -1.0407671
A26: Average DSCR (post-moratorium) | B26: 1.6620079 | C26: 2.9170551 | D26: 0.086067663 | E26: -0.71709348
A27: Covenant breach years | B27: 0 | C27: 0 | D27: 7 | E27: 7
A28: Minimum cash balance (Rs Lakh) | B28: 157.93816 | C28: 1383.5524 | D28: -15769.45 | E28: -29382.499
A30: Project IRR | B30: 0.22129905 | C30: 0.32910762 | D30: -0.18493296 | E30: n.m.
A31: Project NPV @ 12.5% (Rs Lakh) | B31: 12319.378 | C31: 33578.74 | D31: -13303.722 | E31: -28021.262
A32: Equity IRR | B32: 0.26910963 | C32: 0.43225349 | D32: n.m. | E32: n.m.
A33: Money multiple (MOIC) | B33: 12.317531 | C33: 27.773053 | D33: -6.0423918 | E33: -15.527417
A34: Exit enterprise value (Rs Lakh) | B34: 54779.798 | C34: 99856.04 | D34: 2147.6093 | E34: -24779.666
A36: READING THE SCENARIOS
A37: Base case: the management plan. Occupancy reaches 72% by Year 6, ARPOB grows 7.5% a year, operating margin
A38: settles at about 27%. Minimum DSCR 1.46x with no covenant breach. Project IRR 22.1%, equity IRR 26.9%.
A40: Optimistic: a faster ramp and better case mix. Nothing heroic — it simply assumes the hospital fills the way the
A41: better tier-2 assets actually have. Returns rise sharply because the fixed-cost base is already paid for.
A43: Pessimistic and Lender Stress: this is where the case study earns its keep. Both scenarios produce NO meaningful
A44: IRR — the equity is not returned. DSCR collapses below 1.0 and the cash deficit runs to many multiples of the
A45: promoter facility of Rs 17.7 Cr. The project does not gently underperform in a downside; it fails.
A47: The reason is operating leverage. Fixed costs are roughly 60% of the cost base and depreciation and interest are
A48: fixed absolutely. A 20% shortfall in revenue removes far more than 20% of EBITDA. See the Break-even sheet for
A49: the arithmetic and the Monte Carlo sheet for how likely each outcome is.
A51: This is not an argument against the project. It is an argument for the specific mitigations set out in the
... A55: PAYER-MIX SCENARIOS
A56: Metric | B56: Blended 40/35/25 | C56: Govt-heavy 30/25/45 | D56: Cash-premium 60/35/05
A57: Weighted realisation index | B57: 0.909 | C57: 0.859 | D57: 0.965
A58: Weighted debtor days | B58: 47.95 | C58: 64.15 | D58: 26.55
A59: Revenue — Year 5 (Rs Lakh) | B59: 10439.459 | C59: 9988.3857 | D59: 10944.66
A60: EBITDA — Year 5 (Rs Lakh) | B60: 2477.8231 | C60: 2180.1149 | D60: 2811.2562
A61: EBITDA margin — Year 5 | B61: 0.23735168 | C61: 0.21826499 | D61: 0.25686098
A62: Net working capital — Year 5 (Rs Lakh) | B62: 1016.4761 | C62: 1413.6385 | D62: 426.48585
A63: Minimum DSCR | B63: 1.4613631 | C63: 1.2117058 | D63: 1.7317622
A64: Equity IRR | B64: 0.26910963 | C64: 0.23261911 | D64: 0.30892376
A66: A government-heavy mix costs roughly 3 percentage points of equity IRR and pushes minimum DSCR close to covenant —
A67: PMJAY volume is not free: it is paid for in realisation and in 110-day receivables.

Sheet Sensitivity
A1: TWO-WAY SENSITIVITY ANALYSIS
A2: Each cell is a complete re-run of the 10-year model at that combination. Conditional formatting: green = better.
A4: 1. EQUITY IRR — peak occupancy vs Year-1 ARPOB
A5: The two drivers that matter most. Everything else is second order.
A6: Peak occupancy \ Year-1 gross ARPOB (Rs) | B6: 22500 | C6: 24500 | D6: 26500 | E6: 28500 | F6: 30500
A7: 0.6 | B7: 0.029215467 | C7: 0.11279702 | D7: 0.16861341 | E7: 0.21139693 | F7: 0.24782607
A8: 0.64 | B8: 0.0950345 | C8: 0.15981896 | D8: 0.20679255 | E8: 0.24612385 | F8: 0.28034627
A9: 0.68 | B9: 0.1438293 | C9: 0.19659057 | D9: 0.23979469 | E9: 0.27681515 | F9: 0.30959028
A10: 0.72 | B10: 0.18004481 | C10: 0.22845513 | D10: 0.26910963 | E10: 0.30450174 | F10: 0.33613739
A11: 0.76 | B11: 0.21139693 | C11: 0.25674112 | D11: 0.29553 | E11: 0.32979051 | F11: 0.36081647
A12: 0.8 | B12: 0.23921228 | C12: 0.28234633 | D12: 0.31983667 | E12: 0.35336192 | F12: 0.38374204
A15: 2. MINIMUM DSCR — peak occupancy vs Year-1 ARPOB
A16: Red figures are below the 1.25x covenant. This is the grid a credit committee will look at first.
A17: Peak occupancy \ Year-1 gross ARPOB (Rs) | B17: 22500 | C17: 24500 | D17: 26500 | E17: 28500 | F17: 30500
A18: 0.6 | B18: 0.43117232 | C18: 0.65271873 | D18: 0.87426514 | E18: 1.0958116 | F18: 1.317358
A19: 0.64 | B19: 0.59733213 | C19: 0.8336483 | D19: 1.0699645 | E19: 1.3062806 | F19: 1.5425968
A20: 0.68 | B20: 0.76349194 | C20: 1.0145779 | D20: 1.2656638 | E20: 1.5167497 | F20: 1.6858645
A21: 0.72 | B21: 0.92965175 | C21: 1.1955074 | D21: 1.4613631 | E21: 1.6867914 | F21: 1.856258
A22: 0.76 | B22: 1.0958116 | C22: 1.376437 | D22: 1.6570625 | E22: 1.8143541 | F22: 1.9345093
A23: 0.8 | B23: 1.2619714 | C23: 1.5573666 | D23: 1.7501015 | E23: 1.8941753 | F23: 2.1002768
A26: 3. EQUITY IRR — peak occupancy vs interest rate
A27: Note how flat the columns are: 300bps of interest costs less IRR than 4pp of occupancy.
A28: Peak occupancy \ Interest rate | B28: 0.095 | C28: 0.1025 | D28: 0.1075 | E28: 0.115 | F28: 0.125
A29: 0.6 | B29: 0.17687545 | C29: 0.17192608 | D29: 0.16861341 | E29: 0.16362552 | F29: 0.1569993
A30: 0.64 | B30: 0.21466035 | C30: 0.20993329 | D30: 0.20679255 | E30: 0.20206945 | F30: 0.19573903
A31: 0.68 | B31: 0.24738242 | C31: 0.24282282 | D31: 0.23979469 | E31: 0.23525184 | F31: 0.22913742
A32: 0.72 | B32: 0.27646425 | C32: 0.27204437 | D32: 0.26910963 | E32: 0.26462845 | F32: 0.25868811
A33: 0.76 | B33: 0.30285851 | C33: 0.29845341 | D33: 0.29553 | E33: 0.29116432 | F33: 0.28537859
A34: 0.8 | B34: 0.32697671 | C34: 0.32268507 | D34: 0.31983667 | E34: 0.31558265 | F34: 0.30983944
A37: 4. MINIMUM DSCR — peak occupancy vs interest rate
A38: Peak occupancy \ Interest rate | B38: 0.095 | C38: 0.1025 | D38: 0.1075 | E38: 0.115 | F38: 0.125
A39: 0.6 | B39: 0.94980975 | C39: 0.90310406 | D39: 0.87426514 | E39: 0.83406423 | F39: 0.78548304
A40: 0.64 | B40: 1.1624193 | C40: 1.1052588 | D40: 1.0699645 | E40: 1.0207648 | F40: 0.961309
A41: 0.68 | B41: 1.3750289 | C41: 1.3074136 | D41: 1.2656638 | E41: 1.2074654 | F41: 1.137135
A42: 0.72 | B42: 1.5876384 | C42: 1.5095683 | D42: 1.4613631 | E42: 1.394166 | F42: 1.3129609
A43: 0.76 | B43: 1.6842412 | C43: 1.686778 | D43: 1.6570625 | E43: 1.5808666 | F43: 1.4887869
A44: 0.8 | B44: 1.831529 | C44: 1.7817686 | D44: 1.7501015 | E44: 1.7047009 | F44: 1.6646128
A47: 5. EQUITY IRR — consumables ratio vs capex overrun
A48: Cost discipline in procurement matters more than capex discipline, because it recurs every year.
A49: Consumables % of revenue \ Capex overrun | B49: -0.05 | C49: 0 | D49: 0.05 | E49: 0.1 | F49: 0.15
A50: 0.205 | B50: 0.30031679 | C50: 0.29323791 | D50: 0.28635749 | E50: 0.27966194 | F50: 0.27313886
A51: 0.215 | B51: 0.29084709 | C51: 0.28380353 | D51: 0.27695264 | E51: 0.27026403 | F51: 0.26366428
A52: 0.23 | B52: 0.27611114 | C52: 0.26910963 | D52: 0.26219169 | E52: 0.25545056 | F52: 0.24887474
A53: 0.245 | B53: 0.26056208 | C53: 0.25348762 | D53: 0.24659424 | E53: 0.2398694 | F53: 0.23327005
A54: 0.26 | B54: 0.24406291 | C54: 0.23700419 | D54: 0.23007826 | E54: 0.22326544 | F54: 0.21660573
A57: 6. MINIMUM DSCR — consumables ratio vs capex overrun
A58: Consumables % of revenue \ Capex overrun | B58: -0.05 | C58: 0 | D58: 0.05 | E58: 0.1 | F58: 0.15
A59: 0.205 | B59: 1.707164 | C59: 1.6338436 | D59: 1.5663271 | E59: 1.5041692 | F59: 1.4467564
A60: 0.215 | B60: 1.6353428 | C60: 1.5648514 | D60: 1.5001859 | E60: 1.4406528 | F60: 1.3856643
A61: 0.23 | B61: 1.5271927 | C61: 1.4613631 | D61: 1.4009742 | E61: 1.3453781 | F61: 1.2940262
A62: 0.245 | B62: 1.4190427 | C62: 1.3578748 | D62: 1.3017624 | E62: 1.2501035 | F62: 1.2023881
A63: 0.26 | B63: 1.3108926 | C63: 1.2543865 | D63: 1.2025506 | E63: 1.1548288 | F63: 1.11075
A66: 7. EQUITY IRR — exit multiple vs WACC
A67: WACC does not affect equity IRR (IRR is WACC-independent) — the rows move, the columns do not. A useful sanity check that the model is wired correctly.
A68: Exit EV/EBITDA \ WACC | B68: 0.105 | C68: 0.115 | D68: 0.125 | E68: 0.135 | F68: 0.145
A69: 9 | B69: 0.23116518 | C69: 0.23116518 | D69: 0.23116518 | E69: 0.23116518 | F69: 0.23116518
A70: 11 | B70: 0.25143684 | C70: 0.25143684 | D70: 0.25143684 | E70: 0.25143684 | F70: 0.25143684
A71: 13 | B71: 0.26910963 | C71: 0.26910963 | D71: 0.26910963 | E71: 0.26910963 | F71: 0.26910963
A72: 15 | B72: 0.28480385 | C72: 0.28480385 | D72: 0.28480385 | E72: 0.28480385 | F72: 0.28480385
A73: 17 | B73: 0.29893824 | C73: 0.29893824 | D73: 0.29893824 | E73: 0.29893824 | F73: 0.29893824
A76: 8. PROJECT NPV (Rs Lakh) — exit multiple vs WACC
A77: Here WACC bites hard. NPV is highly sensitive to the discount rate; IRR is not.
A78: Exit EV/EBITDA \ WACC | B78: 0.105 | C78: 0.115 | D78: 0.125 | E78: 0.135 | F78: 0.145
A79: 9 | B79: 10317.716 | C79: 8649.6877 | D79: 7128.8465 | E79: 5740.8068 | F79: 4472.7136
A80: 11 | B80: 13422.878 | C80: 11487.335 | D80: 9724.1123 | E80: 8116.2708 | F80: 6648.6801
A81: 13 | B81: 16528.04 | C81: 14324.982 | D81: 12319.378 | E81: 10491.735 | F81: 8824.6466
A82: 15 | B82: 19633.202 | C82: 17162.629 | D82: 14914.644 | E82: 12867.199 | F82: 11000.613
A83: 17 | B83: 22738.364 | C83: 20000.276 | D83: 17509.91 | E83: 15242.663 | F83: 13176.58
A86: 9. EBITDA MARGIN YEAR 5 — peak occupancy vs consumables ratio
A87: Benchmark: ICRA puts the sector operating margin at 22-24%.
A88: Peak occupancy \ Consumables % of revenue | B88: 0.205 | C88: 0.215 | D88: 0.23 | E88: 0.245 | F88: 0.26
A89: 0.6 | B89: 0.19868214 | C89: 0.18868214 | D89: 0.17368214 | E89: 0.15868214 | F89: 0.14368214
A90: 0.64 | B90: 0.22193484 | C90: 0.21193484 | D90: 0.19693484 | E90: 0.18193484 | F90: 0.16693484
A91: 0.68 | B91: 0.24306541 | C91: 0.23306541 | D91: 0.21806541 | E91: 0.20306541 | F91: 0.18806541
A92: 0.72 | B92: 0.26235168 | C92: 0.25235168 | D92: 0.23735168 | E92: 0.22235168 | F92: 0.20735168
A93: 0.76 | B93: 0.28002501 | C93: 0.27002501 | D93: 0.25502501 | E93: 0.24002501 | F93: 0.22502501
A94: 0.8 | B94: 0.29627962 | C94: 0.28627962 | D94: 0.27127962 | E94: 0.25627962 | F94: 0.24127962
A97: Methodology
A98: Each cell is produced by re-running the complete 10-year model with that pair of inputs and reading the
A99: output — not by interpolating from the base case. Values are pasted because Excel cannot recalculate a
A100: two-way data table without VBA; the underlying code is in fl_analytics.py (function all_grids).
A101: All other inputs are held at base-case values. Grids are therefore ceteris paribus and do not capture
A102: correlation between drivers — which is precisely what the Monte Carlo sheet adds.

Sheet Tornado
A1: TORNADO / SWING ANALYSIS
A2: One driver moved at a time, everything else held at base. Ranked by the size of the swing it causes.
A4: Base-case equity IRR | C4: 0.26910963
A5: Base-case minimum DSCR | C5: 1.4613631
A7: A. IMPACT ON EQUITY IRR
A8: Driver | B8: Low input | C8: High input | D8: IRR at low | E8: IRR at high | F8: Downside vs base | G8: Upside vs base | H8: Total swing
A9: Occupancy ramp speed | B9: 0.85 | C9: 1.12 | D9: 0.18071295 | E9: 0.32353915 | F9: -0.088396682 | G9: 0.054429525 | H9: 0.14282621
A10: ARPOB Year 1 (INR/bed-day) | B10: 23000 | C10: 30000 | D10: 0.19308336 | E10: 0.32850779 | F10: -0.076026266 | G10: 0.059398159 | H10: 0.13542443
A11: ARPOB escalation p.a. | B11: 0.05 | C11: 0.095 | D11: 0.18664777 | E11: 0.32090008 | F11: -0.082461857 | G11: 0.051790452 | H11: 0.13425231
A12: Peak occupancy | B12: 0.64 | C12: 0.8 | D12: 0.20679255 | E12: 0.31983667 | F12: -0.062317084 | G12: 0.050727041 | H12: 0.11304413
A13: Exit EV/EBITDA multiple | B13: 9 | C13: 17 | D13: 0.23116518 | E13: 0.29893824 | F13: -0.037944452 | G13: 0.029828609 | H13: 0.067773061
A14: Salary escalation p.a. | B14: 0.1 | C14: 0.06 | D14: 0.23551126 | E14: 0.294274 | F14: -0.033598375 | G14: 0.025164369 | H14: 0.058762744
A15: Consumables % of revenue | B15: 0.26 | C15: 0.205 | D15: 0.23700419 | E15: 0.29323791 | F15: -0.032105436 | G15: 0.024128284 | H15: 0.05623372
A16: OPD footfall | B16: 0.8 | C16: 1.2 | D16: 0.24005411 | E16: 0.29509317 | F16: -0.029055521 | G16: 0.025983536 | H16: 0.055039057
A17: Consultant payout % | B17: 0.13 | C17: 0.09 | D17: 0.25074916 | E17: 0.28626245 | F17: -0.018360475 | G17: 0.017152825 | H17: 0.035513299
A18: Capex overrun | B18: 0.15 | C18: -0.05 | D18: 0.24887474 | E18: 0.27611114 | F18: -0.020234892 | G18: 0.0070015054 | H18: 0.027236398
A19: Interest rate | B19: 0.125 | C19: 0.095 | D19: 0.25868811 | E19: 0.27646425 | F19: -0.010421523 | G19: 0.0073546172 | H19: 0.01777614
A20: Construction delay (months) | B20: 9 | C20: 0 | D20: 0.26466606 | E20: 0.26910963 | F20: -0.004443567 | G20: 0 | H20: 0.004443567
A22: B. IMPACT ON MINIMUM DSCR
A23: Driver | B23: Low input | C23: High input | D23: DSCR at low | E23: DSCR at high | F23: Downside vs base | G23: Upside vs base | H23: Total swing
A24: Occupancy ramp speed | B24: 0.85 | C24: 1.12 | D24: 0.93297494 | E24: 1.7737911 | F24: -0.52838819 | G24: 0.312428 | H24: 0.84081619
A25: ARPOB Year 1 (INR/bed-day) | B25: 23000 | C25: 30000 | D25: 0.99611567 | E25: 1.8059733 | F25: -0.46524746 | G25: 0.34461017 | H25: 0.80985764
A26: Peak occupancy | B26: 0.64 | C26: 0.8 | D26: 1.0699645 | E26: 1.7501015 | F26: -0.39139866 | G26: 0.28873834 | H26: 0.680137
A27: ARPOB escalation p.a. | B27: 0.05 | C27: 0.095 | D27: 1.2229647 | E27: 1.6528048 | F27: -0.23839847 | G27: 0.19144168 | H27: 0.42984014
A28: Consumables % of revenue | B28: 0.26 | C28: 0.205 | D28: 1.2543865 | E28: 1.6338436 | F28: -0.20697658 | G28: 0.17248049 | H28: 0.37945707
A29: OPD footfall | B29: 0.8 | C29: 1.2 | D29: 1.282585 | E29: 1.6401413 | F29: -0.17877817 | G29: 0.17877817 | H29: 0.35755634
A30: Interest rate | B30: 0.125 | C30: 0.095 | D30: 1.3129609 | E30: 1.5876384 | F30: -0.14840223 | G30: 0.12627531 | H30: 0.27467753
A31: Consultant payout % | B31: 0.13 | C31: 0.09 | D31: 1.3390482 | E31: 1.5836781 | F31: -0.12231497 | G31: 0.12231497 | H31: 0.24462994
A32: Capex overrun | B32: 0.15 | C32: -0.05 | D32: 1.2940262 | E32: 1.5271927 | F32: -0.16733693 | G32: 0.065829618 | H32: 0.23316655
A33: Salary escalation p.a. | B33: 0.1 | C33: 0.06 | D33: 1.3544225 | E33: 1.5644155 | F33: -0.10694064 | G33: 0.10305233 | H33: 0.20999297
A34: Construction delay (months) | B34: 9 | C34: 0 | D34: 1.422263 | E34: 1.4613631 | F34: -0.039100097 | G34: 0 | H34: 0.039100097
